Workbook

Sheet Template
A1: Unidade de Negócio | B1: Diretoria / Divisão | C1: Gerência / Área | D1: Matrícula do Colaborador | E1: Nome do Cargo | F1: Grade | G1: Nível Hierárquico | H1: Estado | I1: Cidade | J1: Gênero | K1: Data Contratação | L1: Data Nascimento | M1: Matrícula do Líder | N1: Salário Mensal | O1: Periculosidade + Insalubridade + Outros Adicionais Fixos Mensais | P1: Número de Salários Pagos ao Ano | Q1: Incentivo de Curto Prazo Anual Alvo | R1: Incentivo de Curto Prazo Anual Pago | S1: Incentivo de Longo Prazo Anual Alvo | T1: Incentivo de Longo Prazo Anual Pago | U1: Remuneração Direta Alvo | V1: Camada Organizacional | W1: Span de Controle | X1: Índice de Eficiência Gerencial | Y1: Cargo Líder | Z1: Nível Hierárquico do Líder | AA1: Camada Organizacional do Líder | AB1: Coluna Auxiliar 1 | AC1: Coluna Auxiliar 2 | AE1: company_id
A2: Business_Unit | B2: Group_Macro | C2: Group_Micro | D2: EmployeeID | E2: EmployeeJobTitle | F2: InternalGrade | G2: EmployeeGroup | H2: Estado | I2: Cidade | J2: Gender | K2: HireDate | L2: BirthDate | M2: ManagerEmployeeID | N2: Monthly_Salary | O2: Monthly_FixedAdditives | P2: SalariesPerYear | Q2: ICP_Target | R2: ICP_Paid | S2: ILP_Target | T2: ILP_Paid | U2: RDA | V2: Layer | W2: Span | X2: IEG | Y2: ManagerJobTitle | Z2: ManagerGroup | AA2: ManagerLayer | AB2: AUX_IEG1 | AC2: AUX_IEG2 | AD2: AUX_IEG3 | AE2: ab28b61c-af05-49c5-9d7a-0a76ad62ccfc
A3: MATRIZ | B3: FINANÇAS | C3: TESOURARIA | D3: 20415 | E3: ANALISTA FINANCEIRO PL | F3: 15 | G3: Operacionais / Profissionais | H3: SP | I3: SÃO PAULO | J3: Masculino | K3: 44634 | L3: 27566 | M3: 23251 | N3: 5460 | P3: 13.33 | Q3: 5460 | R3: 0 | U3: =SUM(Template!$N3:$O3)*Template!$P3+Template!$Q3 -> 78241.8 | V3: =IF(Template!$M3="CONSELHO","N",IF(Template!$AA3="N","N1",IF(Template!$AA3="N1","N2",IF(Template!$AA3="N2","N3",IF(Template!$AA3="N3","N4",IF(Template!$AA3="N4","N5",IF(Template!$AA3="N5","N6",IF(Template!$AA3="N6","N7",IF(Template!$AA3="N7","N8",IF(Template!$AA3="N8","N9",IF(Template!$AA3="N9","N10","NA"))))))))))) -> N3 | W3: =COUNTIF(Template!$M$3:$M$619,Template!$D3) -> 0 | X3: =IF(Template!$F3="","",SUMIF(Template!$M$3:$M$619,Template!$D3,Template!$AC$3:$AC$619)) -> 0 | Y3: =IFERROR(VLOOKUP(Template!$M3,Template!$D$3:$G$619,MATCH("EmployeeJobTitle",Template!$D$2:$G$2,0),FALSE),"NA") -> GERENTE DE CONTROLADORIA | Z3: =IFERROR(VLOOKUP(Template!$M3,Template!$D$3:$G$619,MATCH("EmployeeGroup",Template!$D$2:$G$2,0),FALSE),"NA") -> Gerente | AA3: =IFERROR(VLOOKUP(Template!$M3,Template!$D$3:$V$619,MATCH("Layer",Template!$D$2:$V$2,0),FALSE),"NA") -> N2 | AB3: =VLOOKUP(Template!$M3,Template!$D$3:$F$619,MATCH("InternalGrade",Template!$D$2:$F$2,0),FALSE)-Template!$F3 -> 4 | AC3: =IF(Template!$AB3<=1, 0.8,IF(Template!$AB3=2,0.4,IF(Template!$AB3=3,0.2,IF(Template!$AB3=4,0.1,IF(Template!$AB3>=5,0.05,"erro"))))) -> 0.1 | AD3: =Template!$D3=Template!$M3 -> FALSE | AE3: ab28b61c-af05-49c5-9d7a-0a76ad62ccfc
A4: MATRIZ | B4: PRODUTO E ESTILO | C4: GERENCIA DE ESTILO | D4: 16260 | E4: ASSISTENTE ADMINISTRATIVO | F4: 13 | G4: Operacionais / Profissionais | H4: SP | I4: SÃO PAULO | J4: Feminino | K4: 42999 | L4: 31745 | M4: 23265 | N4: 3657.26 | P4: 13.33 | Q4: 3657.26 | R4: 0 | U4: =SUM(Template!$N4:$O4)*Template!$P4+Template!$Q4 -> 52408.536 | V4: =IF(Template!$M4="CONSELHO","N",IF(Template!$AA4="N","N1",IF(Template!$AA4="N1","N2",IF(Template!$AA4="N2","N3",IF(Template!$AA4="N3","N4",IF(Template!$AA4="N4","N5",IF(Template!$AA4="N5","N6",IF(Template!$AA4="N6","N7",IF(Template!$AA4="N7","N8",IF(Template!$AA4="N8","N9",IF(Template!$AA4="N9","N10","NA"))))))))))) -> N2 | W4: =COUNTIF(Template!$M$3:$M$619,Template!$D4) -> 0 | X4: =IF(Template!$F4="","",SUMIF(Template!$M$3:$M$619,Template!$D4,Template!$AC$3:$AC$619)) -> 0 | Y4: =IFERROR(VLOOKUP(Template!$M4,Template!$D$3:$G$619,MATCH("EmployeeJobTitle",Template!$D$2:$G$2,0),FALSE),"NA") -> DIRETORA DE PRODUTO E ESTILO | Z4: =IFERROR(VLOOKUP(Template!$M4,Template!$D$3:$G$619,MATCH("EmployeeGroup",Template!$D$2:$G$2,0),FALSE),"NA") -> Diretor | AA4: =IFERROR(VLOOKUP(Template!$M4,Template!$D$3:$V$619,MATCH("Layer",Template!$D$2:$V$2,0),FALSE),"NA") -> N1 | AB4: =VLOOKUP(Template!$M4,Template!$D$3:$F$619,MATCH("InternalGrade",Template!$D$2:$F$2,0),FALSE)-Template!$F4 -> 8 | AC4: =IF(Template!$AB4<=1, 0.8,IF(Template!$AB4=2,0.4,IF(Template!$AB4=3,0.2,IF(Template!$AB4=4,0.1,IF(Template!$AB4>=5,0.05,"erro"))))) -> 0.05 | AD4: =Template!$D4=Template!$M4 -> FALSE | AE4: ab28b61c-af05-49c5-9d7a-0a76ad62ccfc
A5: MATRIZ | B5: COMPRAS E LOGÍSTICA | C5: GERÊNCIA DE PLANEJAMENTO E ALOCAÇÃO | D5: 17543 | E5: ANALISTA DE PLANEJAMENTO SR | F5: 16 | G5: Operacionais / Profissionais | H5: SP | I5: SÃO PAULO | J5: Feminino | K5: 43507 | L5: 33608 | M5: 18792 | N5: 6123.6 | P5: 13.33 | Q5: 6123.6 | R5: 0 | U5: =SUM(Template!$N5:$O5)*Template!$P5+Template!$Q5 -> 87751.188 | V5: =IF(Template!$M5="CONSELHO","N",IF(Template!$AA5="N","N1",IF(Template!$AA5="N1","N2",IF(Template!$AA5="N2","N3",IF(Template!$AA5="N3","N4",IF(Template!$AA5="N4","N5",IF(Template!$AA5="N5","N6",IF(Template!$AA5="N6","N7",IF(Template!$AA5="N7","N8",IF(Template!$AA5="N8","N9",IF(Template!$AA5="N9","N10","NA"))))))))))) -> N4 | W5: =COUNTIF(Template!$M$3:$M$619,Template!$D5) -> 0 | X5: =IF(Template!$F5="","",SUMIF(Template!$M$3:$M$619,Template!$D5,Template!$AC$3:$AC$619)) -> 0 | Y5: =IFERROR(VLOOKUP(Template!$M5,Template!$D$3:$G$619,MATCH("EmployeeJobTitle",Template!$D$2:$G$2,0),FALSE),"NA") -> COORDENADOR DE PLANEJAMENTO | Z5: =IFERROR(VLOOKUP(Template!$M5,Template!$D$3:$G$619,MATCH("EmployeeGroup",Template!$D$2:$G$2,0),FALSE),"NA") -> Coordenador | AA5: =IFERROR(VLOOKUP(Template!$M5,Template!$D$3:$V$619,MATCH("Layer",Template!$D$2:$V$2,0),FALSE),"NA") -> N3 | AB5: =VLOOKUP(Template!$M5,Template!$D$3:$F$619,MATCH("InternalGrade",Template!$D$2:$F$2,0),FALSE)-Template!$F5 -> 1 | AC5: =IF(Template!$AB5<=1, 0.8,IF(Template!$AB5=2,0.4,IF(Template!$AB5=3,0.2,IF(Template!$AB5=4,0.1,IF(Template!$AB5>=5,0.05,"erro"))))) -> 0.8 | AD5: =Template!$D5=Template!$M5 -> FALSE | AE5: ab28b61c-af05-49c5-9d7a-0a76ad62ccfc
A6: MATRIZ | B6: PRODUTO E ESTILO | C6: GERENCIA DE ESTILO | D6: 20290 | E6: ASSISTENTE DE ESTILO | F6: 13 | G6: Operacionais / Profissionais | H6: SP | I6: SÃO PAULO | J6: Feminino | K6: 44536 | L6: 35751 | M6: 23265 | N6: 3132 | P6: 13.33 | Q6: 3132 | R6: 0 | U6: =SUM(Template!$N6:$O6)*Template!$P6+Template!$Q6 -> 44881.56 | V6: =IF(Template!$M6="CONSELHO","N",IF(Template!$AA6="N","N1",IF(Template!$AA6="N1","N2",IF(Template!$AA6="N2","N3",IF(Template!$AA6="N3","N4",IF(Template!$AA6="N4","N5",IF(Template!$AA6="N5","N6",IF(Template!$AA6="N6","N7",IF(Template!$AA6="N7","N8",IF(Template!$AA6="N8","N9",IF(Template!$AA6="N9","N10","NA"))))))))))) -> N2 | W6: =COUNTIF(Template!$M$3:$M$619,Template!$D6) -> 0 | X6: =IF(Template!$F6="","",SUMIF(Template!$M$3:$M$619,Template!$D6,Template!$AC$3:$AC$619)) -> 0 | Y6: =IFERROR(VLOOKUP(Template!$M6,Template!$D$3:$G$619,MATCH("EmployeeJobTitle",Template!$D$2:$G$2,0),FALSE),"NA") -> DIRETORA DE PRODUTO E ESTILO | Z6: =IFERROR(VLOOKUP(Template!$M6,Template!$D$3:$G$619,MATCH("EmployeeGroup",Template!$D$2:$G$2,0),FALSE),"NA") -> Diretor | AA6: =IFERROR(VLOOKUP(Template!$M6,Template!$D$3:$V$619,MATCH("Layer",Template!$D$2:$V$2,0),FALSE),"NA") -> N1 | AB6: =VLOOKUP(Template!$M6,Template!$D$3:$F$619,MATCH("InternalGrade",Template!$D$2:$F$2,0),FALSE)-Template!$F6 -> 8 | AC6: =IF(Template!$AB6<=1, 0.8,IF(Template!$AB6=2,0.4,IF(Template!$AB6=3,0.2,IF(Template!$AB6=4,0.1,IF(Template!$AB6>=5,0.05,"erro"))))) -> 0.05 | AD6: =Template!$D6=Template!$M6 -> FALSE | AE6: ab28b61c-af05-49c5-9d7a-0a76ad62ccfc
A7: MATRIZ | B7: MARKETING | C7: GERENCIA DE MARKETING | D7: 24279 | E7: DESIGNER PL | F7: 15 | G7: Operacionais / Profissionais | H7: SP | I7: SÃO PAULO | J7: Feminino | K7: 45180 | L7: 36705 | M7: 24771 | N7: 4700 | P7: 13.33 | Q7: 4700 | R7: 0 | U7: =SUM(Template!$N7:$O7)*Template!$P7+Template!$Q7 -> 67351 | V7: =IF(Template!$M7="CONSELHO","N",IF(Template!$AA7="N","N1",IF(Template!$AA7="N1","N2",IF(Template!$AA7="N2","N3",IF(Template!$AA7="N3","N4",IF(Template!$AA7="N4","N5",IF(Template!$AA7="N5","N6",IF(Template!$AA7="N6","N7",IF(Template!$AA7="N7","N8",IF(Template!$AA7="N8","N9",IF(Template!$AA7="N9","N10","NA"))))))))))) -> N4 | W7: =COUNTIF(Template!$M$3:$M$619,Template!$D7) -> 0 | X7: =IF(Template!$F7="","",SUMIF(Template!$M$3:$M$619,Template!$D7,Template!$AC$3:$AC$619)) -> 0 | Y7: =IFERROR(VLOOKUP(Template!$M7,Template!$D$3:$G$619,MATCH("EmployeeJobTitle",Template!$D$2:$G$2,0),FALSE),"NA") -> COORDENADOR DE MARKETING | Z7: =IFERROR(VLOOKUP(Template!$M7,Template!$D$3:$G$619,MATCH("EmployeeGroup",Template!$D$2:$G$2,0),FALSE),"NA") -> Coordenador | AA7: =IFERROR(VLOOKUP(Template!$M7,Template!$D$3:$V$619,MATCH("Layer",Template!$D$2:$V$2,0),FALSE),"NA") -> N3 | AB7: =VLOOKUP(Template!$M7,Template!$D$3:$F$619,MATCH("InternalGrade",Template!$D$2:$F$2,0),FALSE)-Template!$F7 -> 3 | AC7: =IF(Template!$AB7<=1, 0.8,IF(Template!$AB7=2,0.4,IF(Template!$AB7=3,0.2,IF(Template!$AB7=4,0.1,IF(Template!$AB7>=5,0.05,"erro"))))) -> 0.2 | AD7: =Template!$D7=Template!$M7 -> FALSE | AE7: ab28b61c-af05-49c5-9d7a-0a76ad62ccfc
A8: MATRIZ | B8: PRODUTO E ESTILO | C8: GERENCIA DE ESTILO | D8: 24029 | E8: ESTILISTA SR | F8: 18 | G8: Operacionais / Profissionais | H8: SP | I8: SÃO PAULO | J8: Feminino | K8: 45061 | L8: 32492 | M8: 23265 | N8: 18153.33 | P8: 13.33 | Q8: 18153.33 | R8: 0 | U8: =SUM(Template!$N8:$O8)*Template!$P8+Template!$Q8 -> 260137.22 | V8: =IF(Template!$M8="CONSELHO","N",IF(Template!$AA8="N","N1",IF(Template!$AA8="N1","N2",IF(Template!$AA8="N2","N3",IF(Template!$AA8="N3","N4",IF(Template!$AA8="N4","N5",IF(Template!$AA8="N5","N6",IF(Template!$AA8="N6","N7",IF(Template!$AA8="N7","N8",IF(Template!$AA8="N8","N9",IF(Template!$AA8="N9","N10","NA"))))))))))) -> N2 | W8: =COUNTIF(Template!$M$3:$M$619,Template!$D8) -> 0 | X8: =IF(Template!$F8="","",SUMIF(Template!$M$3:$M$619,Template!$D8,Template!$AC$3:$AC$619)) -> 0 | Y8: =IFERROR(VLOOKUP(Template!$M8,Template!$D$3:$G$619,MATCH("EmployeeJobTitle",Template!$D$2:$G$2,0),FALSE),"NA") -> DIRETORA DE PRODUTO E ESTILO | Z8: =IFERROR(VLOOKUP(Template!$M8,Template!$D$3:$G$619,MATCH("EmployeeGroup",Template!$D$2:$G$2,0),FALSE),"NA") -> Diretor | AA8: =IFERROR(VLOOKUP(Template!$M8,Template!$D$3:$V$619,MATCH("Layer",Template!$D$2:$V$2,0),FALSE),"NA") -> N1 | AB8: =VLOOKUP(Template!$M8,Template!$D$3:$F$619,MATCH("InternalGrade",Template!$D$2:$F$2,0),FALSE)-Template!$F8 -> 3 | AC8: =IF(Template!$AB8<=1, 0.8,IF(Template!$AB8=2,0.4,IF(Template!$AB8=3,0.2,IF(Template!$AB8=4,0.1,IF(Template!$AB8>=5,0.05,"erro"))))) -> 0.2 | AD8: =Template!$D8=Template!$M8 -> FALSE | AE8: ab28b61c-af05-49c5-9d7a-0a76ad62ccfc
A9: MATRIZ | B9: FINANÇAS | C9: TESOURARIA | D9: 20506 | E9: ANALISTA FINANCEIRO JR | F9: 14 | G9: Operacionais / Profissionais | H9: SP | I9: SÃO PAULO | J9: Masculino | K9: 44676 | L9: 32125 | M9: 23251 | N9: 4308 | P9: 13.33 | Q9: 4308 | R9: 0 | U9: =SUM(Template!$N9:$O9)*Template!$P9+Template!$Q9 -> 61733.64 | V9: =IF(Template!$M9="CONSELHO","N",IF(Template!$AA9="N","N1",IF(Template!$AA9="N1","N2",IF(Template!$AA9="N2","N3",IF(Template!$AA9="N3","N4",IF(Template!$AA9="N4","N5",IF(Template!$AA9="N5","N6",IF(Template!$AA9="N6","N7",IF(Template!$AA9="N7","N8",IF(Template!$AA9="N8","N9",IF(Template!$AA9="N9","N10","NA"))))))))))) -> N3 | W9: =COUNTIF(Template!$M$3:$M$619,Template!$D9) -> 0 | X9: =IF(Template!$F9="","",SUMIF(Template!$M$3:$M$619,Template!$D9,Template!$AC$3:$AC$619)) -> 0 | Y9: =IFERROR(VLOOKUP(Template!$M9,Template!$D$3:$G$619,MATCH("EmployeeJobTitle",Template!$D$2:$G$2,0),FALSE),"NA") -> GERENTE DE CONTROLADORIA | Z9: =IFERROR(VLOOKUP(Template!$M9,Template!$D$3:$G$619,MATCH("EmployeeGroup",Template!$D$2:$G$2,0),FALSE),"NA") -> Gerente | AA9: =IFERROR(VLOOKUP(Template!$M9,Template!$D$3:$V$619,MATCH("Layer",Template!$D$2:$V$2,0),FALSE),"NA") -> N2 | AB9: =VLOOKUP(Template!$M9,Template!$D$3:$F$619,MATCH("InternalGrade",Template!$D$2:$F$2,0),FALSE)-Template!$F9 -> 5 | AC9: =IF(Template!$AB9<=1, 0.8,IF(Template!$AB9=2,0.4,IF(Template!$AB9=3,0.2,IF(Template!$AB9=4,0.1,IF(Template!$AB9>=5,0.05,"erro"))))) -> 0.05 | AD9: =Template!$D9=Template!$M9 -> FALSE | AE9: ab28b61c-af05-49c5-9d7a-0a76ad62ccfc
A10: MATRIZ | B10: COMERCIAL | C10: GERENCIA DE OPERAÇÕES | D10: 25396 | E10: ANALISTA DE INTELIGENCIA COMERCIAL PL | F10: 15 | G10: Operacionais / Profissionais | H10: SP | I10: SÃO PAULO | J10: Masculino | K10: 45558 | L10: 36033 | M10: 21878 | N10: 5250 | P10: 13.33 | Q10: 5250 | R10: 0 | U10: =SUM(Template!$N10:$O10)*Template!$P10+Template!$Q10 -> 75232.5 | V10: =IF(Template!$M10="CONSELHO","N",IF(Template!$AA10="N","N1",IF(Template!$AA10="N1","N2",IF(Template!$AA10="N2","N3",IF(Template!$AA10="N3","N4",IF(Template!$AA10="N4","N5",IF(Template!$AA10="N5","N6",IF(Template!$AA10="N6","N7",IF(Template!$AA10="N7","N8",IF(Template!$AA10="N8","N9",IF(Template!$AA10="N9","N10","NA"))))))))))) -> N4 | W10: =COUNTIF(Template!$M$3:$M$619,Template!$D10) -> 0 | X10: =IF(Template!$F10="","",SUMIF(Template!$M$3:$M$619,Template!$D10,Template!$AC$3:$AC$619)) -> 0 | Y10: =IFERROR(VLOOKUP(Template!$M10,Template!$D$3:$G$619,MATCH("EmployeeJobTitle",Template!$D$2:$G$2,0),FALSE),"NA") -> COORDENADOR DE INTELIGÊNCIA COMERCIAL | Z10: =IFERROR(VLOOKUP(Template!$M10,Template!$D$3:$G$619,MATCH("EmployeeGroup",Template!$D$2:$G$2,0),FALSE),"NA") -> Coordenador | AA10: =IFERROR(VLOOKUP(Template!$M10,Template!$D$3:$V$619,MATCH("Layer",Template!$D$2:$V$2,0),FALSE),"NA") -> N3 | AB10: =VLOOKUP(Template!$M10,Template!$D$3:$F$619,MATCH("InternalGrade",Template!$D$2:$F$2,0),FALSE)-Template!$F10 -> 3 | AC10: =IF(Template!$AB10<=1, 0.8,IF(Template!$AB10=2,0.4,IF(Template!$AB10=3,0.2,IF(Template!$AB10=4,0.1,IF(Template!$AB10>=5,0.05,"erro"))))) -> 0.2 | AD10: =Template!$D10=Template!$M10 -> FALSE | AE10: ab28b61c-af05-49c5-9d7a-0a76ad62ccfc
A11: MATRIZ | B11: FINANÇAS | C11: TESOURARIA | D11: 11517 | E11: ANALISTA FINANCEIRO SR | F11: 16 | G11: Operacionais / Profissionais | H11: SP | I11: SÃO PAULO | J11: Feminino | K11: 40980 | L11: 30568 | M11: 23251 | N11: 8802 | P11: 13.33 | Q11: 8802 | R11: 0 | U11: =SUM(Template!$N11:$O11)*Template!$P11+Template!$Q11 -> 126132.66 | V11: =IF(Template!$M11="CONSELHO","N",IF(Template!$AA11="N","N1",IF(Template!$AA11="N1","N2",IF(Template!$AA11="N2","N3",IF(Template!$AA11="N3","N4",IF(Template!$AA11="N4","N5",IF(Template!$AA11="N5","N6",IF(Template!$AA11="N6","N7",IF(Template!$AA11="N7","N8",IF(Template!$AA11="N8","N9",IF(Template!$AA11="N9","N10","NA"))))))))))) -> N3 | W11: =COUNTIF(Template!$M$3:$M$619,Template!$D11) -> 0 | X11: =IF(Template!$F11="","",SUMIF(Template!$M$3:$M$619,Template!$D11,Template!$AC$3:$AC$619)) -> 0 | Y11: =IFERROR(VLOOKUP(Template!$M11,Template!$D$3:$G$619,MATCH("EmployeeJobTitle",Template!$D$2:$G$2,0),FALSE),"NA") -> GERENTE DE CONTROLADORIA | Z11: =IFERROR(VLOOKUP(Template!$M11,Template!$D$3:$G$619,MATCH("EmployeeGroup",Template!$D$2:$G$2,0),FALSE),"NA") -> Gerente | AA11: =IFERROR(VLOOKUP(Template!$M11,Template!$D$3:$V$619,MATCH("Layer",Template!$D$2:$V$2,0),FALSE),"NA") -> N2 | AB11: =VLOOKUP(Template!$M11,Template!$D$3:$F$619,MATCH("InternalGrade",Template!$D$2:$F$2,0),FALSE)-Template!$F11 -> 3 | AC11: =IF(Template!$AB11<=1, 0.8,IF(Template!$AB11=2,0.4,IF(Template!$AB11=3,0.2,IF(Template!$AB11=4,0.1,IF(Template!$AB11>=5,0.05,"erro"))))) -> 0.2 | AD11: =Template!$D11=Template!$M11 -> FALSE | AE11: ab28b61c-af05-49c5-9d7a-0a76ad62ccfc
A12: MATRIZ | B12: COMPRAS E LOGÍSTICA | C12: COMPRAS E MANUTENÇÃO | D12: 16889 | E12: AUXILIAR DE SERVIÇOS GERAIS | G12: Operacionais / Profissionais | H12: SP | I12: SÃO PAULO | J12: Feminino | K12: 43264 | L12: 28361 | M12: 18566 | N12: 2021 | P12: 13.33 | Q12: 2021 | R12: 0 | U12: =SUM(Template!$N12:$O12)*Template!$P12+Template!$Q12 -> 28960.93 | V12: =IF(Template!$M12="CONSELHO","N",IF(Template!$AA12="N","N1",IF(Template!$AA12="N1","N2",IF(Template!$AA12="N2","N3",IF(Template!$AA12="N3","N4",IF(Template!$AA12="N4","N5",IF(Template!$AA12="N5","N6",IF(Template!$AA12="N6","N7",IF(Template!$AA12="N7","N8",IF(Template!$AA12="N8","N9",IF(Template!$AA12="N9","N10","NA"))))))))))) -> N3 | W12: =COUNTIF(Template!$M$3:$M$619,Template!$D12) -> 0 | X12: =IF(Template!$F12="","",SUMIF(Template!$M$3:$M$619,Template!$D12,Template!$AC$3:$AC$619)) | Y12: =IFERROR(VLOOKUP(Template!$M12,Template!$D$3:$G$619,MATCH("EmployeeJobTitle",Template!$D$2:$G$2,0),FALSE),"NA") -> COORDENADOR DE COMPRAS | Z12: =IFERROR(VLOOKUP(Template!$M12,Template!$D$3:$G$619,MATCH("EmployeeGroup",Template!$D$2:$G$2,0),FALSE),"NA") -> Coordenador | AA12: =IFERROR(VLOOKUP(Template!$M12,Template!$D$3:$V$619,MATCH("Layer",Template!$D$2:$V$2,0),FALSE),"NA") -> N2 | AB12: =VLOOKUP(Template!$M12,Template!$D$3:$F$619,MATCH("InternalGrade",Template!$D$2:$F$2,0),FALSE)-Template!$F12 -> 18 | AC12: =IF(Template!$AB12<=1, 0.8,IF(Template!$AB12=2,0.4,IF(Template!$AB12=3,0.2,IF(Template!$AB12=4,0.1,IF(Template!$AB12>=5,0.05,"erro"))))) -> 0.05 | AD12: =Template!$D12=Template!$M12 -> FALSE | AE12: ab28b61c-af05-49c5-9d7a-0a76ad62ccfc
A13: MATRIZ | B13: MARKETING | C13: GERENCIA DE MARKETING | D13: 24771 | E13: COORDENADOR DE MARKETING | F13: 18 | G13: Coordenador | H13: SP | I13: SÃO PAULO | J13: Feminino | K13: 45271 | L13: 33392 | M13: 23263 | N13: 13000 | P13: 13.33 | Q13: 19500 | R13: 0 | U13: =SUM(Template!$N13:$O13)*Template!$P13+Template!$Q13 -> 192790 | V13: =IF(Template!$M13="CONSELHO","N",IF(Template!$AA13="N","N1",IF(Template!$AA13="N1","N2",IF(Template!$AA13="N2","N3",IF(Template!$AA13="N3","N4",IF(Template!$AA13="N4","N5",IF(Template!$AA13="N5","N6",IF(Template!$AA13="N6","N7",IF(Template!$AA13="N7","N8",IF(Template!$AA13="N8","N9",IF(Template!$AA13="N9","N10","NA"))))))))))) -> N3 | W13: =COUNTIF(Template!$M$3:$M$619,Template!$D13) -> 6 | X13: =IF(Template!$F13="","",SUMIF(Template!$M$3:$M$619,Template!$D13,Template!$AC$3:$AC$619)) -> 1.25 | Y13: =IFERROR(VLOOKUP(Template!$M13,Template!$D$3:$G$619,MATCH("EmployeeJobTitle",Template!$D$2:$G$2,0),FALSE),"NA") -> GERENTE DE MARKETING | Z13: =IFERROR(VLOOKUP(Template!$M13,Template!$D$3:$G$619,MATCH("EmployeeGroup",Template!$D$2:$G$2,0),FALSE),"NA") -> Gerente | AA13: =IFERROR(VLOOKUP(Template!$M13,Template!$D$3:$V$619,MATCH("Layer",Template!$D$2:$V$2,0),FALSE),"NA") -> N2 | AB13: =VLOOKUP(Template!$M13,Template!$D$3:$F$619,MATCH("InternalGrade",Template!$D$2:$F$2,0),FALSE)-Template!$F13 -> 1 | AC13: =IF(Template!$AB13<=1, 0.8,IF(Template!$AB13=2,0.4,IF(Template!$AB13=3,0.2,IF(Template!$AB13=4,0.1,IF(Template!$AB13>=5,0.05,"erro"))))) -> 0.8 | AD13: =Template!$D13=Template!$M13 -> FALSE | AE13: ab28b61c-af05-49c5-9d7a-0a76ad62ccfc
A14: MATRIZ | B14: COMERCIAL | C14: GERENCIA DE OPERAÇÕES | D14: 21878 | E14: COORDENADOR DE INTELIGÊNCIA COMERCIAL | F14: 18 | G14: Coordenador | H14: SP | I14: SÃO PAULO | J14: Feminino | K14: 44825 | L14: 32316 | M14: 23260 | N14: 12606 | P14: 13.33 | Q14: 18909 | R14: 0 | U14: =SUM(Template!$N14:$O14)*Template!$P14+Template!$Q14 -> 186946.98 | V14: =IF(Template!$M14="CONSELHO","N",IF(Template!$AA14="N","N1",IF(Template!$AA14="N1","N2",IF(Template!$AA14="N2","N3",IF(Template!$AA14="N3","N4",IF(Template!$AA14="N4","N5",IF(Template!$AA14="N5","N6",IF(Template!$AA14="N6","N7",IF(Template!$AA14="N7","N8",IF(Template!$AA14="N8","N9",IF(Template!$AA14="N9","N10","NA"))))))))))) -> N3 | W14: =COUNTIF(Template!$M$3:$M$619,Template!$D14) -> 2 | X14: =IF(Template!$F14="","",SUMIF(Template!$M$3:$M$619,Template!$D14,Template!$AC$3:$AC$619)) -> 0.4 | Y14: =IFERROR(VLOOKUP(Template!$M14,Template!$D$3:$G$619,MATCH("EmployeeJobTitle",Template!$D$2:$G$2,0),FALSE),"NA") -> GERENTE PLANEJAMENTO ESTRATEGICO | Z14: =IFERROR(VLOOKUP(Template!$M14,Template!$D$3:$G$619,MATCH("EmployeeGroup",Template!$D$2:$G$2,0),FALSE),"NA") -> Gerente | AA14: =IFERROR(VLOOKUP(Template!$M14,Template!$D$3:$V$619,MATCH("Layer",Template!$D$2:$V$2,0),FALSE),"NA") -> N2 | AB14: =VLOOKUP(Template!$M14,Template!$D$3:$F$619,MATCH("InternalGrade",Template!$D$2:$F$2,0),FALSE)-Template!$F14 -> 0 | AC14: =IF(Template!$AB14<=1, 0.8,IF(Template!$AB14=2,0.4,IF(Template!$AB14=3,0.2,IF(Template!$AB14=4,0.1,IF(Template!$AB14>=5,0.05,"erro"))))) -> 0.8 | AD14: =Template!$D14=Template!$M14 -> FALSE | AE14: ab28b61c-af05-49c5-9d7a-0a76ad62ccfc
A15: MATRIZ | B15: MARKETING | C15: GERENCIA DE VISUAL MERCHADISING | D15: 24390 | E15: CONSULTOR DE VISUAL MERCHANDISING | F15: 14 | G15: Operacionais / Profissionais | H15: SP | I15: SÃO PAULO | J15: Feminino | K15: 45222 | L15: 30265 | M15: 23266 | N15: 5000 | P15: 13.33 | Q15: 5000 | R15: 0 | U15: =SUM(Template!$N15:$O15)*Template!$P15+Template!$Q15 -> 71650 | V15: =IF(Template!$M15="CONSELHO","N",IF(Template!$AA15="N","N1",IF(Template!$AA15="N1","N2",IF(Template!$AA15="N2","N3",IF(Template!$AA15="N3","N4",IF(Template!$AA15="N4","N5",IF(Template!$AA15="N5","N6",IF(Template!$AA15="N6","N7",IF(Template!$AA15="N7","N8",IF(Template!$AA15="N8","N9",IF(Template!$AA15="N9","N10","NA"))))))))))) -> N3 | W15: =COUNTIF(Template!$M$3:$M$619,Template!$D15) -> 0 | X15: =IF(Template!$F15="","",SUMIF(Template!$M$3:$M$619,Template!$D15,Template!$AC$3:$AC$619)) -> 0 | Y15: =IFERROR(VLOOKUP(Template!$M15,Template!$D$3:$G$619,MATCH("EmployeeJobTitle",Template!$D$2:$G$2,0),FALSE),"NA") -> GERENTE DE VM | Z15: =IFERROR(VLOOKUP(Template!$M15,Template!$D$3:$G$619,MATCH("EmployeeGroup",Template!$D$2:$G$2,0),FALSE),"NA") -> Gerente | AA15: =IFERROR(VLOOKUP(Template!$M15,Template!$D$3:$V$619,MATCH("Layer",Template!$D$2:$V$2,0),FALSE),"NA") -> N2 | AB15: =VLOOKUP(Template!$M15,Template!$D$3:$F$619,MATCH("InternalGrade",Template!$D$2:$F$2,0),FALSE)-Template!$F15 -> 5 | AC15: =IF(Template!$AB15<=1, 0.8,IF(Template!$AB15=2,0.4,IF(Template!$AB15=3,0.2,IF(Template!$AB15=4,0.1,IF(Template!$AB15>=5,0.05,"erro"))))) -> 0.05 | AD15: =Template!$D15=Template!$M15 -> FALSE | AE15: ab28b61c-af05-49c5-9d7a-0a76ad62ccfc
A16: MATRIZ | B16: TECNOLOGIA DA INFORMAÇÃO | C16: TECNOLOGIA DA INFORMAÇÃO | D16: 24838 | E16: ANALISTA DE TI PL | F16: 15 | G16: Operacionais / Profissionais | H16: SP | I16: SÃO PAULO | J16: Masculino | K16: 45323 | L16: 35061 | M16: 25348 | N16: 4532 | P16: 13.33 | Q16: 4532 | R16: 0 | U16: =SUM(Template!$N16:$O16)*Template!$P16+Template!$Q16 -> 64943.56 | V16: =IF(Template!$M16="CONSELHO","N",IF(Template!$AA16="N","N1",IF(Template!$AA16="N1","N2",IF(Template!$AA16="N2","N3",IF(Template!$AA16="N3","N4",IF(Template!$AA16="N4","N5",IF(Template!$AA16="N5","N6",IF(Template!$AA16="N6","N7",IF(Template!$AA16="N7","N8",IF(Template!$AA16="N8","N9",IF(Template!$AA16="N9","N10","NA"))))))))))) -> N3 | W16: =COUNTIF(Template!$M$3:$M$619,Template!$D16) -> 0 | X16: =IF(Template!$F16="","",SUMIF(Template!$M$3:$M$619,Template!$D16,Template!$AC$3:$AC$619)) -> 0 | Y16: =IFERROR(VLOOKUP(Template!$M16,Template!$D$3:$G$619,MATCH("EmployeeJobTitle",Template!$D$2:$G$2,0),FALSE),"NA") -> COORDENADOR DE TI | Z16: =IFERROR(VLOOKUP(Template!$M16,Template!$D$3:$G$619,MATCH("EmployeeGroup",Template!$D$2:$G$2,0),FALSE),"NA") -> Coordenador | AA16: =IFERROR(VLOOKUP(Template!$M16,Template!$D$3:$V$619,MATCH("Layer",Template!$D$2:$V$2,0),FALSE),"NA") -> N2 | AB16: =VLOOKUP(Template!$M16,Template!$D$3:$F$619,MATCH("InternalGrade",Template!$D$2:$F$2,0),FALSE)-Template!$F16 -> 3 | AC16: =IF(Template!$AB16<=1, 0.8,IF(Template!$AB16=2,0.4,IF(Template!$AB16=3,0.2,IF(Template!$AB16=4,0.1,IF(Template!$AB16>=5,0.05,"erro"))))) -> 0.2 | AD16: =Template!$D16=Template!$M16 -> FALSE | AE16: ab28b61c-af05-49c5-9d7a-0a76ad62ccfc
A17: MATRIZ | B17: COMPRAS E LOGÍSTICA | C17: GERÊNCIA DE PLANEJAMENTO E ALOCAÇÃO | D17: 18792 | E17: COORDENADOR DE PLANEJAMENTO | F17: 17 | G17: Coordenador | H17: SP | I17: SÃO PAULO | J17: Feminino | K17: 44123 | L17: 33722 | M17: 14021 | N17: 11105.53 | P17: 13.33 | Q17: 16658.295 | R17: 0 | U17: =SUM(Template!$N17:$O17)*Template!$P17+Template!$Q17 -> 164695.01 | V17: =IF(Template!$M17="CONSELHO","N",IF(Template!$AA17="N","N1",IF(Template!$AA17="N1","N2",IF(Template!$AA17="N2","N3",IF(Template!$AA17="N3","N4",IF(Template!$AA17="N4","N5",IF(Template!$AA17="N5","N6",IF(Template!$AA17="N6","N7",IF(Template!$AA17="N7","N8",IF(Template!$AA17="N8","N9",IF(Template!$AA17="N9","N10","NA"))))))))))) -> N3 | W17: =COUNTIF(Template!$M$3:$M$619,Template!$D17) -> 5 | X17: =IF(Template!$F17="","",SUMIF(Template!$M$3:$M$619,Template!$D17,Template!$AC$3:$AC$619)) -> 1.8 | Y17: =IFERROR(VLOOKUP(Template!$M17,Template!$D$3:$G$619,MATCH("EmployeeJobTitle",Template!$D$2:$G$2,0),FALSE),"NA") -> GERENTE DE PLANEJAMENTO | Z17: =IFERROR(VLOOKUP(Template!$M17,Template!$D$3:$G$619,MATCH("EmployeeGroup",Template!$D$2:$G$2,0),FALSE),"NA") -> Gerente | AA17: =IFERROR(VLOOKUP(Template!$M17,Template!$D$3:$V$619,MATCH("Layer",Template!$D$2:$V$2,0),FALSE),"NA") -> N2 | AB17: =VLOOKUP(Template!$M17,Template!$D$3:$F$619,MATCH("InternalGrade",Template!$D$2:$F$2,0),FALSE)-Template!$F17 -> 2 | AC17: =IF(Template!$AB17<=1, 0.8,IF(Template!$AB17=2,0.4,IF(Template!$AB17=3,0.2,IF(Template!$AB17=4,0.1,IF(Template!$AB17>=5,0.05,"erro"))))) -> 0.4 | AD17: =Template!$D17=Template!$M17 -> FALSE | AE17: ab28b61c-af05-49c5-9d7a-0a76ad62ccfc
A18: MATRIZ | B18: COMERCIAL | C18: E-COMMERCE | D18: 19402 | E18: ASSISTENTE DE VENDAS E-COMMERCE | F18: 12 | G18: Operacionais / Profissionais | H18: SP | I18: SÃO PAULO | J18: Feminino | K18: 44245 | L18: 33607 | M18: 20450 | N18: 2455 | P18: 13.33 | Q18: 2455 | R18: 0 | U18: =SUM(Template!$N18:$O18)*Template!$P18+Template!$Q18 -> 35180.15 | V18: =IF(Template!$M18="CONSELHO","N",IF(Template!$AA18="N","N1",IF(Template!$AA18="N1","N2",IF(Template!$AA18="N2","N3",IF(Template!$AA18="N3","N4",IF(Template!$AA18="N4","N5",IF(Template!$AA18="N5","N6",IF(Template!$AA18="N6","N7",IF(Template!$AA18="N7","N8",IF(Template!$AA18="N8","N9",IF(Template!$AA18="N9","N10","NA"))))))))))) -> N3 | W18: =COUNTIF(Template!$M$3:$M$619,Template!$D18) -> 0 | X18: =IF(Template!$F18="","",SUMIF(Template!$M$3:$M$619,Template!$D18,Template!$AC$3:$AC$619)) -> 0 | Y18: =IFERROR(VLOOKUP(Template!$M18,Template!$D$3:$G$619,MATCH("EmployeeJobTitle",Template!$D$2:$G$2,0),FALSE),"NA") -> COORDENADOR DE ECOMMERCE | Z18: =IFERROR(VLOOKUP(Template!$M18,Template!$D$3:$G$619,MATCH("EmployeeGroup",Template!$D$2:$G$2,0),FALSE),"NA") -> Coordenador | AA18: =IFERROR(VLOOKUP(Template!$M18,Template!$D$3:$V$619,MATCH("Layer",Template!$D$2:$V$2,0),FALSE),"NA") -> N2 | AB18: =VLOOKUP(Template!$M18,Template!$D$3:$F$619,MATCH("InternalGrade",Template!$D$2:$F$2,0),FALSE)-Template!$F18 -> 6 | AC18: =IF(Template!$AB18<=1, 0.8,IF(Template!$AB18=2,0.4,IF(Template!$AB18=3,0.2,IF(Template!$AB18=4,0.1,IF(Template!$AB18>=5,0.05,"erro"))))) -> 0.05 | AD18: =Template!$D18=Template!$M18 -> FALSE | AE18: ab28b61c-af05-49c5-9d7a-0a76ad62ccfc
A19: MATRIZ | B19: RECURSOS HUMANOS | C19: DEPARTAMENTO PESSOAL | D19: 20505 | E19: COORDENADOR DE RECURSOS HUMANOS | F19: 18 | G19: Coordenador | H19: SP | I19: SÃO PAULO | J19: Masculino | K19: 44676 | L19: 29995 | M19: 23262 | N19: 14085 | P19: 13.33 | Q19: 21127.5 | R19: 0 | U19: =SUM(Template!$N19:$O19)*Template!$P19+Template!$Q19 -> 208880.55 | V19: =IF(Template!$M19="CONSELHO","N",IF(Template!$AA19="N","N1",IF(Template!$AA19="N1","N2",IF(Template!$AA19="N2","N3",IF(Template!$AA19="N3","N4",IF(Template!$AA19="N4","N5",IF(Template!$AA19="N5","N6",IF(Template!$AA19="N6","N7",IF(Template!$AA19="N7","N8",IF(Template!$AA19="N8","N9",IF(Template!$AA19="N9","N10","NA"))))))))))) -> N2 | W19: =COUNTIF(Template!$M$3:$M$619,Template!$D19) -> 1 | X19: =IF(Template!$F19="","",SUMIF(Template!$M$3:$M$619,Template!$D19,Template!$AC$3:$AC$619)) -> 0.05 | Y19: =IFERROR(VLOOKUP(Template!$M19,Template!$D$3:$G$619,MATCH("EmployeeJobTitle",Template!$D$2:$G$2,0),FALSE),"NA") -> DIRETORA DE RECURSOS HUMANOS | Z19: =IFERROR(VLOOKUP(Template!$M19,Template!$D$3:$G$619,MATCH("EmployeeGroup",Template!$D$2:$G$2,0),FALSE),"NA") -> Diretor | AA19: =IFERROR(VLOOKUP(Template!$M19,Template!$D$3:$V$619,MATCH("Layer",Template!$D$2:$V$2,0),FALSE),"NA") -> N1 | AB19: =VLOOKUP(Template!$M19,Template!$D$3:$F$619,MATCH("InternalGrade",Template!$D$2:$F$2,0),FALSE)-Template!$F19 -> 3 | AC19: =IF(Template!$AB19<=1, 0.8,IF(Template!$AB19=2,0.4,IF(Template!$AB19=3,0.2,IF(Template!$AB19=4,0.1,IF(Template!$AB19>=5,0.05,"erro"))))) -> 0.2 | AD19: =Template!$D19=Template!$M19 -> FALSE | AE19: ab28b61c-af05-49c5-9d7a-0a76ad62ccfc
A20: MATRIZ | B20: FINANÇAS | C20: CONTROLADORIA | D20: 11398 | E20: COORDENADOR FISCAL | F20: 18 | G20: Coordenador | H20: SP | I20: SÃO PAULO | J20: Masculino | K20: 40931 | L20: 27620 | M20: 23251 | N20: 13444 | P20: 13.33 | Q20: 20166 | R20: 0 | U20: =SUM(Template!$N20:$O20)*Template!$P20+Template!$Q20 -> 199374.52 | V20: =IF(Template!$M20="CONSELHO","N",IF(Template!$AA20="N","N1",IF(Template!$AA20="N1","N2",IF(Template!$AA20="N2","N3",IF(Template!$AA20="N3","N4",IF(Template!$AA20="N4","N5",IF(Template!$AA20="N5","N6",IF(Template!$AA20="N6","N7",IF(Template!$AA20="N7","N8",IF(Template!$AA20="N8","N9",IF(Template!$AA20="N9","N10","NA"))))))))))) -> N3 | W20: =COUNTIF(Template!$M$3:$M$619,Template!$D20) -> 4 | X20: =IF(Template!$F20="","",SUMIF(Template!$M$3:$M$619,Template!$D20,Template!$AC$3:$AC$619)) -> 1.05 | Y20: =IFERROR(VLOOKUP(Template!$M20,Template!$D$3:$G$619,MATCH("EmployeeJobTitle",Template!$D$2:$G$2,0),FALSE),"NA") -> GERENTE DE CONTROLADORIA | Z20: =IFERROR(VLOOKUP(Template!$M20,Template!$D$3:$G$619,MATCH("EmployeeGroup",Template!$D$2:$G$2,0),FALSE),"NA") -> Gerente | AA20: =IFERROR(VLOOKUP(Template!$M20,Template!$D$3:$V$619,MATCH("Layer",Template!$D$2:$V$2,0),FALSE),"NA") -> N2 | AB20: =VLOOKUP(Template!$M20,Template!$D$3:$F$619,MATCH("InternalGrade",Template!$D$2:$F$2,0),FALSE)-Template!$F20 -> 1 | AC20: =IF(Template!$AB20<=1, 0.8,IF(Template!$AB20=2,0.4,IF(Template!$AB20=3,0.2,IF(Template!$AB20=4,0.1,IF(Template!$AB20>=5,0.05,"erro"))))) -> 0.8 | AD20: =Template!$D20=Template!$M20 -> FALSE | AE20: ab28b61c-af05-49c5-9d7a-0a76ad62ccfc
A21: MATRIZ | B21: FINANÇAS | C21: TESOURARIA | D21: 13338 | E21: ANALISTA FINANCEIRO JR | F21: 14 | G21: Operacionais / Profissionais | H21: SP | I21: SÃO PAULO | J21: Feminino | K21: 41730 | L21: 35335 | M21: 23251 | N21: 4146 | P21: 13.33 | Q21: 4146 | R21: 0 | U21: =SUM(Template!$N21:$O21)*Template!$P21+Template!$Q21 -> 59412.18 | V21: =IF(Template!$M21="CONSELHO","N",IF(Template!$AA21="N","N1",IF(Template!$AA21="N1","N2",IF(Template!$AA21="N2","N3",IF(Template!$AA21="N3","N4",IF(Template!$AA21="N4","N5",IF(Template!$AA21="N5","N6",IF(Template!$AA21="N6","N7",IF(Template!$AA21="N7","N8",IF(Template!$AA21="N8","N9",IF(Template!$AA21="N9","N10","NA"))))))))))) -> N3 | W21: =COUNTIF(Template!$M$3:$M$619,Template!$D21) -> 0 | X21: =IF(Template!$F21="","",SUMIF(Template!$M$3:$M$619,Template!$D21,Template!$AC$3:$AC$619)) -> 0 | Y21: =IFERROR(VLOOKUP(Template!$M21,Template!$D$3:$G$619,MATCH("EmployeeJobTitle",Template!$D$2:$G$2,0),FALSE),"NA") -> GERENTE DE CONTROLADORIA | Z21: =IFERROR(VLOOKUP(Template!$M21,Template!$D$3:$G$619,MATCH("EmployeeGroup",Template!$D$2:$G$2,0),FALSE),"NA") -> Gerente | AA21: =IFERROR(VLOOKUP(Template!$M21,Template!$D$3:$V$619,MATCH("Layer",Template!$D$2:$V$2,0),FALSE),"NA") -> N2 | AB21: =VLOOKUP(Template!$M21,Template!$D$3:$F$619,MATCH("InternalGrade",Template!$D$2:$F$2,0),FALSE)-Template!$F21 -> 5 | AC21: =IF(Template!$AB21<=1, 0.8,IF(Template!$AB21=2,0.4,IF(Template!$AB21=3,0.2,IF(Template!$AB21=4,0.1,IF(Template!$AB21>=5,0.05,"erro"))))) -> 0.05 | AD21: =Template!$D21=Template!$M21 -> FALSE | AE21: ab28b61c-af05-49c5-9d7a-0a76ad62ccfc
A22: MATRIZ | B22: FINANÇAS | C22: JURIDICO | D22: 25223 | E22: ASSISTENTE JURIDICO | F22: 13 | G22: Operacionais / Profissionais | H22: SP | I22: SÃO PAULO | J22: Feminino | K22: 45495 | L22: 37426 | M22: 14066 | N22: 2800 | P22: 13.33 | Q22: 2800 | R22: 0 | U22: =SUM(Template!$N22:$O22)*Template!$P22+Template!$Q22 -> 40124 | V22: =IF(Template!$M22="CONSELHO","N",IF(Template!$AA22="N","N1",IF(Template!$AA22="N1","N2",IF(Template!$AA22="N2","N3",IF(Template!$AA22="N3","N4",IF(Template!$AA22="N4","N5",IF(Template!$AA22="N5","N6",IF(Template!$AA22="N6","N7",IF(Template!$AA22="N7","N8",IF(Template!$AA22="N8","N9",IF(Template!$AA22="N9","N10","NA"))))))))))) -> N3 | W22: =COUNTIF(Template!$M$3:$M$619,Template!$D22) -> 0 | X22: =IF(Template!$F22="","",SUMIF(Template!$M$3:$M$619,Template!$D22,Template!$AC$3:$AC$619)) -> 0 | Y22: =IFERROR(VLOOKUP(Template!$M22,Template!$D$3:$G$619,MATCH("EmployeeJobTitle",Template!$D$2:$G$2,0),FALSE),"NA") -> GERENTE JURIDICO | Z22: =IFERROR(VLOOKUP(Template!$M22,Template!$D$3:$G$619,MATCH("EmployeeGroup",Template!$D$2:$G$2,0),FALSE),"NA") -> Gerente | AA22: =IFERROR(VLOOKUP(Template!$M22,Template!$D$3:$V$619,MATCH("Layer",Template!$D$2:$V$2,0),FALSE),"NA") -> N2 | AB22: =VLOOKUP(Template!$M22,Template!$D$3:$F$619,MATCH("InternalGrade",Template!$D$2:$F$2,0),FALSE)-Template!$F22 -> 6 | AC22: =IF(Template!$AB22<=1, 0.8,IF(Template!$AB22=2,0.4,IF(Template!$AB22=3,0.2,IF(Template!$AB22=4,0.1,IF(Template!$AB22>=5,0.05,"erro"))))) -> 0.05 | AD22: =Template!$D22=Template!$M22 -> FALSE | AE22: ab28b61c-af05-49c5-9d7a-0a76ad62ccfc
A23: MATRIZ | B23: COMERCIAL | C23: ARQUITETURA | D23: 24235 | E23: ANALISTA DE GESTÃO DE PROJETOS JR | F23: 14 | G23: Operacionais / Profissionais | H23: SP | I23: SÃO PAULO | J23: Feminino | K23: 45159 | L23: 34668 | M23: 25195 | N23: 3179 | P23: 13.33 | Q23: 3179 | R23: 0 | U23: =SUM(Template!$N23:$O23)*Template!$P23+Template!$Q23 -> 45555.07 | V23: =IF(Template!$M23="CONSELHO","N",IF(Template!$AA23="N","N1",IF(Template!$AA23="N1","N2",IF(Template!$AA23="N2","N3",IF(Template!$AA23="N3","N4",IF(Template!$AA23="N4","N5",IF(Template!$AA23="N5","N6",IF(Template!$AA23="N6","N7",IF(Template!$AA23="N7","N8",IF(Template!$AA23="N8","N9",IF(Template!$AA23="N9","N10","NA"))))))))))) -> N3 | W23: =COUNTIF(Template!$M$3:$M$619,Template!$D23) -> 0 | X23: =IF(Template!$F23="","",SUMIF(Template!$M$3:$M$619,Template!$D23,Template!$AC$3:$AC$619)) -> 0 | Y23: =IFERROR(VLOOKUP(Template!$M23,Template!$D$3:$G$619,MATCH("EmployeeJobTitle",Template!$D$2:$G$2,0),FALSE),"NA") -> GERENTE DE EXPANSÃO, IMPLANTAÇÃO E PROJETOS | Z23: =IFERROR(VLOOKUP(Template!$M23,Template!$D$3:$G$619,MATCH("EmployeeGroup",Template!$D$2:$G$2,0),FALSE),"NA") -> Gerente | AA23: =IFERROR(VLOOKUP(Template!$M23,Template!$D$3:$V$619,MATCH("Layer",Template!$D$2:$V$2,0),FALSE),"NA") -> N2 | AB23: =VLOOKUP(Template!$M23,Template!$D$3:$F$619,MATCH("InternalGrade",Template!$D$2:$F$2,0),FALSE)-Template!$F23 -> 6 | AC23: =IF(Template!$AB23<=1, 0.8,IF(Template!$AB23=2,0.4,IF(Template!$AB23=3,0.2,IF(Template!$AB23=4,0.1,IF(Template!$AB23>=5,0.05,"erro"))))) -> 0.05 | AD23: =Template!$D23=Template!$M23 -> FALSE | AE23: ab28b61c-af05-49c5-9d7a-0a76ad62ccfc
A24: MATRIZ | B24: FINANÇAS | C24: JURIDICO | D24: 25379 | E24: ADVOGADO JR | F24: 15 | G24: Operacionais / Profissionais | H24: SP | I24: SÃO PAULO | J24: Masculino | K24: 45551 | L24: 36327 | M24: 14066 | N24: 5200 | P24: 13.33 | Q24: 5200 | R24: 0 | U24: =SUM(Template!$N24:$O24)*Template!$P24+Template!$Q24 -> 74516 | V24: =IF(Template!$M24="CONSELHO","N",IF(Template!$AA24="N","N1",IF(Template!$AA24="N1","N2",IF(Template!$AA24="N2","N3",IF(Template!$AA24="N3","N4",IF(Template!$AA24="N4","N5",IF(Template!$AA24="N5","N6",IF(Template!$AA24="N6","N7",IF(Template!$AA24="N7","N8",IF(Template!$AA24="N8","N9",IF(Template!$AA24="N9","N10","NA"))))))))))) -> N3 | W24: =COUNTIF(Template!$M$3:$M$619,Template!$D24) -> 0 | X24: =IF(Template!$F24="","",SUMIF(Template!$M$3:$M$619,Template!$D24,Template!$AC$3:$AC$619)) -> 0 | Y24: =IFERROR(VLOOKUP(Template!$M24,Template!$D$3:$G$619,MATCH("EmployeeJobTitle",Template!$D$2:$G$2,0),FALSE),"NA") -> GERENTE JURIDICO | Z24: =IFERROR(VLOOKUP(Template!$M24,Template!$D$3:$G$619,MATCH("EmployeeGroup",Template!$D$2:$G$2,0),FALSE),"NA") -> Gerente | AA24: =IFERROR(VLOOKUP(Template!$M24,Template!$D$3:$V$619,MATCH("Layer",Template!$D$2:$V$2,0),FALSE),"NA") -> N2 | AB24: =VLOOKUP(Template!$M24,Template!$D$3:$F$619,MATCH("InternalGrade",Template!$D$2:$F$2,0),FALSE)-Template!$F24 -> 4 | AC24: =IF(Template!$AB24<=1, 0.8,IF(Template!$AB24=2,0.4,IF(Template!$AB24=3,0.2,IF(Template!$AB24=4,0.1,IF(Template!$AB24>=5,0.05,"erro"))))) -> 0.1 | AD24: =Template!$D24=Template!$M24 -> FALSE | AE24: ab28b61c-af05-49c5-9d7a-0a76ad62ccfc
... A59: MATRIZ | B59: TECNOLOGIA DA INFORMAÇÃO | C59: TECNOLOGIA DA INFORMAÇÃO | D59: 25208 | E59: ANALISTA DE TI JR | F59: 14 | G59: Operacionais / Profissionais | H59: SP | I59: SÃO PAULO | J59: Feminino | K59: 45488 | L59: 37966 | M59: 25348 | N59: 3464 | P59: 13.33 | Q59: 3464 | R59: 0 | U59: =SUM(Template!$N59:$O59)*Template!$P59+Template!$Q59 -> 49639.12 | V59: =IF(Template!$M59="CONSELHO","N",IF(Template!$AA59="N","N1",IF(Template!$AA59="N1","N2",IF(Template!$AA59="N2","N3",IF(Template!$AA59="N3","N4",IF(Template!$AA59="N4","N5",IF(Template!$AA59="N5","N6",IF(Template!$AA59="N6","N7",IF(Template!$AA59="N7","N8",IF(Template!$AA59="N8","N9",IF(Template!$AA59="N9","N10","NA"))))))))))) -> N3 | W59: =COUNTIF(Template!$M$3:$M$619,Template!$D59) -> 0 | X59: =IF(Template!$F59="","",SUMIF(Template!$M$3:$M$619,Template!$D59,Template!$AC$3:$AC$619)) -> 0 | Y59: =IFERROR(VLOOKUP(Template!$M59,Template!$D$3:$G$619,MATCH("EmployeeJobTitle",Template!$D$2:$G$2,0),FALSE),"NA") -> COORDENADOR DE TI | Z59: =IFERROR(VLOOKUP(Template!$M59,Template!$D$3:$G$619,MATCH("EmployeeGroup",Template!$D$2:$G$2,0),FALSE),"NA") -> Coordenador | AA59: =IFERROR(VLOOKUP(Template!$M59,Template!$D$3:$V$619,MATCH("Layer",Template!$D$2:$V$2,0),FALSE),"NA") -> N2 | AB59: =VLOOKUP(Template!$M59,Template!$D$3:$F$619,MATCH("InternalGrade",Template!$D$2:$F$2,0),FALSE)-Template!$F59 -> 4 | AC59: =IF(Template!$AB59<=1, 0.8,IF(Template!$AB59=2,0.4,IF(Template!$AB59=3,0.2,IF(Template!$AB59=4,0.1,IF(Template!$AB59>=5,0.05,"erro"))))) -> 0.1 | AD59: =Template!$D59=Template!$M59 -> FALSE | AE59: ab28b61c-af05-49c5-9d7a-0a76ad62ccfc
A60: MATRIZ | B60: COMPRAS E LOGÍSTICA | C60: COMPRAS E MANUTENÇÃO | D60: 14514 | E60: ENCARREGADO DE MANUTENÇÃO | G60: Coordenador | H60: SP | I60: SÃO PAULO | J60: Masculino | K60: 42282 | L60: 22778 | M60: 18566 | N60: 5001.26 | P60: 13.33 | Q60: 5001.26 | R60: 0 | U60: =SUM(Template!$N60:$O60)*Template!$P60+Template!$Q60 -> 71668.056 | V60: =IF(Template!$M60="CONSELHO","N",IF(Template!$AA60="N","N1",IF(Template!$AA60="N1","N2",IF(Template!$AA60="N2","N3",IF(Template!$AA60="N3","N4",IF(Template!$AA60="N4","N5",IF(Template!$AA60="N5","N6",IF(Template!$AA60="N6","N7",IF(Template!$AA60="N7","N8",IF(Template!$AA60="N8","N9",IF(Template!$AA60="N9","N10","NA"))))))))))) -> N3 | W60: =COUNTIF(Template!$M$3:$M$619,Template!$D60) -> 0 | X60: =IF(Template!$F60="","",SUMIF(Template!$M$3:$M$619,Template!$D60,Template!$AC$3:$AC$619)) | Y60: =IFERROR(VLOOKUP(Template!$M60,Template!$D$3:$G$619,MATCH("EmployeeJobTitle",Template!$D$2:$G$2,0),FALSE),"NA") -> COORDENADOR DE COMPRAS | Z60: =IFERROR(VLOOKUP(Template!$M60,Template!$D$3:$G$619,MATCH("EmployeeGroup",Template!$D$2:$G$2,0),FALSE),"NA") -> Coordenador | AA60: =IFERROR(VLOOKUP(Template!$M60,Template!$D$3:$V$619,MATCH("Layer",Template!$D$2:$V$2,0),FALSE),"NA") -> N2 | AB60: =VLOOKUP(Template!$M60,Template!$D$3:$F$619,MATCH("InternalGrade",Template!$D$2:$F$2,0),FALSE)-Template!$F60 -> 18 | AC60: =IF(Template!$AB60<=1, 0.8,IF(Template!$AB60=2,0.4,IF(Template!$AB60=3,0.2,IF(Template!$AB60=4,0.1,IF(Template!$AB60>=5,0.05,"erro"))))) -> 0.05 | AD60: =Template!$D60=Template!$M60 -> FALSE | AE60: ab28b61c-af05-49c5-9d7a-0a76ad62ccfc
A61: MATRIZ | B61: TECNOLOGIA DA INFORMAÇÃO | C61: TECNOLOGIA DA INFORMAÇÃO | D61: 25348 | E61: COORDENADOR DE TI | F61: 18 | G61: Coordenador | H61: SP | I61: SÃO PAULO | J61: Feminino | K61: 45537 | L61: 32928 | M61: 24945 | N61: 12000 | P61: 13.33 | Q61: 18000 | R61: 0 | U61: =SUM(Template!$N61:$O61)*Template!$P61+Template!$Q61 -> 177960 | V61: =IF(Template!$M61="CONSELHO","N",IF(Template!$AA61="N","N1",IF(Template!$AA61="N1","N2",IF(Template!$AA61="N2","N3",IF(Template!$AA61="N3","N4",IF(Template!$AA61="N4","N5",IF(Template!$AA61="N5","N6",IF(Template!$AA61="N6","N7",IF(Template!$AA61="N7","N8",IF(Template!$AA61="N8","N9",IF(Template!$AA61="N9","N10","NA"))))))))))) -> N2 | W61: =COUNTIF(Template!$M$3:$M$619,Template!$D61) -> 5 | X61: =IF(Template!$F61="","",SUMIF(Template!$M$3:$M$619,Template!$D61,Template!$AC$3:$AC$619)) -> 0.7 | Y61: =IFERROR(VLOOKUP(Template!$M61,Template!$D$3:$G$619,MATCH("EmployeeJobTitle",Template!$D$2:$G$2,0),FALSE),"NA") -> GERENTE SISTEMA DA INFORMAÇÃO | Z61: =IFERROR(VLOOKUP(Template!$M61,Template!$D$3:$G$619,MATCH("EmployeeGroup",Template!$D$2:$G$2,0),FALSE),"NA") -> Gerente | AA61: =IFERROR(VLOOKUP(Template!$M61,Template!$D$3:$V$619,MATCH("Layer",Template!$D$2:$V$2,0),FALSE),"NA") -> N1 | AB61: =VLOOKUP(Template!$M61,Template!$D$3:$F$619,MATCH("InternalGrade",Template!$D$2:$F$2,0),FALSE)-Template!$F61 -> 1 | AC61: =IF(Template!$AB61<=1, 0.8,IF(Template!$AB61=2,0.4,IF(Template!$AB61=3,0.2,IF(Template!$AB61=4,0.1,IF(Template!$AB61>=5,0.05,"erro"))))) -> 0.8 | AD61: =Template!$D61=Template!$M61 -> FALSE | AE61: ab28b61c-af05-49c5-9d7a-0a76ad62ccfc
A62: MATRIZ | B62: COMPRAS E LOGÍSTICA | C62: COMPRAS E MANUTENÇÃO | D62: 17952 | E62: COORDENADOR DE PRODUTOS | F62: 19 | G62: Coordenador | H62: SP | I62: SÃO PAULO | J62: Feminino | K62: 43763 | L62: 27445 | M62: 23261 | N62: 17666 | P62: 13.33 | Q62: 26499 | R62: 0 | U62: =SUM(Template!$N62:$O62)*Template!$P62+Template!$Q62 -> 261986.78 | V62: =IF(Template!$M62="CONSELHO","N",IF(Template!$AA62="N","N1",IF(Template!$AA62="N1","N2",IF(Template!$AA62="N2","N3",IF(Template!$AA62="N3","N4",IF(Template!$AA62="N4","N5",IF(Template!$AA62="N5","N6",IF(Template!$AA62="N6","N7",IF(Template!$AA62="N7","N8",IF(Template!$AA62="N8","N9",IF(Template!$AA62="N9","N10","NA"))))))))))) -> N2 | W62: =COUNTIF(Template!$M$3:$M$619,Template!$D62) -> 4 | X62: =IF(Template!$F62="","",SUMIF(Template!$M$3:$M$619,Template!$D62,Template!$AC$3:$AC$619)) -> 0.75 | Y62: =IFERROR(VLOOKUP(Template!$M62,Template!$D$3:$G$619,MATCH("EmployeeJobTitle",Template!$D$2:$G$2,0),FALSE),"NA") -> DIRETORA DE COMPRAS E LOGISTICA | Z62: =IFERROR(VLOOKUP(Template!$M62,Template!$D$3:$G$619,MATCH("EmployeeGroup",Template!$D$2:$G$2,0),FALSE),"NA") -> Diretor | AA62: =IFERROR(VLOOKUP(Template!$M62,Template!$D$3:$V$619,MATCH("Layer",Template!$D$2:$V$2,0),FALSE),"NA") -> N1 | AB62: =VLOOKUP(Template!$M62,Template!$D$3:$F$619,MATCH("InternalGrade",Template!$D$2:$F$2,0),FALSE)-Template!$F62 -> 2 | AC62: =IF(Template!$AB62<=1, 0.8,IF(Template!$AB62=2,0.4,IF(Template!$AB62=3,0.2,IF(Template!$AB62=4,0.1,IF(Template!$AB62>=5,0.05,"erro"))))) -> 0.4 | AD62: =Template!$D62=Template!$M62 -> FALSE | AE62: ab28b61c-af05-49c5-9d7a-0a76ad62ccfc
A63: MATRIZ | B63: FINANÇAS | C63: DIRETORIA ADMINISTRATIVA FINANCEIRA | D63: 24782 | E63: ANALISTA PLANEJAMENTO FINANCEIRO SR | F63: 16 | G63: Operacionais / Profissionais | H63: SP | I63: SÃO PAULO | J63: Feminino | K63: 45293 | L63: 37203 | M63: 24245 | N63: 6720 | P63: 13.33 | Q63: 6720 | R63: 0 | U63: =SUM(Template!$N63:$O63)*Template!$P63+Template!$Q63 -> 96297.6 | V63: =IF(Template!$M63="CONSELHO","N",IF(Template!$AA63="N","N1",IF(Template!$AA63="N1","N2",IF(Template!$AA63="N2","N3",IF(Template!$AA63="N3","N4",IF(Template!$AA63="N4","N5",IF(Template!$AA63="N5","N6",IF(Template!$AA63="N6","N7",IF(Template!$AA63="N7","N8",IF(Template!$AA63="N8","N9",IF(Template!$AA63="N9","N10","NA"))))))))))) -> N3 | W63: =COUNTIF(Template!$M$3:$M$619,Template!$D63) -> 0 | X63: =IF(Template!$F63="","",SUMIF(Template!$M$3:$M$619,Template!$D63,Template!$AC$3:$AC$619)) -> 0 | Y63: =IFERROR(VLOOKUP(Template!$M63,Template!$D$3:$G$619,MATCH("EmployeeJobTitle",Template!$D$2:$G$2,0),FALSE),"NA") -> GERENTE DE PLAN. FINANCEIRO | Z63: =IFERROR(VLOOKUP(Template!$M63,Template!$D$3:$G$619,MATCH("EmployeeGroup",Template!$D$2:$G$2,0),FALSE),"NA") -> Gerente | AA63: =IFERROR(VLOOKUP(Template!$M63,Template!$D$3:$V$619,MATCH("Layer",Template!$D$2:$V$2,0),FALSE),"NA") -> N2 | AB63: =VLOOKUP(Template!$M63,Template!$D$3:$F$619,MATCH("InternalGrade",Template!$D$2:$F$2,0),FALSE)-Template!$F63 -> 3 | AC63: =IF(Template!$AB63<=1, 0.8,IF(Template!$AB63=2,0.4,IF(Template!$AB63=3,0.2,IF(Template!$AB63=4,0.1,IF(Template!$AB63>=5,0.05,"erro"))))) -> 0.2 | AD63: =Template!$D63=Template!$M63 -> FALSE | AE63: ab28b61c-af05-49c5-9d7a-0a76ad62ccfc
A64: MATRIZ | B64: COMERCIAL | C64: E-COMMERCE | D64: 20450 | E64: COORDENADOR DE ECOMMERCE | F64: 18 | G64: Coordenador | H64: SP | I64: SÃO PAULO | J64: Feminino | K64: 44655 | L64: 35347 | M64: 24307 | N64: 10690 | P64: 13.33 | Q64: 16035 | R64: 0 | U64: =SUM(Template!$N64:$O64)*Template!$P64+Template!$Q64 -> 158532.7 | V64: =IF(Template!$M64="CONSELHO","N",IF(Template!$AA64="N","N1",IF(Template!$AA64="N1","N2",IF(Template!$AA64="N2","N3",IF(Template!$AA64="N3","N4",IF(Template!$AA64="N4","N5",IF(Template!$AA64="N5","N6",IF(Template!$AA64="N6","N7",IF(Template!$AA64="N7","N8",IF(Template!$AA64="N8","N9",IF(Template!$AA64="N9","N10","NA"))))))))))) -> N2 | W64: =COUNTIF(Template!$M$3:$M$619,Template!$D64) -> 5 | X64: =IF(Template!$F64="","",SUMIF(Template!$M$3:$M$619,Template!$D64,Template!$AC$3:$AC$619)) -> 0.75 | Y64: =IFERROR(VLOOKUP(Template!$M64,Template!$D$3:$G$619,MATCH("EmployeeJobTitle",Template!$D$2:$G$2,0),FALSE),"NA") -> DIRETOR COMERCIAL | Z64: =IFERROR(VLOOKUP(Template!$M64,Template!$D$3:$G$619,MATCH("EmployeeGroup",Template!$D$2:$G$2,0),FALSE),"NA") -> Diretor | AA64: =IFERROR(VLOOKUP(Template!$M64,Template!$D$3:$V$619,MATCH("Layer",Template!$D$2:$V$2,0),FALSE),"NA") -> N1 | AB64: =VLOOKUP(Template!$M64,Template!$D$3:$F$619,MATCH("InternalGrade",Template!$D$2:$F$2,0),FALSE)-Template!$F64 -> 4 | AC64: =IF(Template!$AB64<=1, 0.8,IF(Template!$AB64=2,0.4,IF(Template!$AB64=3,0.2,IF(Template!$AB64=4,0.1,IF(Template!$AB64>=5,0.05,"erro"))))) -> 0.1 | AD64: =Template!$D64=Template!$M64 -> FALSE | AE64: ab28b61c-af05-49c5-9d7a-0a76ad62ccfc
A65: MATRIZ | B65: PRODUTO E ESTILO | C65: GERENCIA DE ESTILO | D65: 17138 | E65: MODELISTA | F65: 15 | G65: Operacionais / Profissionais | H65: SP | I65: SÃO PAULO | J65: Feminino | K65: 43395 | L65: 25039 | M65: 23265 | N65: 6251 | P65: 13.33 | Q65: 6251 | R65: 0 | U65: =SUM(Template!$N65:$O65)*Template!$P65+Template!$Q65 -> 89576.83 | V65: =IF(Template!$M65="CONSELHO","N",IF(Template!$AA65="N","N1",IF(Template!$AA65="N1","N2",IF(Template!$AA65="N2","N3",IF(Template!$AA65="N3","N4",IF(Template!$AA65="N4","N5",IF(Template!$AA65="N5","N6",IF(Template!$AA65="N6","N7",IF(Template!$AA65="N7","N8",IF(Template!$AA65="N8","N9",IF(Template!$AA65="N9","N10","NA"))))))))))) -> N2 | W65: =COUNTIF(Template!$M$3:$M$619,Template!$D65) -> 0 | X65: =IF(Template!$F65="","",SUMIF(Template!$M$3:$M$619,Template!$D65,Template!$AC$3:$AC$619)) -> 0 | Y65: =IFERROR(VLOOKUP(Template!$M65,Template!$D$3:$G$619,MATCH("EmployeeJobTitle",Template!$D$2:$G$2,0),FALSE),"NA") -> DIRETORA DE PRODUTO E ESTILO | Z65: =IFERROR(VLOOKUP(Template!$M65,Template!$D$3:$G$619,MATCH("EmployeeGroup",Template!$D$2:$G$2,0),FALSE),"NA") -> Diretor | AA65: =IFERROR(VLOOKUP(Template!$M65,Template!$D$3:$V$619,MATCH("Layer",Template!$D$2:$V$2,0),FALSE),"NA") -> N1 | AB65: =VLOOKUP(Template!$M65,Template!$D$3:$F$619,MATCH("InternalGrade",Template!$D$2:$F$2,0),FALSE)-Template!$F65 -> 6 | AC65: =IF(Template!$AB65<=1, 0.8,IF(Template!$AB65=2,0.4,IF(Template!$AB65=3,0.2,IF(Template!$AB65=4,0.1,IF(Template!$AB65>=5,0.05,"erro"))))) -> 0.05 | AD65: =Template!$D65=Template!$M65 -> FALSE | AE65: ab28b61c-af05-49c5-9d7a-0a76ad62ccfc
A66: MATRIZ | B66: COMPRAS E LOGÍSTICA | C66: COMPRAS E MANUTENÇÃO | D66: 23893 | E66: COMPRADOR PL | F66: 16 | G66: Operacionais / Profissionais | H66: SP | I66: SÃO PAULO | J66: Feminino | K66: 44998 | L66: 32095 | M66: 17952 | N66: 6868 | P66: 13.33 | Q66: 6868 | R66: 0 | U66: =SUM(Template!$N66:$O66)*Template!$P66+Template!$Q66 -> 98418.44 | V66: =IF(Template!$M66="CONSELHO","N",IF(Template!$AA66="N","N1",IF(Template!$AA66="N1","N2",IF(Template!$AA66="N2","N3",IF(Template!$AA66="N3","N4",IF(Template!$AA66="N4","N5",IF(Template!$AA66="N5","N6",IF(Template!$AA66="N6","N7",IF(Template!$AA66="N7","N8",IF(Template!$AA66="N8","N9",IF(Template!$AA66="N9","N10","NA"))))))))))) -> N3 | W66: =COUNTIF(Template!$M$3:$M$619,Template!$D66) -> 0 | X66: =IF(Template!$F66="","",SUMIF(Template!$M$3:$M$619,Template!$D66,Template!$AC$3:$AC$619)) -> 0 | Y66: =IFERROR(VLOOKUP(Template!$M66,Template!$D$3:$G$619,MATCH("EmployeeJobTitle",Template!$D$2:$G$2,0),FALSE),"NA") -> COORDENADOR DE PRODUTOS | Z66: =IFERROR(VLOOKUP(Template!$M66,Template!$D$3:$G$619,MATCH("EmployeeGroup",Template!$D$2:$G$2,0),FALSE),"NA") -> Coordenador | AA66: =IFERROR(VLOOKUP(Template!$M66,Template!$D$3:$V$619,MATCH("Layer",Template!$D$2:$V$2,0),FALSE),"NA") -> N2 | AB66: =VLOOKUP(Template!$M66,Template!$D$3:$F$619,MATCH("InternalGrade",Template!$D$2:$F$2,0),FALSE)-Template!$F66 -> 3 | AC66: =IF(Template!$AB66<=1, 0.8,IF(Template!$AB66=2,0.4,IF(Template!$AB66=3,0.2,IF(Template!$AB66=4,0.1,IF(Template!$AB66>=5,0.05,"erro"))))) -> 0.2 | AD66: =Template!$D66=Template!$M66 -> FALSE | AE66: ab28b61c-af05-49c5-9d7a-0a76ad62ccfc
A67: MATRIZ | B67: COMPRAS E LOGÍSTICA | C67: COMPRAS E MANUTENÇÃO | D67: 12629 | E67: COMPRADOR SR | F67: 17 | G67: Operacionais / Profissionais | H67: SP | I67: SÃO PAULO | J67: Feminino | K67: 41428 | L67: 33294 | M67: 17952 | N67: 12015.44 | P67: 13.33 | Q67: 12015.44 | R67: 0 | U67: =SUM(Template!$N67:$O67)*Template!$P67+Template!$Q67 -> 172181.26 | V67: =IF(Template!$M67="CONSELHO","N",IF(Template!$AA67="N","N1",IF(Template!$AA67="N1","N2",IF(Template!$AA67="N2","N3",IF(Template!$AA67="N3","N4",IF(Template!$AA67="N4","N5",IF(Template!$AA67="N5","N6",IF(Template!$AA67="N6","N7",IF(Template!$AA67="N7","N8",IF(Template!$AA67="N8","N9",IF(Template!$AA67="N9","N10","NA"))))))))))) -> N3 | W67: =COUNTIF(Template!$M$3:$M$619,Template!$D67) -> 0 | X67: =IF(Template!$F67="","",SUMIF(Template!$M$3:$M$619,Template!$D67,Template!$AC$3:$AC$619)) -> 0 | Y67: =IFERROR(VLOOKUP(Template!$M67,Template!$D$3:$G$619,MATCH("EmployeeJobTitle",Template!$D$2:$G$2,0),FALSE),"NA") -> COORDENADOR DE PRODUTOS | Z67: =IFERROR(VLOOKUP(Template!$M67,Template!$D$3:$G$619,MATCH("EmployeeGroup",Template!$D$2:$G$2,0),FALSE),"NA") -> Coordenador | AA67: =IFERROR(VLOOKUP(Template!$M67,Template!$D$3:$V$619,MATCH("Layer",Template!$D$2:$V$2,0),FALSE),"NA") -> N2 | AB67: =VLOOKUP(Template!$M67,Template!$D$3:$F$619,MATCH("InternalGrade",Template!$D$2:$F$2,0),FALSE)-Template!$F67 -> 2 | AC67: =IF(Template!$AB67<=1, 0.8,IF(Template!$AB67=2,0.4,IF(Template!$AB67=3,0.2,IF(Template!$AB67=4,0.1,IF(Template!$AB67>=5,0.05,"erro"))))) -> 0.4 | AD67: =Template!$D67=Template!$M67 -> FALSE | AE67: ab28b61c-af05-49c5-9d7a-0a76ad62ccfc
A68: MATRIZ | B68: FINANÇAS | C68: CONTROLADORIA | D68: 12070 | E68: ANALISTA CONTÁBIL PL | F68: 15 | G68: Operacionais / Profissionais | H68: SP | I68: SÃO PAULO | J68: Masculino | K68: 41199 | L68: 30221 | M68: 19643 | N68: 5775 | P68: 13.33 | Q68: 5775 | R68: 0 | U68: =SUM(Template!$N68:$O68)*Template!$P68+Template!$Q68 -> 82755.75 | V68: =IF(Template!$M68="CONSELHO","N",IF(Template!$AA68="N","N1",IF(Template!$AA68="N1","N2",IF(Template!$AA68="N2","N3",IF(Template!$AA68="N3","N4",IF(Template!$AA68="N4","N5",IF(Template!$AA68="N5","N6",IF(Template!$AA68="N6","N7",IF(Template!$AA68="N7","N8",IF(Template!$AA68="N8","N9",IF(Template!$AA68="N9","N10","NA"))))))))))) -> N4 | W68: =COUNTIF(Template!$M$3:$M$619,Template!$D68) -> 0 | X68: =IF(Template!$F68="","",SUMIF(Template!$M$3:$M$619,Template!$D68,Template!$AC$3:$AC$619)) -> 0 | Y68: =IFERROR(VLOOKUP(Template!$M68,Template!$D$3:$G$619,MATCH("EmployeeJobTitle",Template!$D$2:$G$2,0),FALSE),"NA") -> COORDENADOR CONTABIL | Z68: =IFERROR(VLOOKUP(Template!$M68,Template!$D$3:$G$619,MATCH("EmployeeGroup",Template!$D$2:$G$2,0),FALSE),"NA") -> Coordenador | AA68: =IFERROR(VLOOKUP(Template!$M68,Template!$D$3:$V$619,MATCH("Layer",Template!$D$2:$V$2,0),FALSE),"NA") -> N3 | AB68: =VLOOKUP(Template!$M68,Template!$D$3:$F$619,MATCH("InternalGrade",Template!$D$2:$F$2,0),FALSE)-Template!$F68 -> 2 | AC68: =IF(Template!$AB68<=1, 0.8,IF(Template!$AB68=2,0.4,IF(Template!$AB68=3,0.2,IF(Template!$AB68=4,0.1,IF(Template!$AB68>=5,0.05,"erro"))))) -> 0.4 | AD68: =Template!$D68=Template!$M68 -> FALSE | AE68: ab28b61c-af05-49c5-9d7a-0a76ad62ccfc
A69: MATRIZ | B69: FINANÇAS | C69: CONTROLADORIA | D69: 25257 | E69: ASSISTENTE FISCAL | F69: 13 | G69: Operacionais / Profissionais | H69: SP | I69: SÃO PAULO | J69: Feminino | K69: 45509 | L69: 35805 | M69: 11398 | N69: 2800 | P69: 13.33 | Q69: 2800 | R69: 0 | U69: =SUM(Template!$N69:$O69)*Template!$P69+Template!$Q69 -> 40124 | V69: =IF(Template!$M69="CONSELHO","N",IF(Template!$AA69="N","N1",IF(Template!$AA69="N1","N2",IF(Template!$AA69="N2","N3",IF(Template!$AA69="N3","N4",IF(Template!$AA69="N4","N5",IF(Template!$AA69="N5","N6",IF(Template!$AA69="N6","N7",IF(Template!$AA69="N7","N8",IF(Template!$AA69="N8","N9",IF(Template!$AA69="N9","N10","NA"))))))))))) -> N4 | W69: =COUNTIF(Template!$M$3:$M$619,Template!$D69) -> 0 | X69: =IF(Template!$F69="","",SUMIF(Template!$M$3:$M$619,Template!$D69,Template!$AC$3:$AC$619)) -> 0 | Y69: =IFERROR(VLOOKUP(Template!$M69,Template!$D$3:$G$619,MATCH("EmployeeJobTitle",Template!$D$2:$G$2,0),FALSE),"NA") -> COORDENADOR FISCAL | Z69: =IFERROR(VLOOKUP(Template!$M69,Template!$D$3:$G$619,MATCH("EmployeeGroup",Template!$D$2:$G$2,0),FALSE),"NA") -> Coordenador | AA69: =IFERROR(VLOOKUP(Template!$M69,Template!$D$3:$V$619,MATCH("Layer",Template!$D$2:$V$2,0),FALSE),"NA") -> N3 | AB69: =VLOOKUP(Template!$M69,Template!$D$3:$F$619,MATCH("InternalGrade",Template!$D$2:$F$2,0),FALSE)-Template!$F69 -> 5 | AC69: =IF(Template!$AB69<=1, 0.8,IF(Template!$AB69=2,0.4,IF(Template!$AB69=3,0.2,IF(Template!$AB69=4,0.1,IF(Template!$AB69>=5,0.05,"erro"))))) -> 0.05 | AD69: =Template!$D69=Template!$M69 -> FALSE | AE69: ab28b61c-af05-49c5-9d7a-0a76ad62ccfc
A70: MATRIZ | B70: COMERCIAL | C70: E-COMMERCE | D70: 25256 | E70: ANALISTA DE ECOMMERCE PL | F70: 15 | G70: Operacionais / Profissionais | H70: SP | I70: SÃO PAULO | J70: Feminino | K70: 45509 | L70: 35739 | M70: 20450 | N70: 4749 | P70: 13.33 | Q70: 4749 | R70: 0 | U70: =SUM(Template!$N70:$O70)*Template!$P70+Template!$Q70 -> 68053.17 | V70: =IF(Template!$M70="CONSELHO","N",IF(Template!$AA70="N","N1",IF(Template!$AA70="N1","N2",IF(Template!$AA70="N2","N3",IF(Template!$AA70="N3","N4",IF(Template!$AA70="N4","N5",IF(Template!$AA70="N5","N6",IF(Template!$AA70="N6","N7",IF(Template!$AA70="N7","N8",IF(Template!$AA70="N8","N9",IF(Template!$AA70="N9","N10","NA"))))))))))) -> N3 | W70: =COUNTIF(Template!$M$3:$M$619,Template!$D70) -> 0 | X70: =IF(Template!$F70="","",SUMIF(Template!$M$3:$M$619,Template!$D70,Template!$AC$3:$AC$619)) -> 0 | Y70: =IFERROR(VLOOKUP(Template!$M70,Template!$D$3:$G$619,MATCH("EmployeeJobTitle",Template!$D$2:$G$2,0),FALSE),"NA") -> COORDENADOR DE ECOMMERCE | Z70: =IFERROR(VLOOKUP(Template!$M70,Template!$D$3:$G$619,MATCH("EmployeeGroup",Template!$D$2:$G$2,0),FALSE),"NA") -> Coordenador | AA70: =IFERROR(VLOOKUP(Template!$M70,Template!$D$3:$V$619,MATCH("Layer",Template!$D$2:$V$2,0),FALSE),"NA") -> N2 | AB70: =VLOOKUP(Template!$M70,Template!$D$3:$F$619,MATCH("InternalGrade",Template!$D$2:$F$2,0),FALSE)-Template!$F70 -> 3 | AC70: =IF(Template!$AB70<=1, 0.8,IF(Template!$AB70=2,0.4,IF(Template!$AB70=3,0.2,IF(Template!$AB70=4,0.1,IF(Template!$AB70>=5,0.05,"erro"))))) -> 0.2 | AD70: =Template!$D70=Template!$M70 -> FALSE | AE70: ab28b61c-af05-49c5-9d7a-0a76ad62ccfc
A71: MATRIZ | B71: COMERCIAL | C71: GERENCIA DE OPERAÇÕES | D71: 25075 | E71: ANALISTA DE INTELIGENCIA COMERCIAL PL | F71: 15 | G71: Operacionais / Profissionais | H71: SP | I71: SÃO PAULO | J71: Feminino | K71: 45432 | L71: 36734 | M71: 21878 | N71: 5000 | P71: 13.33 | Q71: 5000 | R71: 0 | U71: =SUM(Template!$N71:$O71)*Template!$P71+Template!$Q71 -> 71650 | V71: =IF(Template!$M71="CONSELHO","N",IF(Template!$AA71="N","N1",IF(Template!$AA71="N1","N2",IF(Template!$AA71="N2","N3",IF(Template!$AA71="N3","N4",IF(Template!$AA71="N4","N5",IF(Template!$AA71="N5","N6",IF(Template!$AA71="N6","N7",IF(Template!$AA71="N7","N8",IF(Template!$AA71="N8","N9",IF(Template!$AA71="N9","N10","NA"))))))))))) -> N4 | W71: =COUNTIF(Template!$M$3:$M$619,Template!$D71) -> 0 | X71: =IF(Template!$F71="","",SUMIF(Template!$M$3:$M$619,Template!$D71,Template!$AC$3:$AC$619)) -> 0 | Y71: =IFERROR(VLOOKUP(Template!$M71,Template!$D$3:$G$619,MATCH("EmployeeJobTitle",Template!$D$2:$G$2,0),FALSE),"NA") -> COORDENADOR DE INTELIGÊNCIA COMERCIAL | Z71: =IFERROR(VLOOKUP(Template!$M71,Template!$D$3:$G$619,MATCH("EmployeeGroup",Template!$D$2:$G$2,0),FALSE),"NA") -> Coordenador | AA71: =IFERROR(VLOOKUP(Template!$M71,Template!$D$3:$V$619,MATCH("Layer",Template!$D$2:$V$2,0),FALSE),"NA") -> N3 | AB71: =VLOOKUP(Template!$M71,Template!$D$3:$F$619,MATCH("InternalGrade",Template!$D$2:$F$2,0),FALSE)-Template!$F71 -> 3 | AC71: =IF(Template!$AB71<=1, 0.8,IF(Template!$AB71=2,0.4,IF(Template!$AB71=3,0.2,IF(Template!$AB71=4,0.1,IF(Template!$AB71>=5,0.05,"erro"))))) -> 0.2 | AD71: =Template!$D71=Template!$M71 -> FALSE | AE71: ab28b61c-af05-49c5-9d7a-0a76ad62ccfc
A72: MATRIZ | B72: MARKETING | C72: GERENCIA DE VISUAL MERCHADISING | D72: 14939 | E72: ANALISTA DE VM PLENO | F72: 14 | G72: Operacionais / Profissionais | H72: SP | I72: SÃO PAULO | J72: Feminino | K72: 42450 | L72: 34596 | M72: 23266 | N72: 4852 | P72: 13.33 | Q72: 4852 | R72: 0 | U72: =SUM(Template!$N72:$O72)*Template!$P72+Template!$Q72 -> 69529.16 | V72: =IF(Template!$M72="CONSELHO","N",IF(Template!$AA72="N","N1",IF(Template!$AA72="N1","N2",IF(Template!$AA72="N2","N3",IF(Template!$AA72="N3","N4",IF(Template!$AA72="N4","N5",IF(Template!$AA72="N5","N6",IF(Template!$AA72="N6","N7",IF(Template!$AA72="N7","N8",IF(Template!$AA72="N8","N9",IF(Template!$AA72="N9","N10","NA"))))))))))) -> N3 | W72: =COUNTIF(Template!$M$3:$M$619,Template!$D72) -> 0 | X72: =IF(Template!$F72="","",SUMIF(Template!$M$3:$M$619,Template!$D72,Template!$AC$3:$AC$619)) -> 0 | Y72: =IFERROR(VLOOKUP(Template!$M72,Template!$D$3:$G$619,MATCH("EmployeeJobTitle",Template!$D$2:$G$2,0),FALSE),"NA") -> GERENTE DE VM | Z72: =IFERROR(VLOOKUP(Template!$M72,Template!$D$3:$G$619,MATCH("EmployeeGroup",Template!$D$2:$G$2,0),FALSE),"NA") -> Gerente | AA72: =IFERROR(VLOOKUP(Template!$M72,Template!$D$3:$V$619,MATCH("Layer",Template!$D$2:$V$2,0),FALSE),"NA") -> N2 | AB72: =VLOOKUP(Template!$M72,Template!$D$3:$F$619,MATCH("InternalGrade",Template!$D$2:$F$2,0),FALSE)-Template!$F72 -> 5 | AC72: =IF(Template!$AB72<=1, 0.8,IF(Template!$AB72=2,0.4,IF(Template!$AB72=3,0.2,IF(Template!$AB72=4,0.1,IF(Template!$AB72>=5,0.05,"erro"))))) -> 0.05 | AD72: =Template!$D72=Template!$M72 -> FALSE | AE72: ab28b61c-af05-49c5-9d7a-0a76ad62ccfc
... A84: MATRIZ | B84: COMERCIAL | C84: MARKETPLACE OUT | D84: 20378 | E84: ANALISTA MARKET PLACE JR | F84: 14 | G84: Operacionais / Profissionais | H84: SP | I84: SÃO PAULO | J84: Feminino | K84: 44601 | L84: 34894 | M84: 22164 | N84: 3531 | P84: 13.33 | Q84: 3531 | R84: 0 | U84: =SUM(Template!$N84:$O84)*Template!$P84+Template!$Q84 -> 50599.23 | V84: =IF(Template!$M84="CONSELHO","N",IF(Template!$AA84="N","N1",IF(Template!$AA84="N1","N2",IF(Template!$AA84="N2","N3",IF(Template!$AA84="N3","N4",IF(Template!$AA84="N4","N5",IF(Template!$AA84="N5","N6",IF(Template!$AA84="N6","N7",IF(Template!$AA84="N7","N8",IF(Template!$AA84="N8","N9",IF(Template!$AA84="N9","N10","NA"))))))))))) -> N3 | W84: =COUNTIF(Template!$M$3:$M$619,Template!$D84) -> 0 | X84: =IF(Template!$F84="","",SUMIF(Template!$M$3:$M$619,Template!$D84,Template!$AC$3:$AC$619)) -> 0 | Y84: =IFERROR(VLOOKUP(Template!$M84,Template!$D$3:$G$619,MATCH("EmployeeJobTitle",Template!$D$2:$G$2,0),FALSE),"NA") -> COORDENADOR DE MARKETPLACE | Z84: =IFERROR(VLOOKUP(Template!$M84,Template!$D$3:$G$619,MATCH("EmployeeGroup",Template!$D$2:$G$2,0),FALSE),"NA") -> Coordenador | AA84: =IFERROR(VLOOKUP(Template!$M84,Template!$D$3:$V$619,MATCH("Layer",Template!$D$2:$V$2,0),FALSE),"NA") -> N2 | AB84: =VLOOKUP(Template!$M84,Template!$D$3:$F$619,MATCH("InternalGrade",Template!$D$2:$F$2,0),FALSE)-Template!$F84 -> 4 | AC84: =IF(Template!$AB84<=1, 0.8,IF(Template!$AB84=2,0.4,IF(Template!$AB84=3,0.2,IF(Template!$AB84=4,0.1,IF(Template!$AB84>=5,0.05,"erro"))))) -> 0.1 | AD84: =Template!$D84=Template!$M84 -> FALSE | AE84: ab28b61c-af05-49c5-9d7a-0a76ad62ccfc
A85: MATRIZ | B85: COMPRAS E LOGÍSTICA | C85: COMPRAS E MANUTENÇÃO | D85: 14545 | E85: AUXILIAR DE SERVIÇOS GERAIS | G85: Operacionais / Profissionais | H85: SP | I85: SÃO PAULO | J85: Feminino | K85: 42298 | L85: 24320 | M85: 18566 | N85: 2021 | P85: 13.33 | Q85: 2021 | R85: 0 | U85: =SUM(Template!$N85:$O85)*Template!$P85+Template!$Q85 -> 28960.93 | V85: =IF(Template!$M85="CONSELHO","N",IF(Template!$AA85="N","N1",IF(Template!$AA85="N1","N2",IF(Template!$AA85="N2","N3",IF(Template!$AA85="N3","N4",IF(Template!$AA85="N4","N5",IF(Template!$AA85="N5","N6",IF(Template!$AA85="N6","N7",IF(Template!$AA85="N7","N8",IF(Template!$AA85="N8","N9",IF(Template!$AA85="N9","N10","NA"))))))))))) -> N3 | W85: =COUNTIF(Template!$M$3:$M$619,Template!$D85) -> 0 | X85: =IF(Template!$F85="","",SUMIF(Template!$M$3:$M$619,Template!$D85,Template!$AC$3:$AC$619)) | Y85: =IFERROR(VLOOKUP(Template!$M85,Template!$D$3:$G$619,MATCH("EmployeeJobTitle",Template!$D$2:$G$2,0),FALSE),"NA") -> COORDENADOR DE COMPRAS | Z85: =IFERROR(VLOOKUP(Template!$M85,Template!$D$3:$G$619,MATCH("EmployeeGroup",Template!$D$2:$G$2,0),FALSE),"NA") -> Coordenador | AA85: =IFERROR(VLOOKUP(Template!$M85,Template!$D$3:$V$619,MATCH("Layer",Template!$D$2:$V$2,0),FALSE),"NA") -> N2 | AB85: =VLOOKUP(Template!$M85,Template!$D$3:$F$619,MATCH("InternalGrade",Template!$D$2:$F$2,0),FALSE)-Template!$F85 -> 18 | AC85: =IF(Template!$AB85<=1, 0.8,IF(Template!$AB85=2,0.4,IF(Template!$AB85=3,0.2,IF(Template!$AB85=4,0.1,IF(Template!$AB85>=5,0.05,"erro"))))) -> 0.05 | AD85: =Template!$D85=Template!$M85 -> FALSE | AE85: ab28b61c-af05-49c5-9d7a-0a76ad62ccfc
A86: MATRIZ | B86: TECNOLOGIA DA INFORMAÇÃO | C86: TECNOLOGIA DA INFORMAÇÃO | D86: 25146 | E86: ANALISTA DE SISTEMAS PL | F86: 15 | G86: Operacionais / Profissionais | H86: SP | I86: SÃO PAULO | J86: Masculino | K86: 45467 | L86: 33606 | M86: 25348 | N86: 4532 | P86: 13.33 | Q86: 4532 | R86: 0 | U86: =SUM(Template!$N86:$O86)*Template!$P86+Template!$Q86 -> 64943.56 | V86: =IF(Template!$M86="CONSELHO","N",IF(Template!$AA86="N","N1",IF(Template!$AA86="N1","N2",IF(Template!$AA86="N2","N3",IF(Template!$AA86="N3","N4",IF(Template!$AA86="N4","N5",IF(Template!$AA86="N5","N6",IF(Template!$AA86="N6","N7",IF(Template!$AA86="N7","N8",IF(Template!$AA86="N8","N9",IF(Template!$AA86="N9","N10","NA"))))))))))) -> N3 | W86: =COUNTIF(Template!$M$3:$M$619,Template!$D86) -> 0 | X86: =IF(Template!$F86="","",SUMIF(Template!$M$3:$M$619,Template!$D86,Template!$AC$3:$AC$619)) -> 0 | Y86: =IFERROR(VLOOKUP(Template!$M86,Template!$D$3:$G$619,MATCH("EmployeeJobTitle",Template!$D$2:$G$2,0),FALSE),"NA") -> COORDENADOR DE TI | Z86: =IFERROR(VLOOKUP(Template!$M86,Template!$D$3:$G$619,MATCH("EmployeeGroup",Template!$D$2:$G$2,0),FALSE),"NA") -> Coordenador | AA86: =IFERROR(VLOOKUP(Template!$M86,Template!$D$3:$V$619,MATCH("Layer",Template!$D$2:$V$2,0),FALSE),"NA") -> N2 | AB86: =VLOOKUP(Template!$M86,Template!$D$3:$F$619,MATCH("InternalGrade",Template!$D$2:$F$2,0),FALSE)-Template!$F86 -> 3 | AC86: =IF(Template!$AB86<=1, 0.8,IF(Template!$AB86=2,0.4,IF(Template!$AB86=3,0.2,IF(Template!$AB86=4,0.1,IF(Template!$AB86>=5,0.05,"erro"))))) -> 0.2 | AD86: =Template!$D86=Template!$M86 -> FALSE | AE86: ab28b61c-af05-49c5-9d7a-0a76ad62ccfc
A87: MATRIZ | B87: COMERCIAL | C87: E-COMMERCE | D87: 16827 | E87: ANALISTA DE ECOMMERCE JR | F87: 14 | G87: Operacionais / Profissionais | H87: SP | I87: SÃO PAULO | J87: Feminino | K87: 43227 | L87: 35170 | M87: 20450 | N87: 2726.4 | P87: 13.33 | Q87: 2726.4 | R87: 0 | U87: =SUM(Template!$N87:$O87)*Template!$P87+Template!$Q87 -> 39069.312 | V87: =IF(Template!$M87="CONSELHO","N",IF(Template!$AA87="N","N1",IF(Template!$AA87="N1","N2",IF(Template!$AA87="N2","N3",IF(Template!$AA87="N3","N4",IF(Template!$AA87="N4","N5",IF(Template!$AA87="N5","N6",IF(Template!$AA87="N6","N7",IF(Template!$AA87="N7","N8",IF(Template!$AA87="N8","N9",IF(Template!$AA87="N9","N10","NA"))))))))))) -> N3 | W87: =COUNTIF(Template!$M$3:$M$619,Template!$D87) -> 0 | X87: =IF(Template!$F87="","",SUMIF(Template!$M$3:$M$619,Template!$D87,Template!$AC$3:$AC$619)) -> 0 | Y87: =IFERROR(VLOOKUP(Template!$M87,Template!$D$3:$G$619,MATCH("EmployeeJobTitle",Template!$D$2:$G$2,0),FALSE),"NA") -> COORDENADOR DE ECOMMERCE | Z87: =IFERROR(VLOOKUP(Template!$M87,Template!$D$3:$G$619,MATCH("EmployeeGroup",Template!$D$2:$G$2,0),FALSE),"NA") -> Coordenador | AA87: =IFERROR(VLOOKUP(Template!$M87,Template!$D$3:$V$619,MATCH("Layer",Template!$D$2:$V$2,0),FALSE),"NA") -> N2 | AB87: =VLOOKUP(Template!$M87,Template!$D$3:$F$619,MATCH("InternalGrade",Template!$D$2:$F$2,0),FALSE)-Template!$F87 -> 4 | AC87: =IF(Template!$AB87<=1, 0.8,IF(Template!$AB87=2,0.4,IF(Template!$AB87=3,0.2,IF(Template!$AB87=4,0.1,IF(Template!$AB87>=5,0.05,"erro"))))) -> 0.1 | AD87: =Template!$D87=Template!$M87 -> FALSE | AE87: ab28b61c-af05-49c5-9d7a-0a76ad62ccfc
A88: MATRIZ | B88: COMERCIAL | C88: REGIONAL NORDESTE | D88: 12404 | E88: GERENTE COMERCIAL | F88: 19 | G88: Coordenador | H88: SP | I88: SÃO PAULO | J88: Feminino | K88: 41337 | L88: 25832 | M88: 24307 | N88: 11408.32 | P88: 13.33 | Q88: 17112.48 | R88: 0 | U88: =SUM(Template!$N88:$O88)*Template!$P88+Template!$Q88 -> 169185.39 | V88: =IF(Template!$M88="CONSELHO","N",IF(Template!$AA88="N","N1",IF(Template!$AA88="N1","N2",IF(Template!$AA88="N2","N3",IF(Template!$AA88="N3","N4",IF(Template!$AA88="N4","N5",IF(Template!$AA88="N5","N6",IF(Template!$AA88="N6","N7",IF(Template!$AA88="N7","N8",IF(Template!$AA88="N8","N9",IF(Template!$AA88="N9","N10","NA"))))))))))) -> N2 | W88: =COUNTIF(Template!$M$3:$M$619,Template!$D88) -> 16 | X88: =IF(Template!$F88="","",SUMIF(Template!$M$3:$M$619,Template!$D88,Template!$AC$3:$AC$619)) -> 0.8 | Y88: =IFERROR(VLOOKUP(Template!$M88,Template!$D$3:$G$619,MATCH("EmployeeJobTitle",Template!$D$2:$G$2,0),FALSE),"NA") -> DIRETOR COMERCIAL | Z88: =IFERROR(VLOOKUP(Template!$M88,Template!$D$3:$G$619,MATCH("EmployeeGroup",Template!$D$2:$G$2,0),FALSE),"NA") -> Diretor | AA88: =IFERROR(VLOOKUP(Template!$M88,Template!$D$3:$V$619,MATCH("Layer",Template!$D$2:$V$2,0),FALSE),"NA") -> N1 | AB88: =VLOOKUP(Template!$M88,Template!$D$3:$F$619,MATCH("InternalGrade",Template!$D$2:$F$2,0),FALSE)-Template!$F88 -> 3 | AC88: =IF(Template!$AB88<=1, 0.8,IF(Template!$AB88=2,0.4,IF(Template!$AB88=3,0.2,IF(Template!$AB88=4,0.1,IF(Template!$AB88>=5,0.05,"erro"))))) -> 0.2 | AD88: =Template!$D88=Template!$M88 -> FALSE | AE88: ab28b61c-af05-49c5-9d7a-0a76ad62ccfc
A89: MATRIZ | B89: COMERCIAL | C89: MARKETPLACE OUT | D89: 22164 | E89: COORDENADOR DE MARKETPLACE | F89: 18 | G89: Coordenador | H89: SP | I89: SÃO PAULO | J89: Masculino | K89: 44851 | L89: 33306 | M89: 24307 | N89: 11686.19 | P89: 13.33 | Q89: 17529.285 | R89: 0 | U89: =SUM(Template!$N89:$O89)*Template!$P89+Template!$Q89 -> 173306.2 | V89: =IF(Template!$M89="CONSELHO","N",IF(Template!$AA89="N","N1",IF(Template!$AA89="N1","N2",IF(Template!$AA89="N2","N3",IF(Template!$AA89="N3","N4",IF(Template!$AA89="N4","N5",IF(Template!$AA89="N5","N6",IF(Template!$AA89="N6","N7",IF(Template!$AA89="N7","N8",IF(Template!$AA89="N8","N9",IF(Template!$AA89="N9","N10","NA"))))))))))) -> N2 | W89: =COUNTIF(Template!$M$3:$M$619,Template!$D89) -> 1 | X89: =IF(Template!$F89="","",SUMIF(Template!$M$3:$M$619,Template!$D89,Template!$AC$3:$AC$619)) -> 0.1 | Y89: =IFERROR(VLOOKUP(Template!$M89,Template!$D$3:$G$619,MATCH("EmployeeJobTitle",Template!$D$2:$G$2,0),FALSE),"NA") -> DIRETOR COMERCIAL | Z89: =IFERROR(VLOOKUP(Template!$M89,Template!$D$3:$G$619,MATCH("EmployeeGroup",Template!$D$2:$G$2,0),FALSE),"NA") -> Diretor | AA89: =IFERROR(VLOOKUP(Template!$M89,Template!$D$3:$V$619,MATCH("Layer",Template!$D$2:$V$2,0),FALSE),"NA") -> N1 | AB89: =VLOOKUP(Template!$M89,Template!$D$3:$F$619,MATCH("InternalGrade",Template!$D$2:$F$2,0),FALSE)-Template!$F89 -> 4 | AC89: =IF(Template!$AB89<=1, 0.8,IF(Template!$AB89=2,0.4,IF(Template!$AB89=3,0.2,IF(Template!$AB89=4,0.1,IF(Template!$AB89>=5,0.05,"erro"))))) -> 0.1 | AD89: =Template!$D89=Template!$M89 -> FALSE | AE89: ab28b61c-af05-49c5-9d7a-0a76ad62ccfc
A90: MATRIZ | B90: PRODUTO E ESTILO | C90: DESENVOLVIMENTO DE PRODUTO | D90: 23265 | E90: DIRETORA DE PRODUTO E ESTILO | F90: 21 | G90: Diretor | H90: SP | I90: SÃO PAULO | J90: Feminino | K90: 44578 | L90: 29272 | M90: 23258 | N90: 37872.81 | P90: 12 | Q90: 189364.05 | R90: 75745.613 | U90: =SUM(Template!$N90:$O90)*Template!$P90+Template!$Q90 -> 643837.77 | V90: =IF(Template!$M90="CONSELHO","N",IF(Template!$AA90="N","N1",IF(Template!$AA90="N1","N2",IF(Template!$AA90="N2","N3",IF(Template!$AA90="N3","N4",IF(Template!$AA90="N4","N5",IF(Template!$AA90="N5","N6",IF(Template!$AA90="N6","N7",IF(Template!$AA90="N7","N8",IF(Template!$AA90="N8","N9",IF(Template!$AA90="N9","N10","NA"))))))))))) -> N1 | W90: =COUNTIF(Template!$M$3:$M$619,Template!$D90) -> 9 | X90: =IF(Template!$F90="","",SUMIF(Template!$M$3:$M$619,Template!$D90,Template!$AC$3:$AC$619)) -> 1.15 | Y90: =IFERROR(VLOOKUP(Template!$M90,Template!$D$3:$G$619,MATCH("EmployeeJobTitle",Template!$D$2:$G$2,0),FALSE),"NA") -> CEO | Z90: =IFERROR(VLOOKUP(Template!$M90,Template!$D$3:$G$619,MATCH("EmployeeGroup",Template!$D$2:$G$2,0),FALSE),"NA") -> CEO | AA90: =IFERROR(VLOOKUP(Template!$M90,Template!$D$3:$V$619,MATCH("Layer",Template!$D$2:$V$2,0),FALSE),"NA") -> N | AB90: =VLOOKUP(Template!$M90,Template!$D$3:$F$619,MATCH("InternalGrade",Template!$D$2:$F$2,0),FALSE)-Template!$F90 -> 4 | AC90: =IF(Template!$AB90<=1, 0.8,IF(Template!$AB90=2,0.4,IF(Template!$AB90=3,0.2,IF(Template!$AB90=4,0.1,IF(Template!$AB90>=5,0.05,"erro"))))) -> 0.1 | AD90: =Template!$D90=Template!$M90 -> FALSE | AE90: ab28b61c-af05-49c5-9d7a-0a76ad62ccfc
A91: MATRIZ | B91: PRODUTO E ESTILO | C91: DESENVOLVIMENTO DE PRODUTO | D91: 24354 | E91: GERENTE DE PRODUTO E NOVOS NEGOCIOS | F91: 19 | G91: Gerente | H91: SP | I91: SÃO PAULO | J91: Feminino | K91: 45139 | L91: 30359 | M91: 23265 | N91: 22946.56 | P91: 12 | Q91: 68839.68 | R91: 13100.723 | U91: =SUM(Template!$N91:$O91)*Template!$P91+Template!$Q91 -> 344198.4 | V91: =IF(Template!$M91="CONSELHO","N",IF(Template!$AA91="N","N1",IF(Template!$AA91="N1","N2",IF(Template!$AA91="N2","N3",IF(Template!$AA91="N3","N4",IF(Template!$AA91="N4","N5",IF(Template!$AA91="N5","N6",IF(Template!$AA91="N6","N7",IF(Template!$AA91="N7","N8",IF(Template!$AA91="N8","N9",IF(Template!$AA91="N9","N10","NA"))))))))))) -> N2 | W91: =COUNTIF(Template!$M$3:$M$619,Template!$D91) -> 0 | X91: =IF(Template!$F91="","",SUMIF(Template!$M$3:$M$619,Template!$D91,Template!$AC$3:$AC$619)) -> 0 | Y91: =IFERROR(VLOOKUP(Template!$M91,Template!$D$3:$G$619,MATCH("EmployeeJobTitle",Template!$D$2:$G$2,0),FALSE),"NA") -> DIRETORA DE PRODUTO E ESTILO | Z91: =IFERROR(VLOOKUP(Template!$M91,Template!$D$3:$G$619,MATCH("EmployeeGroup",Template!$D$2:$G$2,0),FALSE),"NA") -> Diretor | AA91: =IFERROR(VLOOKUP(Template!$M91,Template!$D$3:$V$619,MATCH("Layer",Template!$D$2:$V$2,0),FALSE),"NA") -> N1 | AB91: =VLOOKUP(Template!$M91,Template!$D$3:$F$619,MATCH("InternalGrade",Template!$D$2:$F$2,0),FALSE)-Template!$F91 -> 2 | AC91: =IF(Template!$AB91<=1, 0.8,IF(Template!$AB91=2,0.4,IF(Template!$AB91=3,0.2,IF(Template!$AB91=4,0.1,IF(Template!$AB91>=5,0.05,"erro"))))) -> 0.4 | AD91: =Template!$D91=Template!$M91 -> FALSE | AE91: ab28b61c-af05-49c5-9d7a-0a76ad62ccfc
A92: MATRIZ | B92: RECURSOS HUMANOS | C92: DIRETORIA DE RECURSOS HUMANOS | D92: 23262 | E92: DIRETORA DE RECURSOS HUMANOS | F92: 21 | G92: Diretor | H92: SP | I92: SÃO PAULO | J92: Feminino | K92: 44228 | L92: 29699 | M92: 23258 | N92: 37135.75 | P92: 12 | Q92: 185678.75 | R92: 55703.624 | U92: =SUM(Template!$N92:$O92)*Template!$P92+Template!$Q92 -> 631307.75 | V92: =IF(Template!$M92="CONSELHO","N",IF(Template!$AA92="N","N1",IF(Template!$AA92="N1","N2",IF(Template!$AA92="N2","N3",IF(Template!$AA92="N3","N4",IF(Template!$AA92="N4","N5",IF(Template!$AA92="N5","N6",IF(Template!$AA92="N6","N7",IF(Template!$AA92="N7","N8",IF(Template!$AA92="N8","N9",IF(Template!$AA92="N9","N10","NA"))))))))))) -> N1 | W92: =COUNTIF(Template!$M$3:$M$619,Template!$D92) -> 3 | X92: =IF(Template!$F92="","",SUMIF(Template!$M$3:$M$619,Template!$D92,Template!$AC$3:$AC$619)) -> 0.3 | Y92: =IFERROR(VLOOKUP(Template!$M92,Template!$D$3:$G$619,MATCH("EmployeeJobTitle",Template!$D$2:$G$2,0),FALSE),"NA") -> CEO | Z92: =IFERROR(VLOOKUP(Template!$M92,Template!$D$3:$G$619,MATCH("EmployeeGroup",Template!$D$2:$G$2,0),FALSE),"NA") -> CEO | AA92: =IFERROR(VLOOKUP(Template!$M92,Template!$D$3:$V$619,MATCH("Layer",Template!$D$2:$V$2,0),FALSE),"NA") -> N | AB92: =VLOOKUP(Template!$M92,Template!$D$3:$F$619,MATCH("InternalGrade",Template!$D$2:$F$2,0),FALSE)-Template!$F92 -> 4 | AC92: =IF(Template!$AB92<=1, 0.8,IF(Template!$AB92=2,0.4,IF(Template!$AB92=3,0.2,IF(Template!$AB92=4,0.1,IF(Template!$AB92>=5,0.05,"erro"))))) -> 0.1 | AD92: =Template!$D92=Template!$M92 -> FALSE | AE92: ab28b61c-af05-49c5-9d7a-0a76ad62ccfc
A93: MATRIZ | B93: MARKETING | C93: GERENCIA DE MARKETING | D93: 23263 | E93: GERENTE DE MARKETING | F93: 19 | G93: Gerente | H93: SP | I93: SÃO PAULO | J93: Feminino | K93: 44466 | L93: 32197 | M93: 23259 | N93: 19999.29 | P93: 12 | Q93: 59997.87 | R93: 25232.109 | U93: =SUM(Template!$N93:$O93)*Template!$P93+Template!$Q93 -> 299989.35 | V93: =IF(Template!$M93="CONSELHO","N",IF(Template!$AA93="N","N1",IF(Template!$AA93="N1","N2",IF(Template!$AA93="N2","N3",IF(Template!$AA93="N3","N4",IF(Template!$AA93="N4","N5",IF(Template!$AA93="N5","N6",IF(Template!$AA93="N6","N7",IF(Template!$AA93="N7","N8",IF(Template!$AA93="N8","N9",IF(Template!$AA93="N9","N10","NA"))))))))))) -> N2 | W93: =COUNTIF(Template!$M$3:$M$619,Template!$D93) -> 1 | X93: =IF(Template!$F93="","",SUMIF(Template!$M$3:$M$619,Template!$D93,Template!$AC$3:$AC$619)) -> 0.8 | Y93: =IFERROR(VLOOKUP(Template!$M93,Template!$D$3:$G$619,MATCH("EmployeeJobTitle",Template!$D$2:$G$2,0),FALSE),"NA") -> DIRETOR DE MARKETING | Z93: =IFERROR(VLOOKUP(Template!$M93,Template!$D$3:$G$619,MATCH("EmployeeGroup",Template!$D$2:$G$2,0),FALSE),"NA") -> Diretor | AA93: =IFERROR(VLOOKUP(Template!$M93,Template!$D$3:$V$619,MATCH("Layer",Template!$D$2:$V$2,0),FALSE),"NA") -> N1 | AB93: =VLOOKUP(Template!$M93,Template!$D$3:$F$619,MATCH("InternalGrade",Template!$D$2:$F$2,0),FALSE)-Template!$F93 -> 2 | AC93: =IF(Template!$AB93<=1, 0.8,IF(Template!$AB93=2,0.4,IF(Template!$AB93=3,0.2,IF(Template!$AB93=4,0.1,IF(Template!$AB93>=5,0.05,"erro"))))) -> 0.4 | AD93: =Template!$D93=Template!$M93 -> FALSE | AE93: ab28b61c-af05-49c5-9d7a-0a76ad62ccfc
A94: MATRIZ | B94: COMERCIAL | C94: GERENCIA DE OPERAÇÕES | D94: 24307 | E94: DIRETOR COMERCIAL | F94: 22 | G94: Diretor | H94: SP | I94: SÃO PAULO | J94: Masculino | K94: 45201 | L94: 28007 | M94: 23258 | N94: 50937.5 | P94: 12 | Q94: 254687.5 | R94: 0 | U94: =SUM(Template!$N94:$O94)*Template!$P94+Template!$Q94 -> 865937.5 | V94: =IF(Template!$M94="CONSELHO","N",IF(Template!$AA94="N","N1",IF(Template!$AA94="N1","N2",IF(Template!$AA94="N2","N3",IF(Template!$AA94="N3","N4",IF(Template!$AA94="N4","N5",IF(Template!$AA94="N5","N6",IF(Template!$AA94="N6","N7",IF(Template!$AA94="N7","N8",IF(Template!$AA94="N8","N9",IF(Template!$AA94="N9","N10","NA"))))))))))) -> N1 | W94: =COUNTIF(Template!$M$3:$M$619,Template!$D94) -> 11 | X94: =IF(Template!$F94="","",SUMIF(Template!$M$3:$M$619,Template!$D94,Template!$AC$3:$AC$619)) -> 2.1 | Y94: =IFERROR(VLOOKUP(Template!$M94,Template!$D$3:$G$619,MATCH("EmployeeJobTitle",Template!$D$2:$G$2,0),FALSE),"NA") -> CEO | Z94: =IFERROR(VLOOKUP(Template!$M94,Template!$D$3:$G$619,MATCH("EmployeeGroup",Template!$D$2:$G$2,0),FALSE),"NA") -> CEO | AA94: =IFERROR(VLOOKUP(Template!$M94,Template!$D$3:$V$619,MATCH("Layer",Template!$D$2:$V$2,0),FALSE),"NA") -> N | AB94: =VLOOKUP(Template!$M94,Template!$D$3:$F$619,MATCH("InternalGrade",Template!$D$2:$F$2,0),FALSE)-Template!$F94 -> 3 | AC94: =IF(Template!$AB94<=1, 0.8,IF(Template!$AB94=2,0.4,IF(Template!$AB94=3,0.2,IF(Template!$AB94=4,0.1,IF(Template!$AB94>=5,0.05,"erro"))))) -> 0.2 | AD94: =Template!$D94=Template!$M94 -> FALSE | AE94: ab28b61c-af05-49c5-9d7a-0a76ad62ccfc
A95: MATRIZ | B95: PRESIDÊNCIA | C95: PRESIDÊNCIA | D95: 23258 | E95: CEO | F95: 25 | G95: CEO | H95: SP | I95: SÃO PAULO | J95: Masculino | K95: 43794 | L95: 24341 | M95: CONSELHO | N95: 99107.06 | P95: 12 | Q95: 693749.42 | R95: 210206.07 | U95: =SUM(Template!$N95:$O95)*Template!$P95+Template!$Q95 -> 1883034.1 | V95: =IF(Template!$M95="CONSELHO","N",IF(Template!$AA95="N","N1",IF(Template!$AA95="N1","N2",IF(Template!$AA95="N2","N3",IF(Template!$AA95="N3","N4",IF(Template!$AA95="N4","N5",IF(Template!$AA95="N5","N6",IF(Template!$AA95="N6","N7",IF(Template!$AA95="N7","N8",IF(Template!$AA95="N8","N9",IF(Template!$AA95="N9","N10","NA"))))))))))) -> N | W95: =COUNTIF(Template!$M$3:$M$619,Template!$D95) -> 7 | X95: =IF(Template!$F95="","",SUMIF(Template!$M$3:$M$619,Template!$D95,Template!$AC$3:$AC$619)) -> 0.85 | Y95: =IFERROR(VLOOKUP(Template!$M95,Template!$D$3:$G$619,MATCH("EmployeeJobTitle",Template!$D$2:$G$2,0),FALSE),"NA") -> NA | Z95: =IFERROR(VLOOKUP(Template!$M95,Template!$D$3:$G$619,MATCH("EmployeeGroup",Template!$D$2:$G$2,0),FALSE),"NA") -> NA | AA95: =IFERROR(VLOOKUP(Template!$M95,Template!$D$3:$V$619,MATCH("Layer",Template!$D$2:$V$2,0),FALSE),"NA") -> NA | AB95: =VLOOKUP(Template!$M95,Template!$D$3:$F$619,MATCH("InternalGrade",Template!$D$2:$F$2,0),FALSE)-Template!$F95 -> #N/A | AC95: =IF(Template!$AB95<=1, 0.8,IF(Template!$AB95=2,0.4,IF(Template!$AB95=3,0.2,IF(Template!$AB95=4,0.1,IF(Template!$AB95>=5,0.05,"erro"))))) -> #N/A | AD95: =Template!$D95=Template!$M95 -> FALSE | AE95: ab28b61c-af05-49c5-9d7a-0a76ad62ccfc
A96: MATRIZ | B96: TECNOLOGIA DA INFORMAÇÃO | C96: TECNOLOGIA DA INFORMAÇÃO | D96: 24945 | E96: GERENTE SISTEMA DA INFORMAÇÃO | F96: 19 | G96: Gerente | H96: SP | I96: SÃO PAULO | J96: Masculino | K96: 45369 | L96: 30245 | M96: 23258 | N96: 23500 | P96: 12 | Q96: 70500 | R96: 0 | U96: =SUM(Template!$N96:$O96)*Template!$P96+Template!$Q96 -> 352500 | V96: =IF(Template!$M96="CONSELHO","N",IF(Template!$AA96="N","N1",IF(Template!$AA96="N1","N2",IF(Template!$AA96="N2","N3",IF(Template!$AA96="N3","N4",IF(Template!$AA96="N4","N5",IF(Template!$AA96="N5","N6",IF(Template!$AA96="N6","N7",IF(Template!$AA96="N7","N8",IF(Template!$AA96="N8","N9",IF(Template!$AA96="N9","N10","NA"))))))))))) -> N1 | W96: =COUNTIF(Template!$M$3:$M$619,Template!$D96) -> 1 | X96: =IF(Template!$F96="","",SUMIF(Template!$M$3:$M$619,Template!$D96,Template!$AC$3:$AC$619)) -> 0.8 | Y96: =IFERROR(VLOOKUP(Template!$M96,Template!$D$3:$G$619,MATCH("EmployeeJobTitle",Template!$D$2:$G$2,0),FALSE),"NA") -> CEO | Z96: =IFERROR(VLOOKUP(Template!$M96,Template!$D$3:$G$619,MATCH("EmployeeGroup",Template!$D$2:$G$2,0),FALSE),"NA") -> CEO | AA96: =IFERROR(VLOOKUP(Template!$M96,Template!$D$3:$V$619,MATCH("Layer",Template!$D$2:$V$2,0),FALSE),"NA") -> N | AB96: =VLOOKUP(Template!$M96,Template!$D$3:$F$619,MATCH("InternalGrade",Template!$D$2:$F$2,0),FALSE)-Template!$F96 -> 6 | AC96: =IF(Template!$AB96<=1, 0.8,IF(Template!$AB96=2,0.4,IF(Template!$AB96=3,0.2,IF(Template!$AB96=4,0.1,IF(Template!$AB96>=5,0.05,"erro"))))) -> 0.05 | AD96: =Template!$D96=Template!$M96 -> FALSE | AE96: ab28b61c-af05-49c5-9d7a-0a76ad62ccfc
A97: MATRIZ | B97: FINANÇAS | C97: DIRETORIA ADMINISTRATIVA FINANCEIRA | D97: 23257 | E97: DIRETOR FINANCEIRO | F97: 22 | G97: Diretor | H97: SP | I97: SÃO PAULO | J97: Masculino | K97: 43719 | L97: 28803 | M97: 23258 | N97: 57442.44 | P97: 12 | Q97: 287212.2 | R97: 76961.719 | U97: =SUM(Template!$N97:$O97)*Template!$P97+Template!$Q97 -> 976521.48 | V97: =IF(Template!$M97="CONSELHO","N",IF(Template!$AA97="N","N1",IF(Template!$AA97="N1","N2",IF(Template!$AA97="N2","N3",IF(Template!$AA97="N3","N4",IF(Template!$AA97="N4","N5",IF(Template!$AA97="N5","N6",IF(Template!$AA97="N6","N7",IF(Template!$AA97="N7","N8",IF(Template!$AA97="N8","N9",IF(Template!$AA97="N9","N10","NA"))))))))))) -> N1 | W97: =COUNTIF(Template!$M$3:$M$619,Template!$D97) -> 3 | X97: =IF(Template!$F97="","",SUMIF(Template!$M$3:$M$619,Template!$D97,Template!$AC$3:$AC$619)) -> 0.6 | Y97: =IFERROR(VLOOKUP(Template!$M97,Template!$D$3:$G$619,MATCH("EmployeeJobTitle",Template!$D$2:$G$2,0),FALSE),"NA") -> CEO | Z97: =IFERROR(VLOOKUP(Template!$M97,Template!$D$3:$G$619,MATCH("EmployeeGroup",Template!$D$2:$G$2,0),FALSE),"NA") -> CEO | AA97: =IFERROR(VLOOKUP(Template!$M97,Template!$D$3:$V$619,MATCH("Layer",Template!$D$2:$V$2,0),FALSE),"NA") -> N | AB97: =VLOOKUP(Template!$M97,Template!$D$3:$F$619,MATCH("InternalGrade",Template!$D$2:$F$2,0),FALSE)-Template!$F97 -> 3 | AC97: =IF(Template!$AB97<=1, 0.8,IF(Template!$AB97=2,0.4,IF(Template!$AB97=3,0.2,IF(Template!$AB97=4,0.1,IF(Template!$AB97>=5,0.05,"erro"))))) -> 0.2 | AD97: =Template!$D97=Template!$M97 -> FALSE | AE97: ab28b61c-af05-49c5-9d7a-0a76ad62ccfc
A98: MATRIZ | B98: PRODUTO E ESTILO | C98: DESENVOLVIMENTO DE PRODUTO | D98: 23254 | E98: ESTILISTA SR | F98: 18 | G98: Operacionais / Profissionais | H98: SP | I98: SÃO PAULO | J98: Feminino | K98: 43115 | L98: 29180 | M98: 23265 | N98: 27448.07 | P98: 12 | Q98: 27448.07 | R98: 0 | U98: =SUM(Template!$N98:$O98)*Template!$P98+Template!$Q98 -> 356824.91 | V98: =IF(Template!$M98="CONSELHO","N",IF(Template!$AA98="N","N1",IF(Template!$AA98="N1","N2",IF(Template!$AA98="N2","N3",IF(Template!$AA98="N3","N4",IF(Template!$AA98="N4","N5",IF(Template!$AA98="N5","N6",IF(Template!$AA98="N6","N7",IF(Template!$AA98="N7","N8",IF(Template!$AA98="N8","N9",IF(Template!$AA98="N9","N10","NA"))))))))))) -> N2 | W98: =COUNTIF(Template!$M$3:$M$619,Template!$D98) -> 0 | X98: =IF(Template!$F98="","",SUMIF(Template!$M$3:$M$619,Template!$D98,Template!$AC$3:$AC$619)) -> 0 | Y98: =IFERROR(VLOOKUP(Template!$M98,Template!$D$3:$G$619,MATCH("EmployeeJobTitle",Template!$D$2:$G$2,0),FALSE),"NA") -> DIRETORA DE PRODUTO E ESTILO | Z98: =IFERROR(VLOOKUP(Template!$M98,Template!$D$3:$G$619,MATCH("EmployeeGroup",Template!$D$2:$G$2,0),FALSE),"NA") -> Diretor | AA98: =IFERROR(VLOOKUP(Template!$M98,Template!$D$3:$V$619,MATCH("Layer",Template!$D$2:$V$2,0),FALSE),"NA") -> N1 | AB98: =VLOOKUP(Template!$M98,Template!$D$3:$F$619,MATCH("InternalGrade",Template!$D$2:$F$2,0),FALSE)-Template!$F98 -> 3 | AC98: =IF(Template!$AB98<=1, 0.8,IF(Template!$AB98=2,0.4,IF(Template!$AB98=3,0.2,IF(Template!$AB98=4,0.1,IF(Template!$AB98>=5,0.05,"erro"))))) -> 0.2 | AD98: =Template!$D98=Template!$M98 -> FALSE | AE98: ab28b61c-af05-49c5-9d7a-0a76ad62ccfc
A99: MATRIZ | B99: FINANÇAS | C99: CONTROLADORIA | D99: 23251 | E99: GERENTE DE CONTROLADORIA | F99: 19 | G99: Gerente | H99: SP | I99: SÃO PAULO | J99: Masculino | K99: 41509 | L99: 27426 | M99: 23257 | N99: 32939.38 | P99: 12 | Q99: 98818.14 | R99: 49409.058 | U99: =SUM(Template!$N99:$O99)*Template!$P99+Template!$Q99 -> 494090.7 | V99: =IF(Template!$M99="CONSELHO","N",IF(Template!$AA99="N","N1",IF(Template!$AA99="N1","N2",IF(Template!$AA99="N2","N3",IF(Template!$AA99="N3","N4",IF(Template!$AA99="N4","N5",IF(Template!$AA99="N5","N6",IF(Template!$AA99="N6","N7",IF(Template!$AA99="N7","N8",IF(Template!$AA99="N8","N9",IF(Template!$AA99="N9","N10","NA"))))))))))) -> N2 | W99: =COUNTIF(Template!$M$3:$M$619,Template!$D99) -> 9 | X99: =IF(Template!$F99="","",SUMIF(Template!$M$3:$M$619,Template!$D99,Template!$AC$3:$AC$619)) -> 1.75 | Y99: =IFERROR(VLOOKUP(Template!$M99,Template!$D$3:$G$619,MATCH("EmployeeJobTitle",Template!$D$2:$G$2,0),FALSE),"NA") -> DIRETOR FINANCEIRO | Z99: =IFERROR(VLOOKUP(Template!$M99,Template!$D$3:$G$619,MATCH("EmployeeGroup",Template!$D$2:$G$2,0),FALSE),"NA") -> Diretor | AA99: =IFERROR(VLOOKUP(Template!$M99,Template!$D$3:$V$619,MATCH("Layer",Template!$D$2:$V$2,0),FALSE),"NA") -> N1 | AB99: =VLOOKUP(Template!$M99,Template!$D$3:$F$619,MATCH("InternalGrade",Template!$D$2:$F$2,0),FALSE)-Template!$F99 -> 3 | AC99: =IF(Template!$AB99<=1, 0.8,IF(Template!$AB99=2,0.4,IF(Template!$AB99=3,0.2,IF(Template!$AB99=4,0.1,IF(Template!$AB99>=5,0.05,"erro"))))) -> 0.2 | AD99: =Template!$D99=Template!$M99 -> FALSE | AE99: ab28b61c-af05-49c5-9d7a-0a76ad62ccfc
A100: MATRIZ | B100: MARKETING | C100: GERENCIA DE MARKETING | D100: 23259 | E100: DIRETOR DE MARKETING | F100: 21 | G100: Diretor | H100: SP | I100: SÃO PAULO | J100: Feminino | K100: 43906 | L100: 30061 | M100: 23258 | N100: 40969.27 | P100: 12 | Q100: 204846.35 | R100: 98753.845 | U100: =SUM(Template!$N100:$O100)*Template!$P100+Template!$Q100 -> 696477.59 | V100: =IF(Template!$M100="CONSELHO","N",IF(Template!$AA100="N","N1",IF(Template!$AA100="N1","N2",IF(Template!$AA100="N2","N3",IF(Template!$AA100="N3","N4",IF(Template!$AA100="N4","N5",IF(Template!$AA100="N5","N6",IF(Template!$AA100="N6","N7",IF(Template!$AA100="N7","N8",IF(Template!$AA100="N8","N9",IF(Template!$AA100="N9","N10","NA"))))))))))) -> N1 | W100: =COUNTIF(Template!$M$3:$M$619,Template!$D100) -> 2 | X100: =IF(Template!$F100="","",SUMIF(Template!$M$3:$M$619,Template!$D100,Template!$AC$3:$AC$619)) -> 0.8 | Y100: =IFERROR(VLOOKUP(Template!$M100,Template!$D$3:$G$619,MATCH("EmployeeJobTitle",Template!$D$2:$G$2,0),FALSE),"NA") -> CEO | Z100: =IFERROR(VLOOKUP(Template!$M100,Template!$D$3:$G$619,MATCH("EmployeeGroup",Template!$D$2:$G$2,0),FALSE),"NA") -> CEO | AA100: =IFERROR(VLOOKUP(Template!$M100,Template!$D$3:$V$619,MATCH("Layer",Template!$D$2:$V$2,0),FALSE),"NA") -> N | AB100: =VLOOKUP(Template!$M100,Template!$D$3:$F$619,MATCH("InternalGrade",Template!$D$2:$F$2,0),FALSE)-Template!$F100 -> 4 | AC100: =IF(Template!$AB100<=1, 0.8,IF(Template!$AB100=2,0.4,IF(Template!$AB100=3,0.2,IF(Template!$AB100=4,0.1,IF(Template!$AB100>=5,0.05,"erro"))))) -> 0.1 | AD100: =Template!$D100=Template!$M100 -> FALSE | AE100: ab28b61c-af05-49c5-9d7a-0a76ad62ccfc
A101: MATRIZ | B101: COMPRAS E LOGÍSTICA | C101: COMPRAS E MANUTENÇÃO | D101: 23261 | E101: DIRETORA DE COMPRAS E LOGISTICA | F101: 21 | G101: Diretor | H101: SP | I101: SÃO PAULO | J101: Feminino | K101: 44198 | L101: 29700 | M101: 23258 | N101: 36855.44 | P101: 12 | Q101: 184277.2 | R101: 78533.093 | U101: =SUM(Template!$N101:$O101)*Template!$P101+Template!$Q101 -> 626542.48 | V101: =IF(Template!$M101="CONSELHO","N",IF(Template!$AA101="N","N1",IF(Template!$AA101="N1","N2",IF(Template!$AA101="N2","N3",IF(Template!$AA101="N3","N4",IF(Template!$AA101="N4","N5",IF(Template!$AA101="N5","N6",IF(Template!$AA101="N6","N7",IF(Template!$AA101="N7","N8",IF(Template!$AA101="N8","N9",IF(Template!$AA101="N9","N10","NA"))))))))))) -> N1 | W101: =COUNTIF(Template!$M$3:$M$619,Template!$D101) -> 5 | X101: =IF(Template!$F101="","",SUMIF(Template!$M$3:$M$619,Template!$D101,Template!$AC$3:$AC$619)) -> 1.6 | Y101: =IFERROR(VLOOKUP(Template!$M101,Template!$D$3:$G$619,MATCH("EmployeeJobTitle",Template!$D$2:$G$2,0),FALSE),"NA") -> CEO | Z101: =IFERROR(VLOOKUP(Template!$M101,Template!$D$3:$G$619,MATCH("EmployeeGroup",Template!$D$2:$G$2,0),FALSE),"NA") -> CEO | AA101: =IFERROR(VLOOKUP(Template!$M101,Template!$D$3:$V$619,MATCH("Layer",Template!$D$2:$V$2,0),FALSE),"NA") -> N | AB101: =VLOOKUP(Template!$M101,Template!$D$3:$F$619,MATCH("InternalGrade",Template!$D$2:$F$2,0),FALSE)-Template!$F101 -> 4 | AC101: =IF(Template!$AB101<=1, 0.8,IF(Template!$AB101=2,0.4,IF(Template!$AB101=3,0.2,IF(Template!$AB101=4,0.1,IF(Template!$AB101>=5,0.05,"erro"))))) -> 0.1 | AD101: =Template!$D101=Template!$M101 -> FALSE | AE101: ab28b61c-af05-49c5-9d7a-0a76ad62ccfc
A102: MATRIZ | B102: COMERCIAL | C102: REGIONAL OUTROS ESTADOS | D102: 23256 | E102: GERENTE COMERCIAL | F102: 19 | G102: Coordenador | H102: SP | I102: SÃO PAULO | J102: Feminino | K102: 43237 | L102: 24516 | M102: 24307 | N102: 12636.04 | P102: 12 | Q102: 18954.06 | R102: 0 | U102: =SUM(Template!$N102:$O102)*Template!$P102+Template!$Q102 -> 170586.54 | V102: =IF(Template!$M102="CONSELHO","N",IF(Template!$AA102="N","N1",IF(Template!$AA102="N1","N2",IF(Template!$AA102="N2","N3",IF(Template!$AA102="N3","N4",IF(Template!$AA102="N4","N5",IF(Template!$AA102="N5","N6",IF(Template!$AA102="N6","N7",IF(Template!$AA102="N7","N8",IF(Template!$AA102="N8","N9",IF(Template!$AA102="N9","N10","NA"))))))))))) -> N2 | W102: =COUNTIF(Template!$M$3:$M$619,Template!$D102) -> 16 | X102: =IF(Template!$F102="","",SUMIF(Template!$M$3:$M$619,Template!$D102,Template!$AC$3:$AC$619)) -> 0.8 | Y102: =IFERROR(VLOOKUP(Template!$M102,Template!$D$3:$G$619,MATCH("EmployeeJobTitle",Template!$D$2:$G$2,0),FALSE),"NA") -> DIRETOR COMERCIAL | Z102: =IFERROR(VLOOKUP(Template!$M102,Template!$D$3:$G$619,MATCH("EmployeeGroup",Template!$D$2:$G$2,0),FALSE),"NA") -> Diretor | AA102: =IFERROR(VLOOKUP(Template!$M102,Template!$D$3:$V$619,MATCH("Layer",Template!$D$2:$V$2,0),FALSE),"NA") -> N1 | AB102: =VLOOKUP(Template!$M102,Template!$D$3:$F$619,MATCH("InternalGrade",Template!$D$2:$F$2,0),FALSE)-Template!$F102 -> 3 | AC102: =IF(Template!$AB102<=1, 0.8,IF(Template!$AB102=2,0.4,IF(Template!$AB102=3,0.2,IF(Template!$AB102=4,0.1,IF(Template!$AB102>=5,0.05,"erro"))))) -> 0.2 | AD102: =Template!$D102=Template!$M102 -> FALSE | AE102: ab28b61c-af05-49c5-9d7a-0a76ad62ccfc
A103: MATRIZ | B103: PRODUTO E ESTILO | C103: GERENCIA DE OPERAÇÕES | D103: 23260 | E103: GERENTE PLANEJAMENTO ESTRATEGICO | F103: 18 | G103: Gerente | H103: SP | I103: SÃO PAULO | J103: Masculino | K103: 44053 | L103: 32916 | M103: 24307 | N103: 23512.84 | P103: 12 | Q103: 70538.52 | R103: 31502.675 | U103: =SUM(Template!$N103:$O103)*Template!$P103+Template!$Q103 -> 352692.6 | V103: =IF(Template!$M103="CONSELHO","N",IF(Template!$AA103="N","N1",IF(Template!$AA103="N1","N2",IF(Template!$AA103="N2","N3",IF(Template!$AA103="N3","N4",IF(Template!$AA103="N4","N5",IF(Template!$AA103="N5","N6",IF(Template!$AA103="N6","N7",IF(Template!$AA103="N7","N8",IF(Template!$AA103="N8","N9",IF(Template!$AA103="N9","N10","NA"))))))))))) -> N2 | W103: =COUNTIF(Template!$M$3:$M$619,Template!$D103) -> 1 | X103: =IF(Template!$F103="","",SUMIF(Template!$M$3:$M$619,Template!$D103,Template!$AC$3:$AC$619)) -> 0.8 | Y103: =IFERROR(VLOOKUP(Template!$M103,Template!$D$3:$G$619,MATCH("EmployeeJobTitle",Template!$D$2:$G$2,0),FALSE),"NA") -> DIRETOR COMERCIAL | Z103: =IFERROR(VLOOKUP(Template!$M103,Template!$D$3:$G$619,MATCH("EmployeeGroup",Template!$D$2:$G$2,0),FALSE),"NA") -> Diretor | AA103: =IFERROR(VLOOKUP(Template!$M103,Template!$D$3:$V$619,MATCH("Layer",Template!$D$2:$V$2,0),FALSE),"NA") -> N1 | AB103: =VLOOKUP(Template!$M103,Template!$D$3:$F$619,MATCH("InternalGrade",Template!$D$2:$F$2,0),FALSE)-Template!$F103 -> 4 | AC103: =IF(Template!$AB103<=1, 0.8,IF(Template!$AB103=2,0.4,IF(Template!$AB103=3,0.2,IF(Template!$AB103=4,0.1,IF(Template!$AB103>=5,0.05,"erro"))))) -> 0.1 | AD103: =Template!$D103=Template!$M103 -> FALSE | AE103: ab28b61c-af05-49c5-9d7a-0a76ad62ccfc
A104: MATRIZ | B104: MARKETING | C104: GERENCIA DE VISUAL MERCHADISING | D104: 23266 | E104: GERENTE DE VM | F104: 19 | G104: Gerente | H104: SP | I104: SÃO PAULO | J104: Masculino | K104: 44690 | L104: 31689 | M104: 23259 | N104: 19532.62 | P104: 12 | Q104: 58597.86 | R104: 27641.452 | U104: =SUM(Template!$N104:$O104)*Template!$P104+Template!$Q104 -> 292989.3 | V104: =IF(Template!$M104="CONSELHO","N",IF(Template!$AA104="N","N1",IF(Template!$AA104="N1","N2",IF(Template!$AA104="N2","N3",IF(Template!$AA104="N3","N4",IF(Template!$AA104="N4","N5",IF(Template!$AA104="N5","N6",IF(Template!$AA104="N6","N7",IF(Template!$AA104="N7","N8",IF(Template!$AA104="N8","N9",IF(Template!$AA104="N9","N10","NA"))))))))))) -> N2 | W104: =COUNTIF(Template!$M$3:$M$619,Template!$D104) -> 6 | X104: =IF(Template!$F104="","",SUMIF(Template!$M$3:$M$619,Template!$D104,Template!$AC$3:$AC$619)) -> 0.45 | Y104: =IFERROR(VLOOKUP(Template!$M104,Template!$D$3:$G$619,MATCH("EmployeeJobTitle",Template!$D$2:$G$2,0),FALSE),"NA") -> DIRETOR DE MARKETING | Z104: =IFERROR(VLOOKUP(Template!$M104,Template!$D$3:$G$619,MATCH("EmployeeGroup",Template!$D$2:$G$2,0),FALSE),"NA") -> Diretor | AA104: =IFERROR(VLOOKUP(Template!$M104,Template!$D$3:$V$619,MATCH("Layer",Template!$D$2:$V$2,0),FALSE),"NA") -> N1 | AB104: =VLOOKUP(Template!$M104,Template!$D$3:$F$619,MATCH("InternalGrade",Template!$D$2:$F$2,0),FALSE)-Template!$F104 -> 2 | AC104: =IF(Template!$AB104<=1, 0.8,IF(Template!$AB104=2,0.4,IF(Template!$AB104=3,0.2,IF(Template!$AB104=4,0.1,IF(Template!$AB104>=5,0.05,"erro"))))) -> 0.4 | AD104: =Template!$D104=Template!$M104 -> FALSE | AE104: ab28b61c-af05-49c5-9d7a-0a76ad62ccfc
A105: MATRIZ | B105: COMERCIAL | C105: SUPERVISÃO DE FRANQUIAS | D105: 14247 | E105: GERENTE COMERCIAL | F105: 19 | G105: Coordenador | H105: SP | I105: SÃO PAULO | J105: Feminino | K105: 42142 | L105: 32766 | M105: 24307 | N105: 11146.3 | P105: 13.33 | Q105: 16719.45 | R105: 0 | U105: =SUM(Template!$N105:$O105)*Template!$P105+Template!$Q105 -> 165299.63 | V105: =IF(Template!$M105="CONSELHO","N",IF(Template!$AA105="N","N1",IF(Template!$AA105="N1","N2",IF(Template!$AA105="N2","N3",IF(Template!$AA105="N3","N4",IF(Template!$AA105="N4","N5",IF(Template!$AA105="N5","N6",IF(Template!$AA105="N6","N7",IF(Template!$AA105="N7","N8",IF(Template!$AA105="N8","N9",IF(Template!$AA105="N9","N10","NA"))))))))))) -> N2 | W105: =COUNTIF(Template!$M$3:$M$619,Template!$D105) -> 0 | X105: =IF(Template!$F105="","",SUMIF(Template!$M$3:$M$619,Template!$D105,Template!$AC$3:$AC$619)) -> 0 | Y105: =IFERROR(VLOOKUP(Template!$M105,Template!$D$3:$G$619,MATCH("EmployeeJobTitle",Template!$D$2:$G$2,0),FALSE),"NA") -> DIRETOR COMERCIAL | Z105: =IFERROR(VLOOKUP(Template!$M105,Template!$D$3:$G$619,MATCH("EmployeeGroup",Template!$D$2:$G$2,0),FALSE),"NA") -> Diretor | AA105: =IFERROR(VLOOKUP(Template!$M105,Template!$D$3:$V$619,MATCH("Layer",Template!$D$2:$V$2,0),FALSE),"NA") -> N1 | AB105: =VLOOKUP(Template!$M105,Template!$D$3:$F$619,MATCH("InternalGrade",Template!$D$2:$F$2,0),FALSE)-Template!$F105 -> 3 | AC105: =IF(Template!$AB105<=1, 0.8,IF(Template!$AB105=2,0.4,IF(Template!$AB105=3,0.2,IF(Template!$AB105=4,0.1,IF(Template!$AB105>=5,0.05,"erro"))))) -> 0.2 | AD105: =Template!$D105=Template!$M105 -> FALSE | AE105: ab28b61c-af05-49c5-9d7a-0a76ad62ccfc
A106: MATRIZ | B106: COMERCIAL | C106: SUPERVISÃO DE FRANQUIAS | D106: 24581 | E106: ANALISTA DE OPERAÇÕES E EXPANSÃO JR | F106: 14 | G106: Operacionais / Profissionais | H106: SP | I106: SÃO PAULO | J106: Feminino | K106: 45236 | L106: 37013 | M106: 25195 | N106: 3154 | P106: 13.33 | Q106: 3154 | R106: 0 | U106: =SUM(Template!$N106:$O106)*Template!$P106+Template!$Q106 -> 45196.82 | V106: =IF(Template!$M106="CONSELHO","N",IF(Template!$AA106="N","N1",IF(Template!$AA106="N1","N2",IF(Template!$AA106="N2","N3",IF(Template!$AA106="N3","N4",IF(Template!$AA106="N4","N5",IF(Template!$AA106="N5","N6",IF(Template!$AA106="N6","N7",IF(Template!$AA106="N7","N8",IF(Template!$AA106="N8","N9",IF(Template!$AA106="N9","N10","NA"))))))))))) -> N3 | W106: =COUNTIF(Template!$M$3:$M$619,Template!$D106) -> 0 | X106: =IF(Template!$F106="","",SUMIF(Template!$M$3:$M$619,Template!$D106,Template!$AC$3:$AC$619)) -> 0 | Y106: =IFERROR(VLOOKUP(Template!$M106,Template!$D$3:$G$619,MATCH("EmployeeJobTitle",Template!$D$2:$G$2,0),FALSE),"NA") -> GERENTE DE EXPANSÃO, IMPLANTAÇÃO E PROJETOS | Z106: =IFERROR(VLOOKUP(Template!$M106,Template!$D$3:$G$619,MATCH("EmployeeGroup",Template!$D$2:$G$2,0),FALSE),"NA") -> Gerente | AA106: =IFERROR(VLOOKUP(Template!$M106,Template!$D$3:$V$619,MATCH("Layer",Template!$D$2:$V$2,0),FALSE),"NA") -> N2 | AB106: =VLOOKUP(Template!$M106,Template!$D$3:$F$619,MATCH("InternalGrade",Template!$D$2:$F$2,0),FALSE)-Template!$F106 -> 6 | AC106: =IF(Template!$AB106<=1, 0.8,IF(Template!$AB106=2,0.4,IF(Template!$AB106=3,0.2,IF(Template!$AB106=4,0.1,IF(Template!$AB106>=5,0.05,"erro"))))) -> 0.05 | AD106: =Template!$D106=Template!$M106 -> FALSE | AE106: ab28b61c-af05-49c5-9d7a-0a76ad62ccfc
A107: MATRIZ | B107: COMERCIAL | C107: SUPERVISÃO DE FRANQUIAS | D107: 24325 | E107: GERENTE COMERCIAL | F107: 19 | G107: Coordenador | H107: SP | I107: SÃO PAULO | J107: Feminino | K107: 45201 | L107: 31223 | M107: 24307 | N107: 10000 | P107: 13.33 | Q107: 15000 | R107: 0 | U107: =SUM(Template!$N107:$O107)*Template!$P107+Template!$Q107 -> 148300 | V107: =IF(Template!$M107="CONSELHO","N",IF(Template!$AA107="N","N1",IF(Template!$AA107="N1","N2",IF(Template!$AA107="N2","N3",IF(Template!$AA107="N3","N4",IF(Template!$AA107="N4","N5",IF(Template!$AA107="N5","N6",IF(Template!$AA107="N6","N7",IF(Template!$AA107="N7","N8",IF(Template!$AA107="N8","N9",IF(Template!$AA107="N9","N10","NA"))))))))))) -> N2 | W107: =COUNTIF(Template!$M$3:$M$619,Template!$D107) -> 0 | X107: =IF(Template!$F107="","",SUMIF(Template!$M$3:$M$619,Template!$D107,Template!$AC$3:$AC$619)) -> 0 | Y107: =IFERROR(VLOOKUP(Template!$M107,Template!$D$3:$G$619,MATCH("EmployeeJobTitle",Template!$D$2:$G$2,0),FALSE),"NA") -> DIRETOR COMERCIAL | Z107: =IFERROR(VLOOKUP(Template!$M107,Template!$D$3:$G$619,MATCH("EmployeeGroup",Template!$D$2:$G$2,0),FALSE),"NA") -> Diretor | AA107: =IFERROR(VLOOKUP(Template!$M107,Template!$D$3:$V$619,MATCH("Layer",Template!$D$2:$V$2,0),FALSE),"NA") -> N1 | AB107: =VLOOKUP(Template!$M107,Template!$D$3:$F$619,MATCH("InternalGrade",Template!$D$2:$F$2,0),FALSE)-Template!$F107 -> 3 | AC107: =IF(Template!$AB107<=1, 0.8,IF(Template!$AB107=2,0.4,IF(Template!$AB107=3,0.2,IF(Template!$AB107=4,0.1,IF(Template!$AB107>=5,0.05,"erro"))))) -> 0.2 | AD107: =Template!$D107=Template!$M107 -> FALSE | AE107: ab28b61c-af05-49c5-9d7a-0a76ad62ccfc
... A116: MATRIZ | B116: FINANÇAS | C116: JURIDICO | D116: 14066 | E116: GERENTE JURIDICO | F116: 19 | G116: Gerente | H116: SP | I116: SÃO PAULO | J116: Feminino | K116: 42037 | L116: 29374 | M116: 23257 | N116: 22000 | P116: 12 | Q116: 66000 | R116: 24501 | U116: =SUM(Template!$N116:$O116)*Template!$P116+Template!$Q116 -> 330000 | V116: =IF(Template!$M116="CONSELHO","N",IF(Template!$AA116="N","N1",IF(Template!$AA116="N1","N2",IF(Template!$AA116="N2","N3",IF(Template!$AA116="N3","N4",IF(Template!$AA116="N4","N5",IF(Template!$AA116="N5","N6",IF(Template!$AA116="N6","N7",IF(Template!$AA116="N7","N8",IF(Template!$AA116="N8","N9",IF(Template!$AA116="N9","N10","NA"))))))))))) -> N2 | W116: =COUNTIF(Template!$M$3:$M$619,Template!$D116) -> 2 | X116: =IF(Template!$F116="","",SUMIF(Template!$M$3:$M$619,Template!$D116,Template!$AC$3:$AC$619)) -> 0.15 | Y116: =IFERROR(VLOOKUP(Template!$M116,Template!$D$3:$G$619,MATCH("EmployeeJobTitle",Template!$D$2:$G$2,0),FALSE),"NA") -> DIRETOR FINANCEIRO | Z116: =IFERROR(VLOOKUP(Template!$M116,Template!$D$3:$G$619,MATCH("EmployeeGroup",Template!$D$2:$G$2,0),FALSE),"NA") -> Diretor | AA116: =IFERROR(VLOOKUP(Template!$M116,Template!$D$3:$V$619,MATCH("Layer",Template!$D$2:$V$2,0),FALSE),"NA") -> N1 | AB116: =VLOOKUP(Template!$M116,Template!$D$3:$F$619,MATCH("InternalGrade",Template!$D$2:$F$2,0),FALSE)-Template!$F116 -> 3 | AC116: =IF(Template!$AB116<=1, 0.8,IF(Template!$AB116=2,0.4,IF(Template!$AB116=3,0.2,IF(Template!$AB116=4,0.1,IF(Template!$AB116>=5,0.05,"erro"))))) -> 0.2 | AD116: =Template!$D116=Template!$M116 -> FALSE | AE116: ab28b61c-af05-49c5-9d7a-0a76ad62ccfc
A117: LOJA | B117: REGIONAL RIO DE JANEIRO | C117: RIO DE JANEIRO-L | D117: 25445 | E117: VENDEDOR I | G117: Operacionais / Profissionais | H117: RJ | I117: RIO DE JANEIRO | J117: Feminino | K117: 45579 | L117: 34816 | M117: 14002 | P117: 13.33 | U117: =SUM(Template!$N117:$O117)*Template!$P117+Template!$Q117 -> 0 | V117: =IF(Template!$M117="CONSELHO","N",IF(Template!$AA117="N","N1",IF(Template!$AA117="N1","N2",IF(Template!$AA117="N2","N3",IF(Template!$AA117="N3","N4",IF(Template!$AA117="N4","N5",IF(Template!$AA117="N5","N6",IF(Template!$AA117="N6","N7",IF(Template!$AA117="N7","N8",IF(Template!$AA117="N8","N9",IF(Template!$AA117="N9","N10","NA"))))))))))) -> N4 | W117: =COUNTIF(Template!$M$3:$M$619,Template!$D117) -> 0 | X117: =IF(Template!$F117="","",SUMIF(Template!$M$3:$M$619,Template!$D117,Template!$AC$3:$AC$619)) | Y117: =IFERROR(VLOOKUP(Template!$M117,Template!$D$3:$G$619,MATCH("EmployeeJobTitle",Template!$D$2:$G$2,0),FALSE),"NA") -> GERENTE DE LOJA | Z117: =IFERROR(VLOOKUP(Template!$M117,Template!$D$3:$G$619,MATCH("EmployeeGroup",Template!$D$2:$G$2,0),FALSE),"NA") -> GERENTE | AA117: =IFERROR(VLOOKUP(Template!$M117,Template!$D$3:$V$619,MATCH("Layer",Template!$D$2:$V$2,0),FALSE),"NA") -> N3 | AB117: =VLOOKUP(Template!$M117,Template!$D$3:$F$619,MATCH("InternalGrade",Template!$D$2:$F$2,0),FALSE)-Template!$F117 -> 0 | AC117: =IF(Template!$AB117<=1, 0.8,IF(Template!$AB117=2,0.4,IF(Template!$AB117=3,0.2,IF(Template!$AB117=4,0.1,IF(Template!$AB117>=5,0.05,"erro"))))) -> 0.8 | AD117: =Template!$D117=Template!$M117 -> FALSE | AE117: ab28b61c-af05-49c5-9d7a-0a76ad62ccfc
A118: LOJA | B118: REGIONAL RIO DE JANEIRO | C118: RIO DE JANEIRO-L | D118: 25451 | E118: VENDEDOR I | G118: Operacionais / Profissionais | H118: RJ | I118: RIO DE JANEIRO | J118: Feminino | K118: 45579 | L118: 35752 | M118: 14002 | P118: 13.33 | U118: =SUM(Template!$N118:$O118)*Template!$P118+Template!$Q118 -> 0 | V118: =IF(Template!$M118="CONSELHO","N",IF(Template!$AA118="N","N1",IF(Template!$AA118="N1","N2",IF(Template!$AA118="N2","N3",IF(Template!$AA118="N3","N4",IF(Template!$AA118="N4","N5",IF(Template!$AA118="N5","N6",IF(Template!$AA118="N6","N7",IF(Template!$AA118="N7","N8",IF(Template!$AA118="N8","N9",IF(Template!$AA118="N9","N10","NA"))))))))))) -> N4 | W118: =COUNTIF(Template!$M$3:$M$619,Template!$D118) -> 0 | X118: =IF(Template!$F118="","",SUMIF(Template!$M$3:$M$619,Template!$D118,Template!$AC$3:$AC$619)) | Y118: =IFERROR(VLOOKUP(Template!$M118,Template!$D$3:$G$619,MATCH("EmployeeJobTitle",Template!$D$2:$G$2,0),FALSE),"NA") -> GERENTE DE LOJA | Z118: =IFERROR(VLOOKUP(Template!$M118,Template!$D$3:$G$619,MATCH("EmployeeGroup",Template!$D$2:$G$2,0),FALSE),"NA") -> GERENTE | AA118: =IFERROR(VLOOKUP(Template!$M118,Template!$D$3:$V$619,MATCH("Layer",Template!$D$2:$V$2,0),FALSE),"NA") -> N3 | AB118: =VLOOKUP(Template!$M118,Template!$D$3:$F$619,MATCH("InternalGrade",Template!$D$2:$F$2,0),FALSE)-Template!$F118 -> 0 | AC118: =IF(Template!$AB118<=1, 0.8,IF(Template!$AB118=2,0.4,IF(Template!$AB118=3,0.2,IF(Template!$AB118=4,0.1,IF(Template!$AB118>=5,0.05,"erro"))))) -> 0.8 | AD118: =Template!$D118=Template!$M118 -> FALSE | AE118: ab28b61c-af05-49c5-9d7a-0a76ad62ccfc
A119: LOJA | B119: REGIONAL RIO DE JANEIRO | C119: RIO DE JANEIRO-L | D119: 24389 | E119: VENDEDOR I | G119: Operacionais / Profissionais | H119: RJ | I119: RIO DE JANEIRO | J119: Feminino | K119: 45219 | L119: 34108 | M119: 14002 | P119: 13.33 | U119: =SUM(Template!$N119:$O119)*Template!$P119+Template!$Q119 -> 0 | V119: =IF(Template!$M119="CONSELHO","N",IF(Template!$AA119="N","N1",IF(Template!$AA119="N1","N2",IF(Template!$AA119="N2","N3",IF(Template!$AA119="N3","N4",IF(Template!$AA119="N4","N5",IF(Template!$AA119="N5","N6",IF(Template!$AA119="N6","N7",IF(Template!$AA119="N7","N8",IF(Template!$AA119="N8","N9",IF(Template!$AA119="N9","N10","NA"))))))))))) -> N4 | W119: =COUNTIF(Template!$M$3:$M$619,Template!$D119) -> 0 | X119: =IF(Template!$F119="","",SUMIF(Template!$M$3:$M$619,Template!$D119,Template!$AC$3:$AC$619)) | Y119: =IFERROR(VLOOKUP(Template!$M119,Template!$D$3:$G$619,MATCH("EmployeeJobTitle",Template!$D$2:$G$2,0),FALSE),"NA") -> GERENTE DE LOJA | Z119: =IFERROR(VLOOKUP(Template!$M119,Template!$D$3:$G$619,MATCH("EmployeeGroup",Template!$D$2:$G$2,0),FALSE),"NA") -> GERENTE | AA119: =IFERROR(VLOOKUP(Template!$M119,Template!$D$3:$V$619,MATCH("Layer",Template!$D$2:$V$2,0),FALSE),"NA") -> N3 | AB119: =VLOOKUP(Template!$M119,Template!$D$3:$F$619,MATCH("InternalGrade",Template!$D$2:$F$2,0),FALSE)-Template!$F119 -> 0 | AC119: =IF(Template!$AB119<=1, 0.8,IF(Template!$AB119=2,0.4,IF(Template!$AB119=3,0.2,IF(Template!$AB119=4,0.1,IF(Template!$AB119>=5,0.05,"erro"))))) -> 0.8 | AD119: =Template!$D119=Template!$M119 -> FALSE | AE119: ab28b61c-af05-49c5-9d7a-0a76ad62ccfc
A120: LOJA | B120: REGIONAL RIO DE JANEIRO | C120: RIO DE JANEIRO-L | D120: 24184 | E120: VENDEDOR I | G120: Operacionais / Profissionais | H120: RJ | I120: RIO DE JANEIRO | J120: Feminino | K120: 45139 | L120: 32774 | M120: 14002 | P120: 13.33 | U120: =SUM(Template!$N120:$O120)*Template!$P120+Template!$Q120 -> 0 | V120: =IF(Template!$M120="CONSELHO","N",IF(Template!$AA120="N","N1",IF(Template!$AA120="N1","N2",IF(Template!$AA120="N2","N3",IF(Template!$AA120="N3","N4",IF(Template!$AA120="N4","N5",IF(Template!$AA120="N5","N6",IF(Template!$AA120="N6","N7",IF(Template!$AA120="N7","N8",IF(Template!$AA120="N8","N9",IF(Template!$AA120="N9","N10","NA"))))))))))) -> N4 | W120: =COUNTIF(Template!$M$3:$M$619,Template!$D120) -> 0 | X120: =IF(Template!$F120="","",SUMIF(Template!$M$3:$M$619,Template!$D120,Template!$AC$3:$AC$619)) | Y120: =IFERROR(VLOOKUP(Template!$M120,Template!$D$3:$G$619,MATCH("EmployeeJobTitle",Template!$D$2:$G$2,0),FALSE),"NA") -> GERENTE DE LOJA | Z120: =IFERROR(VLOOKUP(Template!$M120,Template!$D$3:$G$619,MATCH("EmployeeGroup",Template!$D$2:$G$2,0),FALSE),"NA") -> GERENTE | AA120: =IFERROR(VLOOKUP(Template!$M120,Template!$D$3:$V$619,MATCH("Layer",Template!$D$2:$V$2,0),FALSE),"NA") -> N3 | AB120: =VLOOKUP(Template!$M120,Template!$D$3:$F$619,MATCH("InternalGrade",Template!$D$2:$F$2,0),FALSE)-Template!$F120 -> 0 | AC120: =IF(Template!$AB120<=1, 0.8,IF(Template!$AB120=2,0.4,IF(Template!$AB120=3,0.2,IF(Template!$AB120=4,0.1,IF(Template!$AB120>=5,0.05,"erro"))))) -> 0.8 | AD120: =Template!$D120=Template!$M120 -> FALSE | AE120: ab28b61c-af05-49c5-9d7a-0a76ad62ccfc
A121: LOJA | B121: REGIONAL RIO DE JANEIRO | C121: RIO DE JANEIRO-L | D121: 24569 | E121: CAIXA I | G121: Operacionais / Profissionais | H121: RJ | I121: RIO DE JANEIRO | J121: Feminino | K121: 45236 | L121: 36035 | M121: 14002 | N121: 1816 | P121: 13.33 | U121: =SUM(Template!$N121:$O121)*Template!$P121+Template!$Q121 -> 24207.28 | V121: =IF(Template!$M121="CONSELHO","N",IF(Template!$AA121="N","N1",IF(Template!$AA121="N1","N2",IF(Template!$AA121="N2","N3",IF(Template!$AA121="N3","N4",IF(Template!$AA121="N4","N5",IF(Template!$AA121="N5","N6",IF(Template!$AA121="N6","N7",IF(Template!$AA121="N7","N8",IF(Template!$AA121="N8","N9",IF(Template!$AA121="N9","N10","NA"))))))))))) -> N4 | W121: =COUNTIF(Template!$M$3:$M$619,Template!$D121) -> 0 | X121: =IF(Template!$F121="","",SUMIF(Template!$M$3:$M$619,Template!$D121,Template!$AC$3:$AC$619)) | Y121: =IFERROR(VLOOKUP(Template!$M121,Template!$D$3:$G$619,MATCH("EmployeeJobTitle",Template!$D$2:$G$2,0),FALSE),"NA") -> GERENTE DE LOJA | Z121: =IFERROR(VLOOKUP(Template!$M121,Template!$D$3:$G$619,MATCH("EmployeeGroup",Template!$D$2:$G$2,0),FALSE),"NA") -> GERENTE | AA121: =IFERROR(VLOOKUP(Template!$M121,Template!$D$3:$V$619,MATCH("Layer",Template!$D$2:$V$2,0),FALSE),"NA") -> N3 | AB121: =VLOOKUP(Template!$M121,Template!$D$3:$F$619,MATCH("InternalGrade",Template!$D$2:$F$2,0),FALSE)-Template!$F121 -> 0 | AC121: =IF(Template!$AB121<=1, 0.8,IF(Template!$AB121=2,0.4,IF(Template!$AB121=3,0.2,IF(Template!$AB121=4,0.1,IF(Template!$AB121>=5,0.05,"erro"))))) -> 0.8 | AD121: =Template!$D121=Template!$M121 -> FALSE | AE121: ab28b61c-af05-49c5-9d7a-0a76ad62ccfc
A122: LOJA | B122: REGIONAL RIO DE JANEIRO | C122: RIO DE JANEIRO-L | D122: 14962 | E122: VENDEDOR I | G122: Operacionais / Profissionais | H122: RJ | I122: RIO DE JANEIRO | J122: Feminino | K122: 42464 | L122: 30574 | M122: 14002 | P122: 13.33 | U122: =SUM(Template!$N122:$O122)*Template!$P122+Template!$Q122 -> 0 | V122: =IF(Template!$M122="CONSELHO","N",IF(Template!$AA122="N","N1",IF(Template!$AA122="N1","N2",IF(Template!$AA122="N2","N3",IF(Template!$AA122="N3","N4",IF(Template!$AA122="N4","N5",IF(Template!$AA122="N5","N6",IF(Template!$AA122="N6","N7",IF(Template!$AA122="N7","N8",IF(Template!$AA122="N8","N9",IF(Template!$AA122="N9","N10","NA"))))))))))) -> N4 | W122: =COUNTIF(Template!$M$3:$M$619,Template!$D122) -> 0 | X122: =IF(Template!$F122="","",SUMIF(Template!$M$3:$M$619,Template!$D122,Template!$AC$3:$AC$619)) | Y122: =IFERROR(VLOOKUP(Template!$M122,Template!$D$3:$G$619,MATCH("EmployeeJobTitle",Template!$D$2:$G$2,0),FALSE),"NA") -> GERENTE DE LOJA | Z122: =IFERROR(VLOOKUP(Template!$M122,Template!$D$3:$G$619,MATCH("EmployeeGroup",Template!$D$2:$G$2,0),FALSE),"NA") -> GERENTE | AA122: =IFERROR(VLOOKUP(Template!$M122,Template!$D$3:$V$619,MATCH("Layer",Template!$D$2:$V$2,0),FALSE),"NA") -> N3 | AB122: =VLOOKUP(Template!$M122,Template!$D$3:$F$619,MATCH("InternalGrade",Template!$D$2:$F$2,0),FALSE)-Template!$F122 -> 0 | AC122: =IF(Template!$AB122<=1, 0.8,IF(Template!$AB122=2,0.4,IF(Template!$AB122=3,0.2,IF(Template!$AB122=4,0.1,IF(Template!$AB122>=5,0.05,"erro"))))) -> 0.8 | AD122: =Template!$D122=Template!$M122 -> FALSE | AE122: ab28b61c-af05-49c5-9d7a-0a76ad62ccfc
A123: LOJA | B123: REGIONAL RIO DE JANEIRO | C123: RIO DE JANEIRO-L | D123: 24736 | E123: VENDEDOR I | G123: Operacionais / Profissionais | H123: RJ | I123: RIO DE JANEIRO | J123: Feminino | K123: 45266 | L123: 33424 | M123: 14002 | P123: 13.33 | U123: =SUM(Template!$N123:$O123)*Template!$P123+Template!$Q123 -> 0 | V123: =IF(Template!$M123="CONSELHO","N",IF(Template!$AA123="N","N1",IF(Template!$AA123="N1","N2",IF(Template!$AA123="N2","N3",IF(Template!$AA123="N3","N4",IF(Template!$AA123="N4","N5",IF(Template!$AA123="N5","N6",IF(Template!$AA123="N6","N7",IF(Template!$AA123="N7","N8",IF(Template!$AA123="N8","N9",IF(Template!$AA123="N9","N10","NA"))))))))))) -> N4 | W123: =COUNTIF(Template!$M$3:$M$619,Template!$D123) -> 0 | X123: =IF(Template!$F123="","",SUMIF(Template!$M$3:$M$619,Template!$D123,Template!$AC$3:$AC$619)) | Y123: =IFERROR(VLOOKUP(Template!$M123,Template!$D$3:$G$619,MATCH("EmployeeJobTitle",Template!$D$2:$G$2,0),FALSE),"NA") -> GERENTE DE LOJA | Z123: =IFERROR(VLOOKUP(Template!$M123,Template!$D$3:$G$619,MATCH("EmployeeGroup",Template!$D$2:$G$2,0),FALSE),"NA") -> GERENTE | AA123: =IFERROR(VLOOKUP(Template!$M123,Template!$D$3:$V$619,MATCH("Layer",Template!$D$2:$V$2,0),FALSE),"NA") -> N3 | AB123: =VLOOKUP(Template!$M123,Template!$D$3:$F$619,MATCH("InternalGrade",Template!$D$2:$F$2,0),FALSE)-Template!$F123 -> 0 | AC123: =IF(Template!$AB123<=1, 0.8,IF(Template!$AB123=2,0.4,IF(Template!$AB123=3,0.2,IF(Template!$AB123=4,0.1,IF(Template!$AB123>=5,0.05,"erro"))))) -> 0.8 | AD123: =Template!$D123=Template!$M123 -> FALSE | AE123: ab28b61c-af05-49c5-9d7a-0a76ad62ccfc
A124: LOJA | B124: REGIONAL RIO DE JANEIRO | C124: RIO DE JANEIRO-L | D124: 16937 | E124: SUB GERENTE DE LOJA | G124: Coordenador | H124: RJ | I124: RIO DE JANEIRO | J124: Feminino | K124: 43297 | L124: 33559 | M124: 14002 | P124: 13.33 | U124: =SUM(Template!$N124:$O124)*Template!$P124+Template!$Q124 -> 0 | V124: =IF(Template!$M124="CONSELHO","N",IF(Template!$AA124="N","N1",IF(Template!$AA124="N1","N2",IF(Template!$AA124="N2","N3",IF(Template!$AA124="N3","N4",IF(Template!$AA124="N4","N5",IF(Template!$AA124="N5","N6",IF(Template!$AA124="N6","N7",IF(Template!$AA124="N7","N8",IF(Template!$AA124="N8","N9",IF(Template!$AA124="N9","N10","NA"))))))))))) -> N4 | W124: =COUNTIF(Template!$M$3:$M$619,Template!$D124) -> 0 | X124: =IF(Template!$F124="","",SUMIF(Template!$M$3:$M$619,Template!$D124,Template!$AC$3:$AC$619)) | Y124: =IFERROR(VLOOKUP(Template!$M124,Template!$D$3:$G$619,MATCH("EmployeeJobTitle",Template!$D$2:$G$2,0),FALSE),"NA") -> GERENTE DE LOJA | Z124: =IFERROR(VLOOKUP(Template!$M124,Template!$D$3:$G$619,MATCH("EmployeeGroup",Template!$D$2:$G$2,0),FALSE),"NA") -> GERENTE | AA124: =IFERROR(VLOOKUP(Template!$M124,Template!$D$3:$V$619,MATCH("Layer",Template!$D$2:$V$2,0),FALSE),"NA") -> N3 | AB124: =VLOOKUP(Template!$M124,Template!$D$3:$F$619,MATCH("InternalGrade",Template!$D$2:$F$2,0),FALSE)-Template!$F124 -> 0 | AC124: =IF(Template!$AB124<=1, 0.8,IF(Template!$AB124=2,0.4,IF(Template!$AB124=3,0.2,IF(Template!$AB124=4,0.1,IF(Template!$AB124>=5,0.05,"erro"))))) -> 0.8 | AD124: =Template!$D124=Template!$M124 -> FALSE | AE124: ab28b61c-af05-49c5-9d7a-0a76ad62ccfc
A125: LOJA | B125: REGIONAL RIO DE JANEIRO | C125: RIO DE JANEIRO-L | D125: 18048 | E125: CAIXA I | G125: Operacionais / Profissionais | H125: RJ | I125: RIO DE JANEIRO | J125: Feminino | K125: 43787 | L125: 28685 | M125: 14002 | N125: 2129 | P125: 13.33 | U125: =SUM(Template!$N125:$O125)*Template!$P125+Template!$Q125 -> 28379.57 | V125: =IF(Template!$M125="CONSELHO","N",IF(Template!$AA125="N","N1",IF(Template!$AA125="N1","N2",IF(Template!$AA125="N2","N3",IF(Template!$AA125="N3","N4",IF(Template!$AA125="N4","N5",IF(Template!$AA125="N5","N6",IF(Template!$AA125="N6","N7",IF(Template!$AA125="N7","N8",IF(Template!$AA125="N8","N9",IF(Template!$AA125="N9","N10","NA"))))))))))) -> N4 | W125: =COUNTIF(Template!$M$3:$M$619,Template!$D125) -> 0 | X125: =IF(Template!$F125="","",SUMIF(Template!$M$3:$M$619,Template!$D125,Template!$AC$3:$AC$619)) | Y125: =IFERROR(VLOOKUP(Template!$M125,Template!$D$3:$G$619,MATCH("EmployeeJobTitle",Template!$D$2:$G$2,0),FALSE),"NA") -> GERENTE DE LOJA | Z125: =IFERROR(VLOOKUP(Template!$M125,Template!$D$3:$G$619,MATCH("EmployeeGroup",Template!$D$2:$G$2,0),FALSE),"NA") -> GERENTE | AA125: =IFERROR(VLOOKUP(Template!$M125,Template!$D$3:$V$619,MATCH("Layer",Template!$D$2:$V$2,0),FALSE),"NA") -> N3 | AB125: =VLOOKUP(Template!$M125,Template!$D$3:$F$619,MATCH("InternalGrade",Template!$D$2:$F$2,0),FALSE)-Template!$F125 -> 0 | AC125: =IF(Template!$AB125<=1, 0.8,IF(Template!$AB125=2,0.4,IF(Template!$AB125=3,0.2,IF(Template!$AB125=4,0.1,IF(Template!$AB125>=5,0.05,"erro"))))) -> 0.8 | AD125: =Template!$D125=Template!$M125 -> FALSE | AE125: ab28b61c-af05-49c5-9d7a-0a76ad62ccfc
A126: LOJA | B126: REGIONAL RIO DE JANEIRO | C126: RIO DE JANEIRO-L | D126: 19648 | E126: AUXILIAR DE LOJA I | G126: Operacionais / Profissionais | H126: RJ | I126: RIO DE JANEIRO | J126: Feminino | K126: 44378 | L126: 28712 | M126: 14002 | N126: 1703 | P126: 13.33 | U126: =SUM(Template!$N126:$O126)*Template!$P126+Template!$Q126 -> 22700.99 | V126: =IF(Template!$M126="CONSELHO","N",IF(Template!$AA126="N","N1",IF(Template!$AA126="N1","N2",IF(Template!$AA126="N2","N3",IF(Template!$AA126="N3","N4",IF(Template!$AA126="N4","N5",IF(Template!$AA126="N5","N6",IF(Template!$AA126="N6","N7",IF(Template!$AA126="N7","N8",IF(Template!$AA126="N8","N9",IF(Template!$AA126="N9","N10","NA"))))))))))) -> N4 | W126: =COUNTIF(Template!$M$3:$M$619,Template!$D126) -> 0 | X126: =IF(Template!$F126="","",SUMIF(Template!$M$3:$M$619,Template!$D126,Template!$AC$3:$AC$619)) | Y126: =IFERROR(VLOOKUP(Template!$M126,Template!$D$3:$G$619,MATCH("EmployeeJobTitle",Template!$D$2:$G$2,0),FALSE),"NA") -> GERENTE DE LOJA | Z126: =IFERROR(VLOOKUP(Template!$M126,Template!$D$3:$G$619,MATCH("EmployeeGroup",Template!$D$2:$G$2,0),FALSE),"NA") -> GERENTE | AA126: =IFERROR(VLOOKUP(Template!$M126,Template!$D$3:$V$619,MATCH("Layer",Template!$D$2:$V$2,0),FALSE),"NA") -> N3 | AB126: =VLOOKUP(Template!$M126,Template!$D$3:$F$619,MATCH("InternalGrade",Template!$D$2:$F$2,0),FALSE)-Template!$F126 -> 0 | AC126: =IF(Template!$AB126<=1, 0.8,IF(Template!$AB126=2,0.4,IF(Template!$AB126=3,0.2,IF(Template!$AB126=4,0.1,IF(Template!$AB126>=5,0.05,"erro"))))) -> 0.8 | AD126: =Template!$D126=Template!$M126 -> FALSE | AE126: ab28b61c-af05-49c5-9d7a-0a76ad62ccfc
A127: LOJA | B127: REGIONAL RIO DE JANEIRO | C127: RIO DE JANEIRO-L | D127: 14002 | E127: GERENTE DE LOJA | G127: GERENTE | H127: RJ | I127: RIO DE JANEIRO | J127: Feminino | K127: 41974 | L127: 32882 | M127: 23256 | N127: 5393 | P127: 13.33 | U127: =SUM(Template!$N127:$O127)*Template!$P127+Template!$Q127 -> 71888.69 | V127: =IF(Template!$M127="CONSELHO","N",IF(Template!$AA127="N","N1",IF(Template!$AA127="N1","N2",IF(Template!$AA127="N2","N3",IF(Template!$AA127="N3","N4",IF(Template!$AA127="N4","N5",IF(Template!$AA127="N5","N6",IF(Template!$AA127="N6","N7",IF(Template!$AA127="N7","N8",IF(Template!$AA127="N8","N9",IF(Template!$AA127="N9","N10","NA"))))))))))) -> N3 | W127: =COUNTIF(Template!$M$3:$M$619,Template!$D127) -> 14 | X127: =IF(Template!$F127="","",SUMIF(Template!$M$3:$M$619,Template!$D127,Template!$AC$3:$AC$619)) | Y127: =IFERROR(VLOOKUP(Template!$M127,Template!$D$3:$G$619,MATCH("EmployeeJobTitle",Template!$D$2:$G$2,0),FALSE),"NA") -> GERENTE COMERCIAL | Z127: =IFERROR(VLOOKUP(Template!$M127,Template!$D$3:$G$619,MATCH("EmployeeGroup",Template!$D$2:$G$2,0),FALSE),"NA") -> Coordenador | AA127: =IFERROR(VLOOKUP(Template!$M127,Template!$D$3:$V$619,MATCH("Layer",Template!$D$2:$V$2,0),FALSE),"NA") -> N2 | AB127: =VLOOKUP(Template!$M127,Template!$D$3:$F$619,MATCH("InternalGrade",Template!$D$2:$F$2,0),FALSE)-Template!$F127 -> 19 | AC127: =IF(Template!$AB127<=1, 0.8,IF(Template!$AB127=2,0.4,IF(Template!$AB127=3,0.2,IF(Template!$AB127=4,0.1,IF(Template!$AB127>=5,0.05,"erro"))))) -> 0.05 | AD127: =Template!$D127=Template!$M127 -> FALSE | AE127: ab28b61c-af05-49c5-9d7a-0a76ad62ccfc
A128: LOJA | B128: REGIONAL RIO DE JANEIRO | C128: RIO DE JANEIRO-L | D128: 17962 | E128: VENDEDOR I | G128: Operacionais / Profissionais | H128: RJ | I128: RIO DE JANEIRO | J128: Feminino | K128: 43773 | L128: 27895 | M128: 14002 | P128: 13.33 | U128: =SUM(Template!$N128:$O128)*Template!$P128+Template!$Q128 -> 0 | V128: =IF(Template!$M128="CONSELHO","N",IF(Template!$AA128="N","N1",IF(Template!$AA128="N1","N2",IF(Template!$AA128="N2","N3",IF(Template!$AA128="N3","N4",IF(Template!$AA128="N4","N5",IF(Template!$AA128="N5","N6",IF(Template!$AA128="N6","N7",IF(Template!$AA128="N7","N8",IF(Template!$AA128="N8","N9",IF(Template!$AA128="N9","N10","NA"))))))))))) -> N4 | W128: =COUNTIF(Template!$M$3:$M$619,Template!$D128) -> 0 | X128: =IF(Template!$F128="","",SUMIF(Template!$M$3:$M$619,Template!$D128,Template!$AC$3:$AC$619)) | Y128: =IFERROR(VLOOKUP(Template!$M128,Template!$D$3:$G$619,MATCH("EmployeeJobTitle",Template!$D$2:$G$2,0),FALSE),"NA") -> GERENTE DE LOJA | Z128: =IFERROR(VLOOKUP(Template!$M128,Template!$D$3:$G$619,MATCH("EmployeeGroup",Template!$D$2:$G$2,0),FALSE),"NA") -> GERENTE | AA128: =IFERROR(VLOOKUP(Template!$M128,Template!$D$3:$V$619,MATCH("Layer",Template!$D$2:$V$2,0),FALSE),"NA") -> N3 | AB128: =VLOOKUP(Template!$M128,Template!$D$3:$F$619,MATCH("InternalGrade",Template!$D$2:$F$2,0),FALSE)-Template!$F128 -> 0 | AC128: =IF(Template!$AB128<=1, 0.8,IF(Template!$AB128=2,0.4,IF(Template!$AB128=3,0.2,IF(Template!$AB128=4,0.1,IF(Template!$AB128>=5,0.05,"erro"))))) -> 0.8 | AD128: =Template!$D128=Template!$M128 -> FALSE | AE128: ab28b61c-af05-49c5-9d7a-0a76ad62ccfc
A129: LOJA | B129: REGIONAL RIO DE JANEIRO | C129: RIO DE JANEIRO-L | D129: 22536 | E129: AUXILIAR DE LOJA I | G129: Operacionais / Profissionais | H129: RJ | I129: RIO DE JANEIRO | J129: Feminino | K129: 44882 | L129: 27109 | M129: 14002 | N129: 1565 | P129: 13.33 | U129: =SUM(Template!$N129:$O129)*Template!$P129+Template!$Q129 -> 20861.45 | V129: =IF(Template!$M129="CONSELHO","N",IF(Template!$AA129="N","N1",IF(Template!$AA129="N1","N2",IF(Template!$AA129="N2","N3",IF(Template!$AA129="N3","N4",IF(Template!$AA129="N4","N5",IF(Template!$AA129="N5","N6",IF(Template!$AA129="N6","N7",IF(Template!$AA129="N7","N8",IF(Template!$AA129="N8","N9",IF(Template!$AA129="N9","N10","NA"))))))))))) -> N4 | W129: =COUNTIF(Template!$M$3:$M$619,Template!$D129) -> 0 | X129: =IF(Template!$F129="","",SUMIF(Template!$M$3:$M$619,Template!$D129,Template!$AC$3:$AC$619)) | Y129: =IFERROR(VLOOKUP(Template!$M129,Template!$D$3:$G$619,MATCH("EmployeeJobTitle",Template!$D$2:$G$2,0),FALSE),"NA") -> GERENTE DE LOJA | Z129: =IFERROR(VLOOKUP(Template!$M129,Template!$D$3:$G$619,MATCH("EmployeeGroup",Template!$D$2:$G$2,0),FALSE),"NA") -> GERENTE | AA129: =IFERROR(VLOOKUP(Template!$M129,Template!$D$3:$V$619,MATCH("Layer",Template!$D$2:$V$2,0),FALSE),"NA") -> N3 | AB129: =VLOOKUP(Template!$M129,Template!$D$3:$F$619,MATCH("InternalGrade",Template!$D$2:$F$2,0),FALSE)-Template!$F129 -> 0 | AC129: =IF(Template!$AB129<=1, 0.8,IF(Template!$AB129=2,0.4,IF(Template!$AB129=3,0.2,IF(Template!$AB129=4,0.1,IF(Template!$AB129>=5,0.05,"erro"))))) -> 0.8 | AD129: =Template!$D129=Template!$M129 -> FALSE | AE129: ab28b61c-af05-49c5-9d7a-0a76ad62ccfc
A130: LOJA | B130: REGIONAL RIO DE JANEIRO | C130: RIO DE JANEIRO-L | D130: 24238 | E130: VENDEDOR I | G130: Operacionais / Profissionais | H130: RJ | I130: RIO DE JANEIRO | J130: Feminino | K130: 45159 | L130: 32086 | M130: 14002 | P130: 13.33 | U130: =SUM(Template!$N130:$O130)*Template!$P130+Template!$Q130 -> 0 | V130: =IF(Template!$M130="CONSELHO","N",IF(Template!$AA130="N","N1",IF(Template!$AA130="N1","N2",IF(Template!$AA130="N2","N3",IF(Template!$AA130="N3","N4",IF(Template!$AA130="N4","N5",IF(Template!$AA130="N5","N6",IF(Template!$AA130="N6","N7",IF(Template!$AA130="N7","N8",IF(Template!$AA130="N8","N9",IF(Template!$AA130="N9","N10","NA"))))))))))) -> N4 | W130: =COUNTIF(Template!$M$3:$M$619,Template!$D130) -> 0 | X130: =IF(Template!$F130="","",SUMIF(Template!$M$3:$M$619,Template!$D130,Template!$AC$3:$AC$619)) | Y130: =IFERROR(VLOOKUP(Template!$M130,Template!$D$3:$G$619,MATCH("EmployeeJobTitle",Template!$D$2:$G$2,0),FALSE),"NA") -> GERENTE DE LOJA | Z130: =IFERROR(VLOOKUP(Template!$M130,Template!$D$3:$G$619,MATCH("EmployeeGroup",Template!$D$2:$G$2,0),FALSE),"NA") -> GERENTE | AA130: =IFERROR(VLOOKUP(Template!$M130,Template!$D$3:$V$619,MATCH("Layer",Template!$D$2:$V$2,0),FALSE),"NA") -> N3 | AB130: =VLOOKUP(Template!$M130,Template!$D$3:$F$619,MATCH("InternalGrade",Template!$D$2:$F$2,0),FALSE)-Template!$F130 -> 0 | AC130: =IF(Template!$AB130<=1, 0.8,IF(Template!$AB130=2,0.4,IF(Template!$AB130=3,0.2,IF(Template!$AB130=4,0.1,IF(Template!$AB130>=5,0.05,"erro"))))) -> 0.8 | AD130: =Template!$D130=Template!$M130 -> FALSE | AE130: ab28b61c-af05-49c5-9d7a-0a76ad62ccfc
A131: LOJA | B131: REGIONAL RIO DE JANEIRO | C131: RIO DE JANEIRO-L | D131: 25438 | E131: APRENDIZ | G131: Operacionais / Profissionais | H131: RJ | I131: RIO DE JANEIRO | J131: Feminino | K131: 45574 | L131: 39213 | M131: 14002 | N131: 930 | P131: 13.33 | U131: =SUM(Template!$N131:$O131)*Template!$P131+Template!$Q131 -> 12396.9 | V131: =IF(Template!$M131="CONSELHO","N",IF(Template!$AA131="N","N1",IF(Template!$AA131="N1","N2",IF(Template!$AA131="N2","N3",IF(Template!$AA131="N3","N4",IF(Template!$AA131="N4","N5",IF(Template!$AA131="N5","N6",IF(Template!$AA131="N6","N7",IF(Template!$AA131="N7","N8",IF(Template!$AA131="N8","N9",IF(Template!$AA131="N9","N10","NA"))))))))))) -> N4 | W131: =COUNTIF(Template!$M$3:$M$619,Template!$D131) -> 0 | X131: =IF(Template!$F131="","",SUMIF(Template!$M$3:$M$619,Template!$D131,Template!$AC$3:$AC$619)) | Y131: =IFERROR(VLOOKUP(Template!$M131,Template!$D$3:$G$619,MATCH("EmployeeJobTitle",Template!$D$2:$G$2,0),FALSE),"NA") -> GERENTE DE LOJA | Z131: =IFERROR(VLOOKUP(Template!$M131,Template!$D$3:$G$619,MATCH("EmployeeGroup",Template!$D$2:$G$2,0),FALSE),"NA") -> GERENTE | AA131: =IFERROR(VLOOKUP(Template!$M131,Template!$D$3:$V$619,MATCH("Layer",Template!$D$2:$V$2,0),FALSE),"NA") -> N3 | AB131: =VLOOKUP(Template!$M131,Template!$D$3:$F$619,MATCH("InternalGrade",Template!$D$2:$F$2,0),FALSE)-Template!$F131 -> 0 | AC131: =IF(Template!$AB131<=1, 0.8,IF(Template!$AB131=2,0.4,IF(Template!$AB131=3,0.2,IF(Template!$AB131=4,0.1,IF(Template!$AB131>=5,0.05,"erro"))))) -> 0.8 | AD131: =Template!$D131=Template!$M131 -> FALSE | AE131: ab28b61c-af05-49c5-9d7a-0a76ad62ccfc
A132: LOJA | B132: REGIONAL RIO DE JANEIRO | C132: RIO DE JANEIRO-R | D132: 23012 | E132: VENDEDOR I | G132: Operacionais / Profissionais | H132: RJ | I132: RIO DE JANEIRO | J132: Feminino | K132: 44896 | L132: 33176 | M132: 16949 | P132: 13.33 | U132: =SUM(Template!$N132:$O132)*Template!$P132+Template!$Q132 -> 0 | V132: =IF(Template!$M132="CONSELHO","N",IF(Template!$AA132="N","N1",IF(Template!$AA132="N1","N2",IF(Template!$AA132="N2","N3",IF(Template!$AA132="N3","N4",IF(Template!$AA132="N4","N5",IF(Template!$AA132="N5","N6",IF(Template!$AA132="N6","N7",IF(Template!$AA132="N7","N8",IF(Template!$AA132="N8","N9",IF(Template!$AA132="N9","N10","NA"))))))))))) -> N4 | W132: =COUNTIF(Template!$M$3:$M$619,Template!$D132) -> 0 | X132: =IF(Template!$F132="","",SUMIF(Template!$M$3:$M$619,Template!$D132,Template!$AC$3:$AC$619)) | Y132: =IFERROR(VLOOKUP(Template!$M132,Template!$D$3:$G$619,MATCH("EmployeeJobTitle",Template!$D$2:$G$2,0),FALSE),"NA") -> GERENTE DE LOJA | Z132: =IFERROR(VLOOKUP(Template!$M132,Template!$D$3:$G$619,MATCH("EmployeeGroup",Template!$D$2:$G$2,0),FALSE),"NA") -> GERENTE | AA132: =IFERROR(VLOOKUP(Template!$M132,Template!$D$3:$V$619,MATCH("Layer",Template!$D$2:$V$2,0),FALSE),"NA") -> N3 | AB132: =VLOOKUP(Template!$M132,Template!$D$3:$F$619,MATCH("InternalGrade",Template!$D$2:$F$2,0),FALSE)-Template!$F132 -> 0 | AC132: =IF(Template!$AB132<=1, 0.8,IF(Template!$AB132=2,0.4,IF(Template!$AB132=3,0.2,IF(Template!$AB132=4,0.1,IF(Template!$AB132>=5,0.05,"erro"))))) -> 0.8 | AD132: =Template!$D132=Template!$M132 -> FALSE | AE132: ab28b61c-af05-49c5-9d7a-0a76ad62ccfc
A133: LOJA | B133: REGIONAL RIO DE JANEIRO | C133: RIO DE JANEIRO-R | D133: 16949 | E133: GERENTE DE LOJA | G133: GERENTE | H133: RJ | I133: RIO DE JANEIRO | J133: Feminino | K133: 43297 | L133: 33203 | M133: 23256 | N133: 4576 | P133: 13.33 | U133: =SUM(Template!$N133:$O133)*Template!$P133+Template!$Q133 -> 60998.08 | V133: =IF(Template!$M133="CONSELHO","N",IF(Template!$AA133="N","N1",IF(Template!$AA133="N1","N2",IF(Template!$AA133="N2","N3",IF(Template!$AA133="N3","N4",IF(Template!$AA133="N4","N5",IF(Template!$AA133="N5","N6",IF(Template!$AA133="N6","N7",IF(Template!$AA133="N7","N8",IF(Template!$AA133="N8","N9",IF(Template!$AA133="N9","N10","NA"))))))))))) -> N3 | W133: =COUNTIF(Template!$M$3:$M$619,Template!$D133) -> 17 | X133: =IF(Template!$F133="","",SUMIF(Template!$M$3:$M$619,Template!$D133,Template!$AC$3:$AC$619)) | Y133: =IFERROR(VLOOKUP(Template!$M133,Template!$D$3:$G$619,MATCH("EmployeeJobTitle",Template!$D$2:$G$2,0),FALSE),"NA") -> GERENTE COMERCIAL | Z133: =IFERROR(VLOOKUP(Template!$M133,Template!$D$3:$G$619,MATCH("EmployeeGroup",Template!$D$2:$G$2,0),FALSE),"NA") -> Coordenador | AA133: =IFERROR(VLOOKUP(Template!$M133,Template!$D$3:$V$619,MATCH("Layer",Template!$D$2:$V$2,0),FALSE),"NA") -> N2 | AB133: =VLOOKUP(Template!$M133,Template!$D$3:$F$619,MATCH("InternalGrade",Template!$D$2:$F$2,0),FALSE)-Template!$F133 -> 19 | AC133: =IF(Template!$AB133<=1, 0.8,IF(Template!$AB133=2,0.4,IF(Template!$AB133=3,0.2,IF(Template!$AB133=4,0.1,IF(Template!$AB133>=5,0.05,"erro"))))) -> 0.05 | AD133: =Template!$D133=Template!$M133 -> FALSE | AE133: ab28b61c-af05-49c5-9d7a-0a76ad62ccfc
A134: LOJA | B134: REGIONAL RIO DE JANEIRO | C134: RIO DE JANEIRO-R | D134: 20714 | E134: VENDEDOR I | G134: Operacionais / Profissionais | H134: RJ | I134: RIO DE JANEIRO | J134: Feminino | K134: 44732 | L134: 36120 | M134: 16949 | P134: 13.33 | U134: =SUM(Template!$N134:$O134)*Template!$P134+Template!$Q134 -> 0 | V134: =IF(Template!$M134="CONSELHO","N",IF(Template!$AA134="N","N1",IF(Template!$AA134="N1","N2",IF(Template!$AA134="N2","N3",IF(Template!$AA134="N3","N4",IF(Template!$AA134="N4","N5",IF(Template!$AA134="N5","N6",IF(Template!$AA134="N6","N7",IF(Template!$AA134="N7","N8",IF(Template!$AA134="N8","N9",IF(Template!$AA134="N9","N10","NA"))))))))))) -> N4 | W134: =COUNTIF(Template!$M$3:$M$619,Template!$D134) -> 0 | X134: =IF(Template!$F134="","",SUMIF(Template!$M$3:$M$619,Template!$D134,Template!$AC$3:$AC$619)) | Y134: =IFERROR(VLOOKUP(Template!$M134,Template!$D$3:$G$619,MATCH("EmployeeJobTitle",Template!$D$2:$G$2,0),FALSE),"NA") -> GERENTE DE LOJA | Z134: =IFERROR(VLOOKUP(Template!$M134,Template!$D$3:$G$619,MATCH("EmployeeGroup",Template!$D$2:$G$2,0),FALSE),"NA") -> GERENTE | AA134: =IFERROR(VLOOKUP(Template!$M134,Template!$D$3:$V$619,MATCH("Layer",Template!$D$2:$V$2,0),FALSE),"NA") -> N3 | AB134: =VLOOKUP(Template!$M134,Template!$D$3:$F$619,MATCH("InternalGrade",Template!$D$2:$F$2,0),FALSE)-Template!$F134 -> 0 | AC134: =IF(Template!$AB134<=1, 0.8,IF(Template!$AB134=2,0.4,IF(Template!$AB134=3,0.2,IF(Template!$AB134=4,0.1,IF(Template!$AB134>=5,0.05,"erro"))))) -> 0.8 | AD134: =Template!$D134=Template!$M134 -> FALSE | AE134: ab28b61c-af05-49c5-9d7a-0a76ad62ccfc
A135: LOJA | B135: REGIONAL RIO DE JANEIRO | C135: RIO DE JANEIRO-R | D135: 18413 | E135: VENDEDOR I | G135: Operacionais / Profissionais | H135: RJ | I135: RIO DE JANEIRO | J135: Feminino | K135: 43878 | L135: 32720 | M135: 16949 | P135: 13.33 | U135: =SUM(Template!$N135:$O135)*Template!$P135+Template!$Q135 -> 0 | V135: =IF(Template!$M135="CONSELHO","N",IF(Template!$AA135="N","N1",IF(Template!$AA135="N1","N2",IF(Template!$AA135="N2","N3",IF(Template!$AA135="N3","N4",IF(Template!$AA135="N4","N5",IF(Template!$AA135="N5","N6",IF(Template!$AA135="N6","N7",IF(Template!$AA135="N7","N8",IF(Template!$AA135="N8","N9",IF(Template!$AA135="N9","N10","NA"))))))))))) -> N4 | W135: =COUNTIF(Template!$M$3:$M$619,Template!$D135) -> 0 | X135: =IF(Template!$F135="","",SUMIF(Template!$M$3:$M$619,Template!$D135,Template!$AC$3:$AC$619)) | Y135: =IFERROR(VLOOKUP(Template!$M135,Template!$D$3:$G$619,MATCH("EmployeeJobTitle",Template!$D$2:$G$2,0),FALSE),"NA") -> GERENTE DE LOJA | Z135: =IFERROR(VLOOKUP(Template!$M135,Template!$D$3:$G$619,MATCH("EmployeeGroup",Template!$D$2:$G$2,0),FALSE),"NA") -> GERENTE | AA135: =IFERROR(VLOOKUP(Template!$M135,Template!$D$3:$V$619,MATCH("Layer",Template!$D$2:$V$2,0),FALSE),"NA") -> N3 | AB135: =VLOOKUP(Template!$M135,Template!$D$3:$F$619,MATCH("InternalGrade",Template!$D$2:$F$2,0),FALSE)-Template!$F135 -> 0 | AC135: =IF(Template!$AB135<=1, 0.8,IF(Template!$AB135=2,0.4,IF(Template!$AB135=3,0.2,IF(Template!$AB135=4,0.1,IF(Template!$AB135>=5,0.05,"erro"))))) -> 0.8 | AD135: =Template!$D135=Template!$M135 -> FALSE | AE135: ab28b61c-af05-49c5-9d7a-0a76ad62ccfc
A136: LOJA | B136: REGIONAL RIO DE JANEIRO | C136: RIO DE JANEIRO-R | D136: 17737 | E136: VENDEDOR RESPONSAVEL | G136: Operacionais / Profissionais | H136: RJ | I136: RIO DE JANEIRO | J136: Feminino | K136: 43633 | L136: 29788 | M136: 16949 | P136: 13.33 | U136: =SUM(Template!$N136:$O136)*Template!$P136+Template!$Q136 -> 0 | V136: =IF(Template!$M136="CONSELHO","N",IF(Template!$AA136="N","N1",IF(Template!$AA136="N1","N2",IF(Template!$AA136="N2","N3",IF(Template!$AA136="N3","N4",IF(Template!$AA136="N4","N5",IF(Template!$AA136="N5","N6",IF(Template!$AA136="N6","N7",IF(Template!$AA136="N7","N8",IF(Template!$AA136="N8","N9",IF(Template!$AA136="N9","N10","NA"))))))))))) -> N4 | W136: =COUNTIF(Template!$M$3:$M$619,Template!$D136) -> 0 | X136: =IF(Template!$F136="","",SUMIF(Template!$M$3:$M$619,Template!$D136,Template!$AC$3:$AC$619)) | Y136: =IFERROR(VLOOKUP(Template!$M136,Template!$D$3:$G$619,MATCH("EmployeeJobTitle",Template!$D$2:$G$2,0),FALSE),"NA") -> GERENTE DE LOJA | Z136: =IFERROR(VLOOKUP(Template!$M136,Template!$D$3:$G$619,MATCH("EmployeeGroup",Template!$D$2:$G$2,0),FALSE),"NA") -> GERENTE | AA136: =IFERROR(VLOOKUP(Template!$M136,Template!$D$3:$V$619,MATCH("Layer",Template!$D$2:$V$2,0),FALSE),"NA") -> N3 | AB136: =VLOOKUP(Template!$M136,Template!$D$3:$F$619,MATCH("InternalGrade",Template!$D$2:$F$2,0),FALSE)-Template!$F136 -> 0 | AC136: =IF(Template!$AB136<=1, 0.8,IF(Template!$AB136=2,0.4,IF(Template!$AB136=3,0.2,IF(Template!$AB136=4,0.1,IF(Template!$AB136>=5,0.05,"erro"))))) -> 0.8 | AD136: =Template!$D136=Template!$M136 -> FALSE | AE136: ab28b61c-af05-49c5-9d7a-0a76ad62ccfc
A137: LOJA | B137: REGIONAL RIO DE JANEIRO | C137: RIO DE JANEIRO-R | D137: 24903 | E137: AUXILIAR DE LOJA I | G137: Operacionais / Profissionais | H137: RJ | I137: RIO DE JANEIRO | J137: Feminino | K137: 45355 | L137: 34563 | M137: 16949 | N137: 1515 | P137: 13.33 | U137: =SUM(Template!$N137:$O137)*Template!$P137+Template!$Q137 -> 20194.95 | V137: =IF(Template!$M137="CONSELHO","N",IF(Template!$AA137="N","N1",IF(Template!$AA137="N1","N2",IF(Template!$AA137="N2","N3",IF(Template!$AA137="N3","N4",IF(Template!$AA137="N4","N5",IF(Template!$AA137="N5","N6",IF(Template!$AA137="N6","N7",IF(Template!$AA137="N7","N8",IF(Template!$AA137="N8","N9",IF(Template!$AA137="N9","N10","NA"))))))))))) -> N4 | W137: =COUNTIF(Template!$M$3:$M$619,Template!$D137) -> 0 | X137: =IF(Template!$F137="","",SUMIF(Template!$M$3:$M$619,Template!$D137,Template!$AC$3:$AC$619)) | Y137: =IFERROR(VLOOKUP(Template!$M137,Template!$D$3:$G$619,MATCH("EmployeeJobTitle",Template!$D$2:$G$2,0),FALSE),"NA") -> GERENTE DE LOJA | Z137: =IFERROR(VLOOKUP(Template!$M137,Template!$D$3:$G$619,MATCH("EmployeeGroup",Template!$D$2:$G$2,0),FALSE),"NA") -> GERENTE | AA137: =IFERROR(VLOOKUP(Template!$M137,Template!$D$3:$V$619,MATCH("Layer",Template!$D$2:$V$2,0),FALSE),"NA") -> N3 | AB137: =VLOOKUP(Template!$M137,Template!$D$3:$F$619,MATCH("InternalGrade",Template!$D$2:$F$2,0),FALSE)-Template!$F137 -> 0 | AC137: =IF(Template!$AB137<=1, 0.8,IF(Template!$AB137=2,0.4,IF(Template!$AB137=3,0.2,IF(Template!$AB137=4,0.1,IF(Template!$AB137>=5,0.05,"erro"))))) -> 0.8 | AD137: =Template!$D137=Template!$M137 -> FALSE | AE137: ab28b61c-af05-49c5-9d7a-0a76ad62ccfc
A138: LOJA | B138: REGIONAL RIO DE JANEIRO | C138: RIO DE JANEIRO-R | D138: 25188 | E138: VENDEDOR I | G138: Operacionais / Profissionais | H138: RJ | I138: RIO DE JANEIRO | J138: Feminino | K138: 45483 | L138: 33979 | M138: 16949 | P138: 13.33 | U138: =SUM(Template!$N138:$O138)*Template!$P138+Template!$Q138 -> 0 | V138: =IF(Template!$M138="CONSELHO","N",IF(Template!$AA138="N","N1",IF(Template!$AA138="N1","N2",IF(Template!$AA138="N2","N3",IF(Template!$AA138="N3","N4",IF(Template!$AA138="N4","N5",IF(Template!$AA138="N5","N6",IF(Template!$AA138="N6","N7",IF(Template!$AA138="N7","N8",IF(Template!$AA138="N8","N9",IF(Template!$AA138="N9","N10","NA"))))))))))) -> N4 | W138: =COUNTIF(Template!$M$3:$M$619,Template!$D138) -> 0 | X138: =IF(Template!$F138="","",SUMIF(Template!$M$3:$M$619,Template!$D138,Template!$AC$3:$AC$619)) | Y138: =IFERROR(VLOOKUP(Template!$M138,Template!$D$3:$G$619,MATCH("EmployeeJobTitle",Template!$D$2:$G$2,0),FALSE),"NA") -> GERENTE DE LOJA | Z138: =IFERROR(VLOOKUP(Template!$M138,Template!$D$3:$G$619,MATCH("EmployeeGroup",Template!$D$2:$G$2,0),FALSE),"NA") -> GERENTE | AA138: =IFERROR(VLOOKUP(Template!$M138,Template!$D$3:$V$619,MATCH("Layer",Template!$D$2:$V$2,0),FALSE),"NA") -> N3 | AB138: =VLOOKUP(Template!$M138,Template!$D$3:$F$619,MATCH("InternalGrade",Template!$D$2:$F$2,0),FALSE)-Template!$F138 -> 0 | AC138: =IF(Template!$AB138<=1, 0.8,IF(Template!$AB138=2,0.4,IF(Template!$AB138=3,0.2,IF(Template!$AB138=4,0.1,IF(Template!$AB138>=5,0.05,"erro"))))) -> 0.8 | AD138: =Template!$D138=Template!$M138 -> FALSE | AE138: ab28b61c-af05-49c5-9d7a-0a76ad62ccfc
A139: LOJA | B139: REGIONAL RIO DE JANEIRO | C139: RIO DE JANEIRO-R | D139: 24071 | E139: CAIXA I | G139: Operacionais / Profissionais | H139: RJ | I139: RIO DE JANEIRO | J139: Feminino | K139: 45082 | L139: 35862 | M139: 16949 | N139: 1846 | P139: 13.33 | U139: =SUM(Template!$N139:$O139)*Template!$P139+Template!$Q139 -> 24607.18 | V139: =IF(Template!$M139="CONSELHO","N",IF(Template!$AA139="N","N1",IF(Template!$AA139="N1","N2",IF(Template!$AA139="N2","N3",IF(Template!$AA139="N3","N4",IF(Template!$AA139="N4","N5",IF(Template!$AA139="N5","N6",IF(Template!$AA139="N6","N7",IF(Template!$AA139="N7","N8",IF(Template!$AA139="N8","N9",IF(Template!$AA139="N9","N10","NA"))))))))))) -> N4 | W139: =COUNTIF(Template!$M$3:$M$619,Template!$D139) -> 0 | X139: =IF(Template!$F139="","",SUMIF(Template!$M$3:$M$619,Template!$D139,Template!$AC$3:$AC$619)) | Y139: =IFERROR(VLOOKUP(Template!$M139,Template!$D$3:$G$619,MATCH("EmployeeJobTitle",Template!$D$2:$G$2,0),FALSE),"NA") -> GERENTE DE LOJA | Z139: =IFERROR(VLOOKUP(Template!$M139,Template!$D$3:$G$619,MATCH("EmployeeGroup",Template!$D$2:$G$2,0),FALSE),"NA") -> GERENTE | AA139: =IFERROR(VLOOKUP(Template!$M139,Template!$D$3:$V$619,MATCH("Layer",Template!$D$2:$V$2,0),FALSE),"NA") -> N3 | AB139: =VLOOKUP(Template!$M139,Template!$D$3:$F$619,MATCH("InternalGrade",Template!$D$2:$F$2,0),FALSE)-Template!$F139 -> 0 | AC139: =IF(Template!$AB139<=1, 0.8,IF(Template!$AB139=2,0.4,IF(Template!$AB139=3,0.2,IF(Template!$AB139=4,0.1,IF(Template!$AB139>=5,0.05,"erro"))))) -> 0.8 | AD139: =Template!$D139=Template!$M139 -> FALSE | AE139: ab28b61c-af05-49c5-9d7a-0a76ad62ccfc
A140: LOJA | B140: REGIONAL RIO DE JANEIRO | C140: RIO DE JANEIRO-R | D140: 22500 | E140: VENDEDOR I | G140: Operacionais / Profissionais | H140: RJ | I140: RIO DE JANEIRO | J140: Feminino | K140: 44882 | L140: 31717 | M140: 16949 | P140: 13.33 | U140: =SUM(Template!$N140:$O140)*Template!$P140+Template!$Q140 -> 0 | V140: =IF(Template!$M140="CONSELHO","N",IF(Template!$AA140="N","N1",IF(Template!$AA140="N1","N2",IF(Template!$AA140="N2","N3",IF(Template!$AA140="N3","N4",IF(Template!$AA140="N4","N5",IF(Template!$AA140="N5","N6",IF(Template!$AA140="N6","N7",IF(Template!$AA140="N7","N8",IF(Template!$AA140="N8","N9",IF(Template!$AA140="N9","N10","NA"))))))))))) -> N4 | W140: =COUNTIF(Template!$M$3:$M$619,Template!$D140) -> 0 | X140: =IF(Template!$F140="","",SUMIF(Template!$M$3:$M$619,Template!$D140,Template!$AC$3:$AC$619)) | Y140: =IFERROR(VLOOKUP(Template!$M140,Template!$D$3:$G$619,MATCH("EmployeeJobTitle",Template!$D$2:$G$2,0),FALSE),"NA") -> GERENTE DE LOJA | Z140: =IFERROR(VLOOKUP(Template!$M140,Template!$D$3:$G$619,MATCH("EmployeeGroup",Template!$D$2:$G$2,0),FALSE),"NA") -> GERENTE | AA140: =IFERROR(VLOOKUP(Template!$M140,Template!$D$3:$V$619,MATCH("Layer",Template!$D$2:$V$2,0),FALSE),"NA") -> N3 | AB140: =VLOOKUP(Template!$M140,Template!$D$3:$F$619,MATCH("InternalGrade",Template!$D$2:$F$2,0),FALSE)-Template!$F140 -> 0 | AC140: =IF(Template!$AB140<=1, 0.8,IF(Template!$AB140=2,0.4,IF(Template!$AB140=3,0.2,IF(Template!$AB140=4,0.1,IF(Template!$AB140>=5,0.05,"erro"))))) -> 0.8 | AD140: =Template!$D140=Template!$M140 -> FALSE | AE140: ab28b61c-af05-49c5-9d7a-0a76ad62ccfc
A141: LOJA | B141: REGIONAL RIO DE JANEIRO | C141: RIO DE JANEIRO-R | D141: 18056 | E141: VENDEDOR RESPONSAVEL | G141: Operacionais / Profissionais | H141: RJ | I141: RIO DE JANEIRO | J141: Feminino | K141: 43787 | L141: 31609 | M141: 16949 | P141: 13.33 | U141: =SUM(Template!$N141:$O141)*Template!$P141+Template!$Q141 -> 0 | V141: =IF(Template!$M141="CONSELHO","N",IF(Template!$AA141="N","N1",IF(Template!$AA141="N1","N2",IF(Template!$AA141="N2","N3",IF(Template!$AA141="N3","N4",IF(Template!$AA141="N4","N5",IF(Template!$AA141="N5","N6",IF(Template!$AA141="N6","N7",IF(Template!$AA141="N7","N8",IF(Template!$AA141="N8","N9",IF(Template!$AA141="N9","N10","NA"))))))))))) -> N4 | W141: =COUNTIF(Template!$M$3:$M$619,Template!$D141) -> 0 | X141: =IF(Template!$F141="","",SUMIF(Template!$M$3:$M$619,Template!$D141,Template!$AC$3:$AC$619)) | Y141: =IFERROR(VLOOKUP(Template!$M141,Template!$D$3:$G$619,MATCH("EmployeeJobTitle",Template!$D$2:$G$2,0),FALSE),"NA") -> GERENTE DE LOJA | Z141: =IFERROR(VLOOKUP(Template!$M141,Template!$D$3:$G$619,MATCH("EmployeeGroup",Template!$D$2:$G$2,0),FALSE),"NA") -> GERENTE | AA141: =IFERROR(VLOOKUP(Template!$M141,Template!$D$3:$V$619,MATCH("Layer",Template!$D$2:$V$2,0),FALSE),"NA") -> N3 | AB141: =VLOOKUP(Template!$M141,Template!$D$3:$F$619,MATCH("InternalGrade",Template!$D$2:$F$2,0),FALSE)-Template!$F141 -> 0 | AC141: =IF(Template!$AB141<=1, 0.8,IF(Template!$AB141=2,0.4,IF(Template!$AB141=3,0.2,IF(Template!$AB141=4,0.1,IF(Template!$AB141>=5,0.05,"erro"))))) -> 0.8 | AD141: =Template!$D141=Template!$M141 -> FALSE | AE141: ab28b61c-af05-49c5-9d7a-0a76ad62ccfc
A142: LOJA | B142: REGIONAL RIO DE JANEIRO | C142: RIO DE JANEIRO-R | D142: 19857 | E142: VENDEDOR I | G142: Operacionais / Profissionais | H142: RJ | I142: RIO DE JANEIRO | J142: Feminino | K142: 44487 | L142: 34454 | M142: 16949 | P142: 13.33 | U142: =SUM(Template!$N142:$O142)*Template!$P142+Template!$Q142 -> 0 | V142: =IF(Template!$M142="CONSELHO","N",IF(Template!$AA142="N","N1",IF(Template!$AA142="N1","N2",IF(Template!$AA142="N2","N3",IF(Template!$AA142="N3","N4",IF(Template!$AA142="N4","N5",IF(Template!$AA142="N5","N6",IF(Template!$AA142="N6","N7",IF(Template!$AA142="N7","N8",IF(Template!$AA142="N8","N9",IF(Template!$AA142="N9","N10","NA"))))))))))) -> N4 | W142: =COUNTIF(Template!$M$3:$M$619,Template!$D142) -> 0 | X142: =IF(Template!$F142="","",SUMIF(Template!$M$3:$M$619,Template!$D142,Template!$AC$3:$AC$619)) | Y142: =IFERROR(VLOOKUP(Template!$M142,Template!$D$3:$G$619,MATCH("EmployeeJobTitle",Template!$D$2:$G$2,0),FALSE),"NA") -> GERENTE DE LOJA | Z142: =IFERROR(VLOOKUP(Template!$M142,Template!$D$3:$G$619,MATCH("EmployeeGroup",Template!$D$2:$G$2,0),FALSE),"NA") -> GERENTE | AA142: =IFERROR(VLOOKUP(Template!$M142,Template!$D$3:$V$619,MATCH("Layer",Template!$D$2:$V$2,0),FALSE),"NA") -> N3 | AB142: =VLOOKUP(Template!$M142,Template!$D$3:$F$619,MATCH("InternalGrade",Template!$D$2:$F$2,0),FALSE)-Template!$F142 -> 0 | AC142: =IF(Template!$AB142<=1, 0.8,IF(Template!$AB142=2,0.4,IF(Template!$AB142=3,0.2,IF(Template!$AB142=4,0.1,IF(Template!$AB142>=5,0.05,"erro"))))) -> 0.8 | AD142: =Template!$D142=Template!$M142 -> FALSE | AE142: ab28b61c-af05-49c5-9d7a-0a76ad62ccfc
A143: LOJA | B143: REGIONAL RIO DE JANEIRO | C143: RIO DE JANEIRO-R | D143: 24566 | E143: VENDEDOR I | G143: Operacionais / Profissionais | H143: RJ | I143: RIO DE JANEIRO | J143: Feminino | K143: 45236 | L143: 28261 | M143: 16949 | P143: 13.33 | U143: =SUM(Template!$N143:$O143)*Template!$P143+Template!$Q143 -> 0 | V143: =IF(Template!$M143="CONSELHO","N",IF(Template!$AA143="N","N1",IF(Template!$AA143="N1","N2",IF(Template!$AA143="N2","N3",IF(Template!$AA143="N3","N4",IF(Template!$AA143="N4","N5",IF(Template!$AA143="N5","N6",IF(Template!$AA143="N6","N7",IF(Template!$AA143="N7","N8",IF(Template!$AA143="N8","N9",IF(Template!$AA143="N9","N10","NA"))))))))))) -> N4 | W143: =COUNTIF(Template!$M$3:$M$619,Template!$D143) -> 0 | X143: =IF(Template!$F143="","",SUMIF(Template!$M$3:$M$619,Template!$D143,Template!$AC$3:$AC$619)) | Y143: =IFERROR(VLOOKUP(Template!$M143,Template!$D$3:$G$619,MATCH("EmployeeJobTitle",Template!$D$2:$G$2,0),FALSE),"NA") -> GERENTE DE LOJA | Z143: =IFERROR(VLOOKUP(Template!$M143,Template!$D$3:$G$619,MATCH("EmployeeGroup",Template!$D$2:$G$2,0),FALSE),"NA") -> GERENTE | AA143: =IFERROR(VLOOKUP(Template!$M143,Template!$D$3:$V$619,MATCH("Layer",Template!$D$2:$V$2,0),FALSE),"NA") -> N3 | AB143: =VLOOKUP(Template!$M143,Template!$D$3:$F$619,MATCH("InternalGrade",Template!$D$2:$F$2,0),FALSE)-Template!$F143 -> 0 | AC143: =IF(Template!$AB143<=1, 0.8,IF(Template!$AB143=2,0.4,IF(Template!$AB143=3,0.2,IF(Template!$AB143=4,0.1,IF(Template!$AB143>=5,0.05,"erro"))))) -> 0.8 | AD143: =Template!$D143=Template!$M143 -> FALSE | AE143: ab28b61c-af05-49c5-9d7a-0a76ad62ccfc
A144: LOJA | B144: REGIONAL RIO DE JANEIRO | C144: RIO DE JANEIRO-R | D144: 17574 | E144: VENDEDOR LIDER VM | G144: Operacionais / Profissionais | H144: RJ | I144: RIO DE JANEIRO | J144: Feminino | K144: 43528 | L144: 31922 | M144: 16949 | P144: 13.33 | U144: =SUM(Template!$N144:$O144)*Template!$P144+Template!$Q144 -> 0 | V144: =IF(Template!$M144="CONSELHO","N",IF(Template!$AA144="N","N1",IF(Template!$AA144="N1","N2",IF(Template!$AA144="N2","N3",IF(Template!$AA144="N3","N4",IF(Template!$AA144="N4","N5",IF(Template!$AA144="N5","N6",IF(Template!$AA144="N6","N7",IF(Template!$AA144="N7","N8",IF(Template!$AA144="N8","N9",IF(Template!$AA144="N9","N10","NA"))))))))))) -> N4 | W144: =COUNTIF(Template!$M$3:$M$619,Template!$D144) -> 0 | X144: =IF(Template!$F144="","",SUMIF(Template!$M$3:$M$619,Template!$D144,Template!$AC$3:$AC$619)) | Y144: =IFERROR(VLOOKUP(Template!$M144,Template!$D$3:$G$619,MATCH("EmployeeJobTitle",Template!$D$2:$G$2,0),FALSE),"NA") -> GERENTE DE LOJA | Z144: =IFERROR(VLOOKUP(Template!$M144,Template!$D$3:$G$619,MATCH("EmployeeGroup",Template!$D$2:$G$2,0),FALSE),"NA") -> GERENTE | AA144: =IFERROR(VLOOKUP(Template!$M144,Template!$D$3:$V$619,MATCH("Layer",Template!$D$2:$V$2,0),FALSE),"NA") -> N3 | AB144: =VLOOKUP(Template!$M144,Template!$D$3:$F$619,MATCH("InternalGrade",Template!$D$2:$F$2,0),FALSE)-Template!$F144 -> 0 | AC144: =IF(Template!$AB144<=1, 0.8,IF(Template!$AB144=2,0.4,IF(Template!$AB144=3,0.2,IF(Template!$AB144=4,0.1,IF(Template!$AB144>=5,0.05,"erro"))))) -> 0.8 | AD144: =Template!$D144=Template!$M144 -> FALSE | AE144: ab28b61c-af05-49c5-9d7a-0a76ad62ccfc
A145: LOJA | B145: REGIONAL RIO DE JANEIRO | C145: RIO DE JANEIRO-R | D145: 19903 | E145: AUXILIAR DE LOJA I | G145: Operacionais / Profissionais | H145: RJ | I145: RIO DE JANEIRO | J145: Feminino | K145: 44503 | L145: 28976 | M145: 16949 | N145: 1624 | P145: 13.33 | U145: =SUM(Template!$N145:$O145)*Template!$P145+Template!$Q145 -> 21647.92 | V145: =IF(Template!$M145="CONSELHO","N",IF(Template!$AA145="N","N1",IF(Template!$AA145="N1","N2",IF(Template!$AA145="N2","N3",IF(Template!$AA145="N3","N4",IF(Template!$AA145="N4","N5",IF(Template!$AA145="N5","N6",IF(Template!$AA145="N6","N7",IF(Template!$AA145="N7","N8",IF(Template!$AA145="N8","N9",IF(Template!$AA145="N9","N10","NA"))))))))))) -> N4 | W145: =COUNTIF(Template!$M$3:$M$619,Template!$D145) -> 0 | X145: =IF(Template!$F145="","",SUMIF(Template!$M$3:$M$619,Template!$D145,Template!$AC$3:$AC$619)) | Y145: =IFERROR(VLOOKUP(Template!$M145,Template!$D$3:$G$619,MATCH("EmployeeJobTitle",Template!$D$2:$G$2,0),FALSE),"NA") -> GERENTE DE LOJA | Z145: =IFERROR(VLOOKUP(Template!$M145,Template!$D$3:$G$619,MATCH("EmployeeGroup",Template!$D$2:$G$2,0),FALSE),"NA") -> GERENTE | AA145: =IFERROR(VLOOKUP(Template!$M145,Template!$D$3:$V$619,MATCH("Layer",Template!$D$2:$V$2,0),FALSE),"NA") -> N3 | AB145: =VLOOKUP(Template!$M145,Template!$D$3:$F$619,MATCH("InternalGrade",Template!$D$2:$F$2,0),FALSE)-Template!$F145 -> 0 | AC145: =IF(Template!$AB145<=1, 0.8,IF(Template!$AB145=2,0.4,IF(Template!$AB145=3,0.2,IF(Template!$AB145=4,0.1,IF(Template!$AB145>=5,0.05,"erro"))))) -> 0.8 | AD145: =Template!$D145=Template!$M145 -> FALSE | AE145: ab28b61c-af05-49c5-9d7a-0a76ad62ccfc
A146: LOJA | B146: REGIONAL RIO DE JANEIRO | C146: RIO DE JANEIRO-R | D146: 25262 | E146: VENDEDOR I | G146: Operacionais / Profissionais | H146: RJ | I146: RIO DE JANEIRO | J146: Feminino | K146: 45509 | L146: 33566 | M146: 16949 | P146: 13.33 | U146: =SUM(Template!$N146:$O146)*Template!$P146+Template!$Q146 -> 0 | V146: =IF(Template!$M146="CONSELHO","N",IF(Template!$AA146="N","N1",IF(Template!$AA146="N1","N2",IF(Template!$AA146="N2","N3",IF(Template!$AA146="N3","N4",IF(Template!$AA146="N4","N5",IF(Template!$AA146="N5","N6",IF(Template!$AA146="N6","N7",IF(Template!$AA146="N7","N8",IF(Template!$AA146="N8","N9",IF(Template!$AA146="N9","N10","NA"))))))))))) -> N4 | W146: =COUNTIF(Template!$M$3:$M$619,Template!$D146) -> 0 | X146: =IF(Template!$F146="","",SUMIF(Template!$M$3:$M$619,Template!$D146,Template!$AC$3:$AC$619)) | Y146: =IFERROR(VLOOKUP(Template!$M146,Template!$D$3:$G$619,MATCH("EmployeeJobTitle",Template!$D$2:$G$2,0),FALSE),"NA") -> GERENTE DE LOJA | Z146: =IFERROR(VLOOKUP(Template!$M146,Template!$D$3:$G$619,MATCH("EmployeeGroup",Template!$D$2:$G$2,0),FALSE),"NA") -> GERENTE | AA146: =IFERROR(VLOOKUP(Template!$M146,Template!$D$3:$V$619,MATCH("Layer",Template!$D$2:$V$2,0),FALSE),"NA") -> N3 | AB146: =VLOOKUP(Template!$M146,Template!$D$3:$F$619,MATCH("InternalGrade",Template!$D$2:$F$2,0),FALSE)-Template!$F146 -> 0 | AC146: =IF(Template!$AB146<=1, 0.8,IF(Template!$AB146=2,0.4,IF(Template!$AB146=3,0.2,IF(Template!$AB146=4,0.1,IF(Template!$AB146>=5,0.05,"erro"))))) -> 0.8 | AD146: =Template!$D146=Template!$M146 -> FALSE | AE146: ab28b61c-af05-49c5-9d7a-0a76ad62ccfc
A147: LOJA | B147: REGIONAL RIO DE JANEIRO | C147: RIO DE JANEIRO-R | D147: 17075 | E147: VENDEDOR I | G147: Operacionais / Profissionais | H147: RJ | I147: RIO DE JANEIRO | J147: Feminino | K147: 43360 | L147: 32718 | M147: 16949 | P147: 13.33 | U147: =SUM(Template!$N147:$O147)*Template!$P147+Template!$Q147 -> 0 | V147: =IF(Template!$M147="CONSELHO","N",IF(Template!$AA147="N","N1",IF(Template!$AA147="N1","N2",IF(Template!$AA147="N2","N3",IF(Template!$AA147="N3","N4",IF(Template!$AA147="N4","N5",IF(Template!$AA147="N5","N6",IF(Template!$AA147="N6","N7",IF(Template!$AA147="N7","N8",IF(Template!$AA147="N8","N9",IF(Template!$AA147="N9","N10","NA"))))))))))) -> N4 | W147: =COUNTIF(Template!$M$3:$M$619,Template!$D147) -> 0 | X147: =IF(Template!$F147="","",SUMIF(Template!$M$3:$M$619,Template!$D147,Template!$AC$3:$AC$619)) | Y147: =IFERROR(VLOOKUP(Template!$M147,Template!$D$3:$G$619,MATCH("EmployeeJobTitle",Template!$D$2:$G$2,0),FALSE),"NA") -> GERENTE DE LOJA | Z147: =IFERROR(VLOOKUP(Template!$M147,Template!$D$3:$G$619,MATCH("EmployeeGroup",Template!$D$2:$G$2,0),FALSE),"NA") -> GERENTE | AA147: =IFERROR(VLOOKUP(Template!$M147,Template!$D$3:$V$619,MATCH("Layer",Template!$D$2:$V$2,0),FALSE),"NA") -> N3 | AB147: =VLOOKUP(Template!$M147,Template!$D$3:$F$619,MATCH("InternalGrade",Template!$D$2:$F$2,0),FALSE)-Template!$F147 -> 0 | AC147: =IF(Template!$AB147<=1, 0.8,IF(Template!$AB147=2,0.4,IF(Template!$AB147=3,0.2,IF(Template!$AB147=4,0.1,IF(Template!$AB147>=5,0.05,"erro"))))) -> 0.8 | AD147: =Template!$D147=Template!$M147 -> FALSE | AE147: ab28b61c-af05-49c5-9d7a-0a76ad62ccfc
A148: LOJA | B148: REGIONAL RIO DE JANEIRO | C148: RIO DE JANEIRO-R | D148: 25410 | E148: CAIXA I | G148: Operacionais / Profissionais | H148: RJ | I148: RIO DE JANEIRO | J148: Feminino | K148: 45566 | L148: 28614 | M148: 16949 | N148: 1780 | P148: 13.33 | U148: =SUM(Template!$N148:$O148)*Template!$P148+Template!$Q148 -> 23727.4 | V148: =IF(Template!$M148="CONSELHO","N",IF(Template!$AA148="N","N1",IF(Template!$AA148="N1","N2",IF(Template!$AA148="N2","N3",IF(Template!$AA148="N3","N4",IF(Template!$AA148="N4","N5",IF(Template!$AA148="N5","N6",IF(Template!$AA148="N6","N7",IF(Template!$AA148="N7","N8",IF(Template!$AA148="N8","N9",IF(Template!$AA148="N9","N10","NA"))))))))))) -> N4 | W148: =COUNTIF(Template!$M$3:$M$619,Template!$D148) -> 0 | X148: =IF(Template!$F148="","",SUMIF(Template!$M$3:$M$619,Template!$D148,Template!$AC$3:$AC$619)) | Y148: =IFERROR(VLOOKUP(Template!$M148,Template!$D$3:$G$619,MATCH("EmployeeJobTitle",Template!$D$2:$G$2,0),FALSE),"NA") -> GERENTE DE LOJA | Z148: =IFERROR(VLOOKUP(Template!$M148,Template!$D$3:$G$619,MATCH("EmployeeGroup",Template!$D$2:$G$2,0),FALSE),"NA") -> GERENTE | AA148: =IFERROR(VLOOKUP(Template!$M148,Template!$D$3:$V$619,MATCH("Layer",Template!$D$2:$V$2,0),FALSE),"NA") -> N3 | AB148: =VLOOKUP(Template!$M148,Template!$D$3:$F$619,MATCH("InternalGrade",Template!$D$2:$F$2,0),FALSE)-Template!$F148 -> 0 | AC148: =IF(Template!$AB148<=1, 0.8,IF(Template!$AB148=2,0.4,IF(Template!$AB148=3,0.2,IF(Template!$AB148=4,0.1,IF(Template!$AB148>=5,0.05,"erro"))))) -> 0.8 | AD148: =Template!$D148=Template!$M148 -> FALSE | AE148: ab28b61c-af05-49c5-9d7a-0a76ad62ccfc
A149: LOJA | B149: REGIONAL RIO DE JANEIRO | C149: RIO DE JANEIRO-R | D149: 24397 | E149: APRENDIZ | G149: Operacionais / Profissionais | H149: RJ | I149: RIO DE JANEIRO | J149: Feminino | K149: 45219 | L149: 38426 | M149: 16949 | N149: 995.08 | P149: 13.33 | U149: =SUM(Template!$N149:$O149)*Template!$P149+Template!$Q149 -> 13264.416 | V149: =IF(Template!$M149="CONSELHO","N",IF(Template!$AA149="N","N1",IF(Template!$AA149="N1","N2",IF(Template!$AA149="N2","N3",IF(Template!$AA149="N3","N4",IF(Template!$AA149="N4","N5",IF(Template!$AA149="N5","N6",IF(Template!$AA149="N6","N7",IF(Template!$AA149="N7","N8",IF(Template!$AA149="N8","N9",IF(Template!$AA149="N9","N10","NA"))))))))))) -> N4 | W149: =COUNTIF(Template!$M$3:$M$619,Template!$D149) -> 0 | X149: =IF(Template!$F149="","",SUMIF(Template!$M$3:$M$619,Template!$D149,Template!$AC$3:$AC$619)) | Y149: =IFERROR(VLOOKUP(Template!$M149,Template!$D$3:$G$619,MATCH("EmployeeJobTitle",Template!$D$2:$G$2,0),FALSE),"NA") -> GERENTE DE LOJA | Z149: =IFERROR(VLOOKUP(Template!$M149,Template!$D$3:$G$619,MATCH("EmployeeGroup",Template!$D$2:$G$2,0),FALSE),"NA") -> GERENTE | AA149: =IFERROR(VLOOKUP(Template!$M149,Template!$D$3:$V$619,MATCH("Layer",Template!$D$2:$V$2,0),FALSE),"NA") -> N3 | AB149: =VLOOKUP(Template!$M149,Template!$D$3:$F$619,MATCH("InternalGrade",Template!$D$2:$F$2,0),FALSE)-Template!$F149 -> 0 | AC149: =IF(Template!$AB149<=1, 0.8,IF(Template!$AB149=2,0.4,IF(Template!$AB149=3,0.2,IF(Template!$AB149=4,0.1,IF(Template!$AB149>=5,0.05,"erro"))))) -> 0.8 | AD149: =Template!$D149=Template!$M149 -> FALSE | AE149: ab28b61c-af05-49c5-9d7a-0a76ad62ccfc
A150: LOJA | B150: REGIONAL RIO DE JANEIRO | C150: RIO DE JANEIRO-B | D150: 20527 | E150: AUXILIAR DE LOJA LÍDER DE VM | G150: Operacionais / Profissionais | H150: RJ | I150: RIO DE JANEIRO | J150: Feminino | K150: 44683 | L150: 32576 | M150: 25270 | N150: 1565 | P150: 13.33 | U150: =SUM(Template!$N150:$O150)*Template!$P150+Template!$Q150 -> 20861.45 | V150: =IF(Template!$M150="CONSELHO","N",IF(Template!$AA150="N","N1",IF(Template!$AA150="N1","N2",IF(Template!$AA150="N2","N3",IF(Template!$AA150="N3","N4",IF(Template!$AA150="N4","N5",IF(Template!$AA150="N5","N6",IF(Template!$AA150="N6","N7",IF(Template!$AA150="N7","N8",IF(Template!$AA150="N8","N9",IF(Template!$AA150="N9","N10","NA"))))))))))) -> N4 | W150: =COUNTIF(Template!$M$3:$M$619,Template!$D150) -> 0 | X150: =IF(Template!$F150="","",SUMIF(Template!$M$3:$M$619,Template!$D150,Template!$AC$3:$AC$619)) | Y150: =IFERROR(VLOOKUP(Template!$M150,Template!$D$3:$G$619,MATCH("EmployeeJobTitle",Template!$D$2:$G$2,0),FALSE),"NA") -> GERENTE DE LOJA SR | Z150: =IFERROR(VLOOKUP(Template!$M150,Template!$D$3:$G$619,MATCH("EmployeeGroup",Template!$D$2:$G$2,0),FALSE),"NA") -> GERENTE | AA150: =IFERROR(VLOOKUP(Template!$M150,Template!$D$3:$V$619,MATCH("Layer",Template!$D$2:$V$2,0),FALSE),"NA") -> N3 | AB150: =VLOOKUP(Template!$M150,Template!$D$3:$F$619,MATCH("InternalGrade",Template!$D$2:$F$2,0),FALSE)-Template!$F150 -> 0 | AC150: =IF(Template!$AB150<=1, 0.8,IF(Template!$AB150=2,0.4,IF(Template!$AB150=3,0.2,IF(Template!$AB150=4,0.1,IF(Template!$AB150>=5,0.05,"erro"))))) -> 0.8 | AD150: =Template!$D150=Template!$M150 -> FALSE | AE150: ab28b61c-af05-49c5-9d7a-0a76ad62ccfc
A151: LOJA | B151: REGIONAL RIO DE JANEIRO | C151: RIO DE JANEIRO-B | D151: 22512 | E151: VENDEDOR I | G151: Operacionais / Profissionais | H151: RJ | I151: RIO DE JANEIRO | J151: Feminino | K151: 44882 | L151: 26997 | M151: 25270 | P151: 13.33 | U151: =SUM(Template!$N151:$O151)*Template!$P151+Template!$Q151 -> 0 | V151: =IF(Template!$M151="CONSELHO","N",IF(Template!$AA151="N","N1",IF(Template!$AA151="N1","N2",IF(Template!$AA151="N2","N3",IF(Template!$AA151="N3","N4",IF(Template!$AA151="N4","N5",IF(Template!$AA151="N5","N6",IF(Template!$AA151="N6","N7",IF(Template!$AA151="N7","N8",IF(Template!$AA151="N8","N9",IF(Template!$AA151="N9","N10","NA"))))))))))) -> N4 | W151: =COUNTIF(Template!$M$3:$M$619,Template!$D151) -> 0 | X151: =IF(Template!$F151="","",SUMIF(Template!$M$3:$M$619,Template!$D151,Template!$AC$3:$AC$619)) | Y151: =IFERROR(VLOOKUP(Template!$M151,Template!$D$3:$G$619,MATCH("EmployeeJobTitle",Template!$D$2:$G$2,0),FALSE),"NA") -> GERENTE DE LOJA SR | Z151: =IFERROR(VLOOKUP(Template!$M151,Template!$D$3:$G$619,MATCH("EmployeeGroup",Template!$D$2:$G$2,0),FALSE),"NA") -> GERENTE | AA151: =IFERROR(VLOOKUP(Template!$M151,Template!$D$3:$V$619,MATCH("Layer",Template!$D$2:$V$2,0),FALSE),"NA") -> N3 | AB151: =VLOOKUP(Template!$M151,Template!$D$3:$F$619,MATCH("InternalGrade",Template!$D$2:$F$2,0),FALSE)-Template!$F151 -> 0 | AC151: =IF(Template!$AB151<=1, 0.8,IF(Template!$AB151=2,0.4,IF(Template!$AB151=3,0.2,IF(Template!$AB151=4,0.1,IF(Template!$AB151>=5,0.05,"erro"))))) -> 0.8 | AD151: =Template!$D151=Template!$M151 -> FALSE | AE151: ab28b61c-af05-49c5-9d7a-0a76ad62ccfc
A152: LOJA | B152: REGIONAL RIO DE JANEIRO | C152: RIO DE JANEIRO-B | D152: 22354 | E152: CAIXA I | G152: Operacionais / Profissionais | H152: RJ | I152: RIO DE JANEIRO | J152: Feminino | K152: 44866 | L152: 30651 | M152: 25270 | N152: 1936 | P152: 13.33 | U152: =SUM(Template!$N152:$O152)*Template!$P152+Template!$Q152 -> 25806.88 | V152: =IF(Template!$M152="CONSELHO","N",IF(Template!$AA152="N","N1",IF(Template!$AA152="N1","N2",IF(Template!$AA152="N2","N3",IF(Template!$AA152="N3","N4",IF(Template!$AA152="N4","N5",IF(Template!$AA152="N5","N6",IF(Template!$AA152="N6","N7",IF(Template!$AA152="N7","N8",IF(Template!$AA152="N8","N9",IF(Template!$AA152="N9","N10","NA"))))))))))) -> N4 | W152: =COUNTIF(Template!$M$3:$M$619,Template!$D152) -> 0 | X152: =IF(Template!$F152="","",SUMIF(Template!$M$3:$M$619,Template!$D152,Template!$AC$3:$AC$619)) | Y152: =IFERROR(VLOOKUP(Template!$M152,Template!$D$3:$G$619,MATCH("EmployeeJobTitle",Template!$D$2:$G$2,0),FALSE),"NA") -> GERENTE DE LOJA SR | Z152: =IFERROR(VLOOKUP(Template!$M152,Template!$D$3:$G$619,MATCH("EmployeeGroup",Template!$D$2:$G$2,0),FALSE),"NA") -> GERENTE | AA152: =IFERROR(VLOOKUP(Template!$M152,Template!$D$3:$V$619,MATCH("Layer",Template!$D$2:$V$2,0),FALSE),"NA") -> N3 | AB152: =VLOOKUP(Template!$M152,Template!$D$3:$F$619,MATCH("InternalGrade",Template!$D$2:$F$2,0),FALSE)-Template!$F152 -> 0 | AC152: =IF(Template!$AB152<=1, 0.8,IF(Template!$AB152=2,0.4,IF(Template!$AB152=3,0.2,IF(Template!$AB152=4,0.1,IF(Template!$AB152>=5,0.05,"erro"))))) -> 0.8 | AD152: =Template!$D152=Template!$M152 -> FALSE | AE152: ab28b61c-af05-49c5-9d7a-0a76ad62ccfc
A153: LOJA | B153: REGIONAL RIO DE JANEIRO | C153: RIO DE JANEIRO-B | D153: 17795 | E153: VENDEDOR RESPONSAVEL | G153: Operacionais / Profissionais | H153: RJ | I153: RIO DE JANEIRO | J153: Feminino | K153: 43678 | L153: 32281 | M153: 25270 | P153: 13.33 | U153: =SUM(Template!$N153:$O153)*Template!$P153+Template!$Q153 -> 0 | V153: =IF(Template!$M153="CONSELHO","N",IF(Template!$AA153="N","N1",IF(Template!$AA153="N1","N2",IF(Template!$AA153="N2","N3",IF(Template!$AA153="N3","N4",IF(Template!$AA153="N4","N5",IF(Template!$AA153="N5","N6",IF(Template!$AA153="N6","N7",IF(Template!$AA153="N7","N8",IF(Template!$AA153="N8","N9",IF(Template!$AA153="N9","N10","NA"))))))))))) -> N4 | W153: =COUNTIF(Template!$M$3:$M$619,Template!$D153) -> 0 | X153: =IF(Template!$F153="","",SUMIF(Template!$M$3:$M$619,Template!$D153,Template!$AC$3:$AC$619)) | Y153: =IFERROR(VLOOKUP(Template!$M153,Template!$D$3:$G$619,MATCH("EmployeeJobTitle",Template!$D$2:$G$2,0),FALSE),"NA") -> GERENTE DE LOJA SR | Z153: =IFERROR(VLOOKUP(Template!$M153,Template!$D$3:$G$619,MATCH("EmployeeGroup",Template!$D$2:$G$2,0),FALSE),"NA") -> GERENTE | AA153: =IFERROR(VLOOKUP(Template!$M153,Template!$D$3:$V$619,MATCH("Layer",Template!$D$2:$V$2,0),FALSE),"NA") -> N3 | AB153: =VLOOKUP(Template!$M153,Template!$D$3:$F$619,MATCH("InternalGrade",Template!$D$2:$F$2,0),FALSE)-Template!$F153 -> 0 | AC153: =IF(Template!$AB153<=1, 0.8,IF(Template!$AB153=2,0.4,IF(Template!$AB153=3,0.2,IF(Template!$AB153=4,0.1,IF(Template!$AB153>=5,0.05,"erro"))))) -> 0.8 | AD153: =Template!$D153=Template!$M153 -> FALSE | AE153: ab28b61c-af05-49c5-9d7a-0a76ad62ccfc
...
